Workbook
Name MesesEnTotal: DATEDIF(MesesEnTotal,TODAY(),"m")

Sheet Plantilla
A2: Departamento : | B2: D1
A3: Propietario : | B3: =LOOKUP(B2,#REF!,#REF!) -> #REF!
A4: Inquilino : | B4: =LOOKUP(B2,#REF!,#REF!) -> #REF!
A5: Teléfono : | B5: =LOOKUP(B2,#REF!,#REF!) -> #REF!
A6: Celular : | B6: =LOOKUP(B2,#REF!,#REF!) -> #REF!
A7: Correo : | B7: =LOOKUP(B2,#REF!,#REF!) -> #REF! | H7: Resumen
A9: Fecha | B9: Concepto | C9: Recibo | D9: Expensas | E9: Agua | F9: Column6 | G9: Total | H9: Deuda
A10: 42674 | B10: Saldo deudor al 31/10/2016 | F10: 0 | G10: =SUM(D10:F10) -> 0 | H10: =G10 -> 0
A11: 43032 | B11: Pago mantenimiento octubre/2016 | F11: 0 | G11: =SUM(D11:F11) -> 0 | H11: =H10+G11 -> 0
A12: 43069 | B12: Mantenimiento noviembre/2016 | F12: 0 | G12: =SUM(D12:F12) -> 0 | H12: =H11+G12 -> 0
A13: 42711 | B13: Pago mantenimiento noviembre/2016 | F13: 0 | G13: =SUM(D13:F13) -> 0 | H13: =H12+G13 -> 0
A14: 42735 | B14: Mantenimiento diciembre/2016 | F14: 0 | G14: =SUM(D14:F14) -> 0 | H14: =H13+G14 -> 0
A15: 42740 | B15: Pago mantenimiento diciembre/2016 | F15: 0 | G15: =SUM(D15:F15) -> 0 | H15: =H14+G15 -> 0
A16: 42766 | B16: Mantenimiento enero/2017 | F16: 0 | G16: =SUM(D16:F16) -> 0 | H16: =H15+G16 -> 0
A17: 42773 | B17: Pago mantenimiento enero/2017 | F17: 0 | G17: =SUM(D17:F17) -> 0 | H17: =H16+G17 -> 0
A18: 42794 | B18: Mantenimiento febrero/2017 | F18: 0 | G18: =SUM(D18:F18) -> 0 | H18: =H17+G18 -> 0
A19: 04/0372017 | B19: Pago mantenimiento febrero/2017 | F19: 0 | G19: =SUM(D19:F19) -> 0 | H19: =H18+G19 -> 0
A20: 42825 | B20: Mantenimiento marzo/2017 | G20: =SUM(D20:F20) -> 0 | H20: =H19+G20 -> 0
A21: 42835 | B21: Pago mantenimiento marzo/2017 | F21: 0 | G21: =SUM(D21:F21) -> 0 | H21: =H20+G21 -> 0
A22: 42855 | B22: Mantenimiento abril/2017 | G22: =SUM(D22:F22) -> 0 | H22: =H21+G22 -> 0
A23: 42860 | B23: Pago mantenimiento abril/2017 | F23: 0 | G23: =SUM(D23:F23) -> 0 | H23: =H22+G23 -> 0
A24: 42886 | B24: Mantenimiento mayo/2017 | G24: =SUM(D24:F24) -> 0 | H24: =H23+G24 -> 0
A25: 42892 | B25: Pago mantenimiento mayo/2017 | G25: =SUM(D25:F25) -> 0 | H25: =H24+G25 -> 0
A26: 42916 | B26: Mantenimiento junio/2017 | G26: =SUM(D26:F26) -> 0 | H26: =H25+G26 -> 0
B27: Pago mantenimiento junio/2017 | G27: =SUM(D27:F27) -> 0 | H27: =H26+G27 -> 0
A28: 42947 | B28: Mantenimiento julio/2017 | G28: =SUM(D28:F28) -> 0 | H28: =H27+G28 -> 0
B29: Pago mantenimiento julio/2017 | G29: =SUM(D29:F29) -> 0 | H29: =H28+G29 -> 0
A30: 42978 | B30: Mantenimiento agosto/2017 | G30: =SUM(D30:F30) -> 0 | H30: =H29+G30 -> 0
B31: Pago mantenimiento agosto/2017 | G31: =SUM(D31:F31) -> 0 | H31: =H30+G31 -> 0
A32: 43008 | B32: Mantenimiento septiembre/2017 | G32: =SUM(D32:F32) -> 0 | H32: =H31+G32 -> 0
B33: Pago mantenimiento septiembre/2017 | G33: =SUM(D33:F33) -> 0 | H33: =H32+G33 -> 0
A34: 43039 | B34: Mantenimiento octubre/2017 | G34: =SUM(D34:F34) -> 0 | H34: =H33+G34 -> 0
B35: Pago mantenimiento octubre/2017 | G35: =SUM(D35:F35) -> 0 | H35: =H34+G35 -> 0
A36: 43069 | B36: Mantenimiento noviembre/2017 | G36: =SUM(D36:F36) -> 0 | H36: =H35+G36 -> 0
B37: Pago mantenimiento noviembre/2017 | G37: =SUM(D37:F37) -> 0 | H37: =H36+G37 -> 0
A38: 43100 | B38: Mantenimiento diciembre/2017 | G38: =SUM(D38:F38) -> 0 | H38: =H37+G38 -> 0
B39: Pago mantenimiento diciembre/2017 | G39: =SUM(D39:F39) -> 0 | H39: =H38+G39 -> 0

Sheet LOCAL 01
A2: Departamento : | B2: LOCAL 01
A3: Propietario : | B3: =LOOKUP(B2,#REF!,#REF!) -> #REF!
A4: Inquilino : | B4: =LOOKUP(B2,#REF!,#REF!) -> #REF!
A5: Teléfono : | B5: =LOOKUP(B2,#REF!,#REF!) -> #REF!
A6: Celular : | B6: =LOOKUP(B2,#REF!,#REF!) -> #REF!
A7: Correo : | B7: =LOOKUP(B2,#REF!,#REF!) -> #REF! | H7: Resumen
A8: Inquilino ACTUAL:
A9: Fecha | B9: Concepto | C9: Recibo | D9: Expensas | E9: Agua | F9: Multa | G9: Total | H9: Deuda | I9: Pagado | J9: Columna1 | K9: Columna2
G10: =SUM(D10:F48) -> 117 | H10: 0 | I10: =IF(T_T134[[#This Row],[Total]]<0,T_T134[[#This Row],[Total]]*-1,0) -> 0
A11: 46052 | B11: Mantenimiento enero/2026 | D11: 90 | E11: 3 | G11: =+T_T134[[#This Row],[Expensas]]+T_T134[[#This Row],[Agua]]+T_T134[[#This Row],[Multa]] -> 93 | H11: =+H10+T_T134[[#This Row],[Total]] -> 93 | I11: =IF(T_T134[[#This Row],[Total]]<0,T_T134[[#This Row],[Total]]*-1,0) -> 0
B12: Pago mantenimiento enero/2026 | C12: 8525-8892 | D12: =-26-64 -> -90 | E12: -3 | G12: =SUM(D12:F12) -> -93 | H12: =+H11+T_T134[[#This Row],[Total]] -> 0 | I12: =IF(T_T134[[#This Row],[Total]]<0,T_T134[[#This Row],[Total]]*-1,0) -> 93
A13: 45715 | B13: Mantenimiento febrero/2025 | D13: 90 | E13: 5 | G13: =SUM(D13:F13) -> 95 | H13: =+H12+T_T134[[#This Row],[Total]] -> 95 | I13: =IF(T_T134[[#This Row],[Total]]<0,T_T134[[#This Row],[Total]]*-1,0) -> 0
B14: Pago mantenimiento febrero/2025 | C14: 8893-8892 | D14: =-64-26 -> -90 | E14: -5 | G14: =SUM(D14:F14) -> -95 | H14: =+H13+T_T134[[#This Row],[Total]] -> 0 | I14: =IF(T_T134[[#This Row],[Total]]<0,T_T134[[#This Row],[Total]]*-1,0) -> 95
A15: 45747 | B15: Mantenimiento marzo/2025 | D15: 107 | E15: 5 | G15: =SUM(D15:F15) -> 112 | H15: =+H14+T_T134[[#This Row],[Total]] -> 112 | I15: =IF(T_T134[[#This Row],[Total]]<0,T_T134[[#This Row],[Total]]*-1,0) -> 0
B16: Pago matenimiento marzo/2025 | C16: 8892-8893 | D16: =-77-30 -> -107 | E16: -5 | G16: =SUM(D16:F16) -> -112 | H16: =+H15+T_T134[[#This Row],[Total]] -> 0 | I16: =IF(T_T134[[#This Row],[Total]]<0,T_T134[[#This Row],[Total]]*-1,0) -> 112
A17: 45777 | B17: Mantenimiento abril/2025 | D17: 107 | E17: 10 | G17: =SUM(D17:F17) -> 117 | H17: =+H16+T_T134[[#This Row],[Total]] -> 117 | I17: =IF(T_T134[[#This Row],[Total]]<0,T_T134[[#This Row],[Total]]*-1,0) -> 0
B18: Pago mantenimiento abril/2025 | C18: 8893-8895 | D18: =-30-77 -> -107 | E18: -10 | G18: =SUM(D18:F18) -> -117 | H18: =+H17+T_T134[[#This Row],[Total]] -> 0 | I18: =IF(T_T134[[#This Row],[Total]]<0,T_T134[[#This Row],[Total]]*-1,0) -> 117
A19: 45807 | B19: Mantenimiento mayo/2025 | D19: 107 | E19: 10 | G19: =SUM(D19:F19) -> 117 | H19: =+H18+T_T134[[#This Row],[Total]] -> 117 | I19: =IF(T_T134[[#This Row],[Total]]<0,T_T134[[#This Row],[Total]]*-1,0) -> 0
B20: Pago mantenimiento mayo/2025 | G20: =SUM(D20:F20) -> 0 | H20: =+H19+T_T134[[#This Row],[Total]] -> 117 | I20: =IF(T_T134[[#This Row],[Total]]<0,T_T134[[#This Row],[Total]]*-1,0) -> 0
A21: 45838 | B21: Mantenimiento junio/2025 | G21: =SUM(D21:F21) -> 0 | H21: =+H20+T_T134[[#This Row],[Total]] -> 117 | I21: =IF(T_T134[[#This Row],[Total]]<0,T_T134[[#This Row],[Total]]*-1,0) -> 0
B22: Pago mantenimiento junio/2025 | G22: =SUM(D22:F22) -> 0 | H22: =+H21+T_T134[[#This Row],[Total]] -> 117 | I22: =IF(T_T134[[#This Row],[Total]]<0,T_T134[[#This Row],[Total]]*-1,0) -> 0
A23: 45868 | B23: Mantenimiento julio/2025 | G23: =SUM(D23:F23) -> 0 | H23: =+H22+T_T134[[#This Row],[Total]] -> 117 | I23: =IF(T_T134[[#This Row],[Total]]<0,T_T134[[#This Row],[Total]]*-1,0) -> 0
B24: Pago mantenimient julio/2025 | G24: =SUM(D24:F24) -> 0 | H24: =+H23+T_T134[[#This Row],[Total]] -> 117 | I24: =IF(T_T134[[#This Row],[Total]]<0,T_T134[[#This Row],[Total]]*-1,0) -> 0
A25: 45899 | B25: Mantenimiento agosto/2025 | G25: =SUM(D25:F25) -> 0 | H25: =H24+G25 -> 117 | I25: =IF(T_T134[[#This Row],[Total]]<0,T_T134[[#This Row],[Total]]*-1,0) -> 0
B26: Pago mantenimiento agosto/2025 | G26: =SUM(D26:F26) -> 0 | H26: =H25+G26 -> 117 | I26: =IF(T_T134[[#This Row],[Total]]<0,T_T134[[#This Row],[Total]]*-1,0) -> 0
A27: 45930 | B27: Mantenimiento septiembre/2025 | G27: =SUM(D27:F27) -> 0 | H27: =H26+G27 -> 117 | I27: =IF(T_T134[[#This Row],[Total]]<0,T_T134[[#This Row],[Total]]*-1,0) -> 0
B28: Pago mantenimiento septiembre/2025 | G28: =SUM(D28:F28) -> 0 | H28: =H27+G28 -> 117 | I28: =IF(T_T134[[#This Row],[Total]]<0,T_T134[[#This Row],[Total]]*-1,0) -> 0
A29: 45960 | B29: Mantenimiento octubre /2025 | G29: =SUM(D29:F29) -> 0 | H29: =H28+G29 -> 117 | I29: =IF(T_T134[[#This Row],[Total]]<0,T_T134[[#This Row],[Total]]*-1,0) -> 0
B30: Pago mantenimiento octubre/2025 | G30: =SUM(D30:F30) -> 0 | H30: =H29+G30 -> 117 | I30: =IF(T_T134[[#This Row],[Total]]<0,T_T134[[#This Row],[Total]]*-1,0) -> 0
A31: 45991 | B31: Mantenimiento noviembre/2025 | G31: =SUM(D31:F31) -> 0 | H31: =H30+G31 -> 117 | I31: =IF(T_T134[[#This Row],[Total]]<0,T_T134[[#This Row],[Total]]*-1,0) -> 0
B32: Pago mantenimiento noviembre/2025 | G32: =SUM(D32:F32) -> 0 | H32: =H31+G32 -> 117 | I32: =IF(T_T134[[#This Row],[Total]]<0,T_T134[[#This Row],[Total]]*-1,0) -> 0
A33: 46021 | B33: Mantenimiento diciembre/2025 | G33: =SUM(D33:F33) -> 0 | H33: =H32+G33 -> 117 | I33: =IF(T_T134[[#This Row],[Total]]<0,T_T134[[#This Row],[Total]]*-1,0) -> 0
B34: Pago de Mantenimiento diciembre/2025 | G34: =SUM(D34:F34) -> 0 | H34: =H33+G34 -> 117 | I34: =IF(T_T134[[#This Row],[Total]]<0,T_T134[[#This Row],[Total]]*-1,0) -> 0
G35: =SUM(D35:F42) -> 0 | H35: =H34+G35 -> 117 | I35: =IF(T_T134[[#This Row],[Total]]<0,T_T134[[#This Row],[Total]]*-1,0) -> 0
G36: =SUM(D36:F43) -> 0 | H36: =H35+G36 -> 117 | I36: =IF(T_T134[[#This Row],[Total]]<0,T_T134[[#This Row],[Total]]*-1,0) -> 0
G37: =SUM(D37:F44) -> 0 | H37: =H36+G37 -> 117 | I37: =IF(T_T134[[#This Row],[Total]]<0,T_T134[[#This Row],[Total]]*-1,0) -> 0
G38: =SUM(D38:F45) -> 0 | H38: =H37+G38 -> 117 | I38: =IF(T_T134[[#This Row],[Total]]<0,T_T134[[#This Row],[Total]]*-1,0) -> 0
G39: =SUM(D39:F45) -> 0 | H39: =H38+G39 -> 117 | I39: =IF(T_T134[[#This Row],[Total]]<0,T_T134[[#This Row],[Total]]*-1,0) -> 0
G40: =SUM(D40:F45) -> 0 | H40: =H39+G40 -> 117 | I40: =IF(T_T134[[#This Row],[Total]]<0,T_T134[[#This Row],[Total]]*-1,0) -> 0
G41: =SUM(D41:F45) -> 0 | H41: =H40+G41 -> 117 | I41: =IF(T_T134[[#This Row],[Total]]<0,T_T134[[#This Row],[Total]]*-1,0) -> 0
G42: =SUM(D42:F45) -> 0 | H42: =H41+G42 -> 117 | I42: =IF(T_T134[[#This Row],[Total]]<0,T_T134[[#This Row],[Total]]*-1,0) -> 0
G43: =SUM(D43:F45) -> 0 | H43: =H42+G43 -> 117 | I43: =IF(T_T134[[#This Row],[Total]]<0,T_T134[[#This Row],[Total]]*-1,0) -> 0
G44: =SUM(D44:F45) -> 0 | H44: =H43+G44 -> 117 | I44: =IF(T_T134[[#This Row],[Total]]<0,T_T134[[#This Row],[Total]]*-1,0) -> 0
G45: =SUM(D45:F45) -> 0 | H45: =H44+G45 -> 117 | I45: =IF(T_T134[[#This Row],[Total]]<0,T_T134[[#This Row],[Total]]*-1,0) -> 0

Sheet LOCAL 02
A2: Departamento : | B2: LOCAL 02
A3: Propietario : | B3: SR. JOSE ORGAZ
A4: Inquilino : | B4: =LOOKUP(B2,#REF!,#REF!) -> #REF!
A5: Teléfono : | B5: =LOOKUP(B2,#REF!,#REF!) -> #REF!
A6: Celular : | B6: =LOOKUP(B2,#REF!,#REF!) -> #REF!
A7: Inquilino : | H7: Resumen
A9: Fecha | B9: Concepto | C9: Recibo | D9: Expensas | E9: Agua | F9: Multa | G9: Total | H9: Deuda | I9: Pagado
A11: 46052 | B11: Mantenimiento enero/2026 | D11: 70 | E11: 13 | G11: =SUM(D11:F11) -> 83 | H11: =+H10+T_T134144[[#This Row],[Total]] -> 83 | I11: =IF(T_T134144[[#This Row],[Total]]<0,T_T134144[[#This Row],[Total]]*-1,0) -> 0 | O11: 240
B12: Pago mantenimiento enero/2026 | G12: =SUM(D12:F12) -> 0 | H12: =+H11+T_T134144[[#This Row],[Total]] -> 83 | I12: =IF(T_T134144[[#This Row],[Total]]<0,T_T134144[[#This Row],[Total]]*-1,0) -> 0 | O12: 324
A13: 45715 | B13: Mantenimiento febrero/2026 | D13: 70 | E13: 13 | G13: =SUM(D13:F13) -> 83 | H13: =H12+G13 -> 166 | I13: =IF(T_T134144[[#This Row],[Total]]<0,T_T134144[[#This Row],[Total]]*-1,0) -> 0 | O13: =SUM(O11:O12) -> 564
B14: Pago mantenimiento febrero/2025 | G14: =SUM(D14:F14) -> 0 | H14: =H13+G14 -> 166 | I14: =IF(T_T134144[[#This Row],[Total]]<0,T_T134144[[#This Row],[Total]]*-1,0) -> 0
A15: 45747 | B15: Mantenimiento marzo/2025 | D15: 84 | E15: 13 | G15: =SUM(D15:F15) -> 97 | H15: =H14+G15 -> 263 | I15: =IF(T_T134144[[#This Row],[Total]]<0,T_T134144[[#This Row],[Total]]*-1,0) -> 0
B16: Pago matenimiento marzo/2025 | G16: =SUM(D16:F16) -> 0 | H16: =H15+G16 -> 263 | I16: =IF(T_T134144[[#This Row],[Total]]<0,T_T134144[[#This Row],[Total]]*-1,0) -> 0
A17: 45777 | B17: Mantenimiento abril/2025 | D17: 84 | E17: 13 | G17: =SUM(D17:F17) -> 97 | H17: =H16+G17 -> 360 | I17: =IF(T_T134144[[#This Row],[Total]]<0,T_T134144[[#This Row],[Total]]*-1,0) -> 0
B18: Pago mantenimiento abril/2025 | G18: =SUM(D18:F18) -> 0 | H18: =H17+G18 -> 360 | I18: =IF(T_T134144[[#This Row],[Total]]<0,T_T134144[[#This Row],[Total]]*-1,0) -> 0
A19: 45807 | B19: Mantenimiento mayo/2025 | D19: 84 | E19: 13 | G19: =SUM(D19:F19) -> 97 | H19: =H18+G19 -> 457 | I19: =IF(T_T134144[[#This Row],[Total]]<0,T_T134144[[#This Row],[Total]]*-1,0) -> 0
B20: Pago mantenimiento mayo/2025 | G20: =SUM(D20:F20) -> 0 | H20: =H19+G20 -> 457 | I20: =IF(T_T134144[[#This Row],[Total]]<0,T_T134144[[#This Row],[Total]]*-1,0) -> 0
A21: 45838 | B21: Mantenimiento junio/2025 | G21: =SUM(D21:F21) -> 0 | H21: =H20+G21 -> 457 | I21: =IF(T_T134144[[#This Row],[Total]]<0,T_T134144[[#This Row],[Total]]*-1,0) -> 0
B22: Pago mantenimiento junio/2025 | G22: =SUM(D22:F22) -> 0 | H22: =H21+G22 -> 457 | I22: =IF(T_T134144[[#This Row],[Total]]<0,T_T134144[[#This Row],[Total]]*-1,0) -> 0
A23: 45868 | B23: Mantenimiento julio/2025 | G23: =SUM(D23:F23) -> 0 | H23: =H22+G23 -> 457 | I23: =IF(T_T134144[[#This Row],[Total]]<0,T_T134144[[#This Row],[Total]]*-1,0) -> 0
B24: Pago mantenimient julio/2025 | G24: =SUM(D24:F24) -> 0 | H24: =H23+G24 -> 457 | I24: =IF(T_T134144[[#This Row],[Total]]<0,T_T134144[[#This Row],[Total]]*-1,0) -> 0
A25: 45899 | B25: Mantenimiento agosto/2025 | G25: =SUM(D25:F25) -> 0 | H25: =H24+G25 -> 457 | I25: =IF(T_T134144[[#This Row],[Total]]<0,T_T134144[[#This Row],[Total]]*-1,0) -> 0
B26: Pago mantenimiento agosto/2025 | G26: =SUM(D26:F26) -> 0 | H26: =H25+G26 -> 457 | I26: =IF(T_T134144[[#This Row],[Total]]<0,T_T134144[[#This Row],[Total]]*-1,0) -> 0
A27: 45930 | B27: Mantenimiento septiembre/2025 | G27: =SUM(D27:F27) -> 0 | H27: =H26+G27 -> 457 | I27: =IF(T_T134144[[#This Row],[Total]]<0,T_T134144[[#This Row],[Total]]*-1,0) -> 0
B28: Pago mantenimiento septiembre/2025 | G28: =SUM(D28:F28) -> 0 | H28: =H27+G28 -> 457 | I28: =IF(T_T134144[[#This Row],[Total]]<0,T_T134144[[#This Row],[Total]]*-1,0) -> 0
A29: 45960 | B29: Mantenimiento octubre /2025 | G29: =SUM(D29:F29) -> 0 | H29: =H28+G29 -> 457 | I29: =IF(T_T134144[[#This Row],[Total]]<0,T_T134144[[#This Row],[Total]]*-1,0) -> 0
B30: Pago mantenimiento octubre/2025 | G30: =SUM(D30:F30) -> 0 | H30: =H29+G30 -> 457 | I30: =IF(T_T134144[[#This Row],[Total]]<0,T_T134144[[#This Row],[Total]]*-1,0) -> 0
A31: 45991 | B31: Mantenimiento noviembre/2025 | G31: =SUM(D31:F31) -> 0 | H31: =H30+G31 -> 457 | I31: =IF(T_T134144[[#This Row],[Total]]<0,T_T134144[[#This Row],[Total]]*-1,0) -> 0
B32: Pago mantenimiento noviembre/2025 | G32: =SUM(D32:F32) -> 0 | H32: =H31+G32 -> 457 | I32: =IF(T_T134144[[#This Row],[Total]]<0,T_T134144[[#This Row],[Total]]*-1,0) -> 0
A33: 46021 | B33: Mantenimiento diciembre/2025 | G33: =SUM(D33:F33) -> 0 | H33: =H32+G33 -> 457 | I33: =IF(T_T134144[[#This Row],[Total]]<0,T_T134144[[#This Row],[Total]]*-1,0) -> 0
B34: Pago de Mantenimiento diciembre/2025 | G34: =SUM(D34:F34) -> 0 | H34: =H33+G34 -> 457 | I34: =IF(T_T134144[[#This Row],[Total]]<0,T_T134144[[#This Row],[Total]]*-1,0) -> 0
G35: =SUM(D35:F42) -> 0 | H35: =H34+G35 -> 457 | I35: =IF(T_T134144[[#This Row],[Total]]<0,T_T134144[[#This Row],[Total]]*-1,0) -> 0
G36: =SUM(D36:F43) -> 0 | H36: =H35+G36 -> 457 | I36: =IF(T_T134144[[#This Row],[Total]]<0,T_T134144[[#This Row],[Total]]*-1,0) -> 0
G37: =SUM(D37:F37) -> 0 | H37: =H36+G37 -> 457 | I37: =IF(T_T134144[[#This Row],[Total]]<0,T_T134144[[#This Row],[Total]]*-1,0) -> 0
G38: =SUM(D38:F38) -> 0 | H38: =H37+G38 -> 457 | I38: =IF(T_T134144[[#This Row],[Total]]<0,T_T134144[[#This Row],[Total]]*-1,0) -> 0
G39: =SUM(D39:F39) -> 0 | H39: =H38+G39 -> 457 | I39: =IF(T_T134144[[#This Row],[Total]]<0,T_T134144[[#This Row],[Total]]*-1,0) -> 0
G40: =SUM(D40:F40) -> 0 | H40: =H39+G40 -> 457 | I40: =IF(T_T134144[[#This Row],[Total]]<0,T_T134144[[#This Row],[Total]]*-1,0) -> 0
G41: =SUM(D41:F41) -> 0 | H41: =H40+G41 -> 457 | I41: =IF(T_T134144[[#This Row],[Total]]<0,T_T134144[[#This Row],[Total]]*-1,0) -> 0

Sheet LOCAL 03
A2: Departamento : | B2: LOCAL 03
A3: Propietario : | B3: MERY FERNANDEZ
A4: Inquilino : | B4: =LOOKUP(B2,#REF!,#REF!) -> #REF!
A5: Teléfono : | B5: =LOOKUP(B2,#REF!,#REF!) -> #REF!
A6: Celular : | B6: =LOOKUP(B2,#REF!,#REF!) -> #REF!
A7: Inquilino : | B7: SIMCORT LTDA | H7: Resumen
A9: Fecha | B9: Concepto | C9: Recibo | D9: Expensas | E9: Agua | F9: Multa | G9: Total | H9: Deuda | I9: Pagado | J9: Columna1 | K9: Columna2 | L9: Columna3
B10: DEUDA GESTION 2017-2020 | H10: 0
B11: DEUDA GESTION 2021 | H11: 0 | I11: =IF(T_T134145[[#This Row],[Total]]<0,T_T134145[[#This Row],[Total]]*-1,0) -> 0
B12: DEUDA GESTION 2022 | H12: 0 | I12: =IF(T_T134145[[#This Row],[Total]]<0,T_T134145[[#This Row],[Total]]*-1,0) -> 0
B13: DEUDA GESTION 2023 | H13: 0 | I13: =IF(T_T134145[[#This Row],[Total]]<0,T_T134145[[#This Row],[Total]]*-1,0) -> 0
B14: DEUDA GESTION 2024 | I14: =IF(T_T134145[[#This Row],[Total]]<0,T_T134145[[#This Row],[Total]]*-1,0) -> 0
A15: 46052 | B15: Mantenimiento enero/2026 | D15: 102 | E15: 15 | G15: =SUM(D15:F15) -> 117 | H15: =+H13+T_T134145[[#This Row],[Total]] -> 117 | I15: =IF(T_T134145[[#This Row],[Total]]<0,T_T134145[[#This Row],[Total]]*-1,0) -> 0
B16: Pago mantenimiento enero/2026 | C16: 8645 | D16: -102 | E16: -15 | G16: =SUM(D16:F16) -> -117 | H16: =H15+G16 -> 0 | I16: =IF(T_T134145[[#This Row],[Total]]<0,T_T134145[[#This Row],[Total]]*-1,0) -> 117
A17: 45715 | B17: Mantenimiento febrero/2025 | D17: 102 | E17: 13 | G17: =SUM(D17:F17) -> 115 | H17: =H16+G17 -> 115 | I17: =IF(T_T134145[[#This Row],[Total]]<0,T_T134145[[#This Row],[Total]]*-1,0) -> 0
B18: Pago mantenimiento febrero/2025 | G18: =SUM(D18:F18) -> 0 | H18: =H17+G18 -> 115 | I18: =IF(T_T134145[[#This Row],[Total]]<0,T_T134145[[#This Row],[Total]]*-1,0) -> 0
A19: 45747 | B19: Mantenimiento marzo/2025 | D19: 122 | E19: 9 | G19: =SUM(D19:F19) -> 131 | H19: =H18+G19 -> 246 | I19: =IF(T_T134145[[#This Row],[Total]]<0,T_T134145[[#This Row],[Total]]*-1,0) -> 0
B20: Pago matenimiento marzo/2025 | G20: =SUM(D20:F20) -> 0 | H20: =H19+G20 -> 246 | I20: =IF(T_T134145[[#This Row],[Total]]<0,T_T134145[[#This Row],[Total]]*-1,0) -> 0
A21: 45777 | B21: Mantenimiento abril/2025 | D21: 122 | E21: 1 | G21: =SUM(D21:F21) -> 123 | H21: =H20+G21 -> 369 | I21: =IF(T_T134145[[#This Row],[Total]]<0,T_T134145[[#This Row],[Total]]*-1,0) -> 0
B22: Pago mantenimiento abril/2025 | G22: =SUM(D22:F22) -> 0 | H22: =H21+G22 -> 369 | I22: =IF(T_T134145[[#This Row],[Total]]<0,T_T134145[[#This Row],[Total]]*-1,0) -> 0
A23: 45807 | B23: Mantenimiento mayo/2025 | D23: 122 | E23: 8 | G23: =SUM(D23:F23) -> 130 | H23: =H22+G23 -> 499 | I23: =IF(T_T134145[[#This Row],[Total]]<0,T_T134145[[#This Row],[Total]]*-1,0) -> 0
B24: Pago mantenimiento mayo/2025 | G24: =SUM(D24:F24) -> 0 | H24: =H23+G24 -> 499 | I24: =IF(T_T134145[[#This Row],[Total]]<0,T_T134145[[#This Row],[Total]]*-1,0) -> 0
A25: 45838 | B25: Mantenimiento junio/2025 | G25: =SUM(D25:F25) -> 0 | H25: =H24+G25 -> 499 | I25: =IF(T_T134145[[#This Row],[Total]]<0,T_T134145[[#This Row],[Total]]*-1,0) -> 0
B26: Pago mantenimiento junio/2025 | G26: =SUM(D26:F26) -> 0 | H26: =H25+G26 -> 499 | I26: =IF(T_T134145[[#This Row],[Total]]<0,T_T134145[[#This Row],[Total]]*-1,0) -> 0
A27: 45868 | B27: Mantenimiento julio/2025 | G27: =SUM(D27:F27) -> 0 | H27: =H26+G27 -> 499 | I27: =IF(T_T134145[[#This Row],[Total]]<0,T_T134145[[#This Row],[Total]]*-1,0) -> 0
B28: Pago mantenimient julio/2025 | G28: =SUM(D28:F28) -> 0 | H28: =H27+G28 -> 499 | I28: =IF(T_T134145[[#This Row],[Total]]<0,T_T134145[[#This Row],[Total]]*-1,0) -> 0
A29: 45899 | B29: Mantenimiento agosto/2025 | G29: =SUM(D29:F29) -> 0 | H29: =H28+G29 -> 499 | I29: =IF(T_T134145[[#This Row],[Total]]<0,T_T134145[[#This Row],[Total]]*-1,0) -> 0
B30: Pago mantenimiento agosto/2025 | G30: =SUM(D30:F30) -> 0 | H30: =H29+G30 -> 499 | I30: =IF(T_T134145[[#This Row],[Total]]<0,T_T134145[[#This Row],[Total]]*-1,0) -> 0
A31: 45930 | B31: Mantenimiento septiembre/2025 | G31: =SUM(D31:F31) -> 0 | H31: =H30+G31 -> 499 | I31: =IF(T_T134145[[#This Row],[Total]]<0,T_T134145[[#This Row],[Total]]*-1,0) -> 0
B32: Pago mantenimiento septiembre/2025 | G32: =SUM(D32:F32) -> 0 | H32: =H31+G32 -> 499 | I32: =IF(T_T134145[[#This Row],[Total]]<0,T_T134145[[#This Row],[Total]]*-1,0) -> 0
A33: 45960 | B33: Mantenimiento octubre /2025 | G33: =SUM(D33:F33) -> 0 | H33: =H32+G33 -> 499 | I33: =IF(T_T134145[[#This Row],[Total]]<0,T_T134145[[#This Row],[Total]]*-1,0) -> 0
B34: Pago mantenimiento octubre/2025 | G34: =SUM(D34:F34) -> 0 | H34: =H33+G34 -> 499 | I34: =IF(T_T134145[[#This Row],[Total]]<0,T_T134145[[#This Row],[Total]]*-1,0) -> 0
A35: 45991 | B35: Mantenimiento noviembre/2025 | G35: =SUM(D35:F35) -> 0 | H35: =H34+G35 -> 499 | I35: =IF(T_T134145[[#This Row],[Total]]<0,T_T134145[[#This Row],[Total]]*-1,0) -> 0
B36: Pago mantenimiento noviembre/2025 | G36: =SUM(D36:F36) -> 0 | H36: =H35+G36 -> 499 | I36: =IF(T_T134145[[#This Row],[Total]]<0,T_T134145[[#This Row],[Total]]*-1,0) -> 0
A37: 46021 | B37: Mantenimiento diciembre/2025 | G37: =SUM(D37:F37) -> 0 | H37: =H36+G37 -> 499 | I37: =IF(T_T134145[[#This Row],[Total]]<0,T_T134145[[#This Row],[Total]]*-1,0) -> 0
B38: Pago de Mantenimiento diciembre/2025 | G38: =SUM(D38:F38) -> 0 | H38: =H37+G38 -> 499 | I38: =IF(T_T134145[[#This Row],[Total]]<0,T_T134145[[#This Row],[Total]]*-1,0) -> 0
G39: =SUM(D39:F46) -> 0 | H39: =H38+G39 -> 499 | I39: =IF(T_T134145[[#This Row],[Total]]<0,T_T134145[[#This Row],[Total]]*-1,0) -> 0
G40: =SUM(D40:F47) -> 0 | H40: =H39+G40 -> 499 | I40: =IF(T_T134145[[#This Row],[Total]]<0,T_T134145[[#This Row],[Total]]*-1,0) -> 0

Sheet LOCAL 04
A2: Departamento : | B2: LOCAL 04
A3: Propietario : | B3: PAULA BURGOS
A4: Inquilino : | B4: =LOOKUP(B2,#REF!,#REF!) -> #REF!
A5: Teléfono : | B5: =LOOKUP(B2,#REF!,#REF!) -> #REF!
A6: Celular : | B6: =LOOKUP(B2,#REF!,#REF!) -> #REF!
A7: Correo : | B7: =LOOKUP(B2,#REF!,#REF!) -> #REF! | H7: Resumen
A9: Fecha | B9: Concepto | C9: Recibo | D9: Expensas | E9: Agua | F9: Multa | G9: Total | H9: Deuda | I9: Pagado | J9: Columna1 | K9: Columna2 | L9: Columna3
B10: DEUDA GESTION 2017-2020 | H10: 0 | I10: =IF(T_T1343[[#This Row],[Total]]<0,T_T1343[[#This Row],[Total]]*-1,0) -> 0
B11: DEUDA GESTION 2021 | H11: 0 | I11: =IF(T_T1343[[#This Row],[Total]]<0,T_T1343[[#This Row],[Total]]*-1,0) -> 0
B12: DEUDA GESTION 2022 | H12: 0 | I12: =IF(T_T1343[[#This Row],[Total]]<0,T_T1343[[#This Row],[Total]]*-1,0) -> 0
B13: DEUDA GESTION 2023 | H13: 0 | I13: =IF(T_T1343[[#This Row],[Total]]<0,T_T1343[[#This Row],[Total]]*-1,0) -> 0
B14: DEUDA GESTION 2024 | I14: =IF(T_T1343[[#This Row],[Total]]<0,T_T1343[[#This Row],[Total]]*-1,0) -> 0
A15: 46052 | B15: Mantenimiento enero/2026 | D15: 101 | E15: 104 | G15: =SUM(D15:F15) -> 205 | H15: =+H13+T_T1343[[#This Row],[Total]] -> 205 | I15: =IF(T_T1343[[#This Row],[Total]]<0,T_T1343[[#This Row],[Total]]*-1,0) -> 0
B16: Pago mantenimiento enero/2026 | G16: =SUM(D16:F16) -> 0 | H16: =H15+G16 -> 205 | I16: =IF(T_T1343[[#This Row],[Total]]<0,T_T1343[[#This Row],[Total]]*-1,0) -> 0
A17: 45715 | B17: Mantenimiento febrero/2026 | D17: 101 | E17: 259 | G17: =SUM(D17:F17) -> 360 | H17: =H16+G17 -> 565 | I17: =IF(T_T1343[[#This Row],[Total]]<0,T_T1343[[#This Row],[Total]]*-1,0) -> 0
B18: Pago mantenimiento febrero/2026 | G18: =SUM(D18:F18) -> 0 | H18: =H17+G18 -> 565 | I18: =IF(T_T1343[[#This Row],[Total]]<0,T_T1343[[#This Row],[Total]]*-1,0) -> 0
A19: 45747 | B19: Mantenimiento marzo/2025 | D19: 121 | E19: 30 | G19: =SUM(D19:F19) -> 151 | H19: =H18+G19 -> 716 | I19: =IF(T_T1343[[#This Row],[Total]]<0,T_T1343[[#This Row],[Total]]*-1,0) -> 0
B20: Pago matenimiento marzo/2025 | G20: =SUM(D20:F20) -> 0 | H20: =H19+G20 -> 716 | I20: =IF(T_T1343[[#This Row],[Total]]<0,T_T1343[[#This Row],[Total]]*-1,0) -> 0
A21: 45777 | B21: Mantenimiento abril/2025 | D21: 121 | E21: 3 | G21: =SUM(D21:F21) -> 124 | H21: =H20+G21 -> 840 | I21: =IF(T_T1343[[#This Row],[Total]]<0,T_T1343[[#This Row],[Total]]*-1,0) -> 0
B22: Pago mantenimiento abril/2025 | G22: =SUM(D22:F22) -> 0 | H22: =H21+G22 -> 840 | I22: =IF(T_T1343[[#This Row],[Total]]<0,T_T1343[[#This Row],[Total]]*-1,0) -> 0
A23: 45807 | B23: Mantenimiento mayo/2025 | D23: 121 | E23: 17 | G23: =SUM(D23:F23) -> 138 | H23: =H22+G23 -> 978 | I23: =IF(T_T1343[[#This Row],[Total]]<0,T_T1343[[#This Row],[Total]]*-1,0) -> 0
B24: Pago mantenimiento mayo/2025 | G24: =SUM(D24:F24) -> 0 | H24: =H23+G24 -> 978 | I24: =IF(T_T1343[[#This Row],[Total]]<0,T_T1343[[#This Row],[Total]]*-1,0) -> 0
A25: 45838 | B25: Mantenimiento junio/2025 | G25: =SUM(D25:F25) -> 0 | H25: =H24+G25 -> 978 | I25: =IF(T_T1343[[#This Row],[Total]]<0,T_T1343[[#This Row],[Total]]*-1,0) -> 0
B26: Pago mantenimiento junio/2025 | G26: =SUM(D26:F26) -> 0 | H26: =H25+G26 -> 978 | I26: =IF(T_T1343[[#This Row],[Total]]<0,T_T1343[[#This Row],[Total]]*-1,0) -> 0 | N26: SABRINA ARDAYA
A27: 45868 | B27: Mantenimiento julio/2025 | G27: =SUM(D27:F27) -> 0 | H27: =H26+G27 -> 978 | I27: =IF(T_T1343[[#This Row],[Total]]<0,T_T1343[[#This Row],[Total]]*-1,0) -> 0
B28: Pago mantenimient julio/2025 | G28: =SUM(D28:F28) -> 0 | H28: =H27+G28 -> 978 | I28: =IF(T_T1343[[#This Row],[Total]]<0,T_T1343[[#This Row],[Total]]*-1,0) -> 0
A29: 45899 | B29: Mantenimiento agosto/2025 | G29: =SUM(D29:F29) -> 0 | H29: =H28+G29 -> 978 | I29: =IF(T_T1343[[#This Row],[Total]]<0,T_T1343[[#This Row],[Total]]*-1,0) -> 0
B30: Pago mantenimiento agosto/2025 | G30: =SUM(D30:F30) -> 0 | H30: =H29+G30 -> 978 | I30: =IF(T_T1343[[#This Row],[Total]]<0,T_T1343[[#This Row],[Total]]*-1,0) -> 0
A31: 45930 | B31: Mantenimiento septiembre/2025 | G31: =SUM(D31:F31) -> 0 | H31: =H30+G31 -> 978 | I31: =IF(T_T1343[[#This Row],[Total]]<0,T_T1343[[#This Row],[Total]]*-1,0) -> 0
B32: Pago mantenimiento septiembre/2025 | G32: =SUM(D32:F32) -> 0 | H32: =H31+G32 -> 978 | I32: =IF(T_T1343[[#This Row],[Total]]<0,T_T1343[[#This Row],[Total]]*-1,0) -> 0
A33: 45960 | B33: Mantenimiento octubre /2025 | G33: =SUM(D33:F33) -> 0 | H33: =H32+G33 -> 978 | I33: =IF(T_T1343[[#This Row],[Total]]<0,T_T1343[[#This Row],[Total]]*-1,0) -> 0
B34: Pago mantenimiento octubre/2025 | G34: =SUM(D34:F34) -> 0 | H34: =H33+G34 -> 978 | I34: =IF(T_T1343[[#This Row],[Total]]<0,T_T1343[[#This Row],[Total]]*-1,0) -> 0
A35: 45991 | B35: Mantenimiento noviembre/2025 | G35: =SUM(D35:F35) -> 0 | H35: =H34+G35 -> 978 | I35: =IF(T_T1343[[#This Row],[Total]]<0,T_T1343[[#This Row],[Total]]*-1,0) -> 0
B36: Pago mantenimiento noviembre/2025 | G36: =SUM(D36:F36) -> 0 | H36: =H35+G36 -> 978 | I36: =IF(T_T1343[[#This Row],[Total]]<0,T_T1343[[#This Row],[Total]]*-1,0) -> 0
A37: 46021 | B37: Mantenimiento diciembre/2025 | G37: =SUM(D37:F37) -> 0 | H37: =H36+G37 -> 978 | I37: =IF(T_T1343[[#This Row],[Total]]<0,T_T1343[[#This Row],[Total]]*-1,0) -> 0
B38: Pago de Mantenimiento diciembre/2025 | G38: =SUM(D38:F38) -> 0 | H38: =H37+G38 -> 978 | I38: =IF(T_T1343[[#This Row],[Total]]<0,T_T1343[[#This Row],[Total]]*-1,0) -> 0
G39: =SUM(D39:F46) -> 0 | H39: =H38+G39 -> 978 | I39: =IF(T_T1343[[#This Row],[Total]]<0,T_T1343[[#This Row],[Total]]*-1,0) -> 0
G40: =SUM(D40:F47) -> 0 | H40: =H39+G40 -> 978 | I40: =IF(T_T1343[[#This Row],[Total]]<0,T_T1343[[#This Row],[Total]]*-1,0) -> 0

Sheet LOCAL 05
A2: Departamento : | B2: LOCAL 05
A3: Propietario : | B3: LUPE MARCELA LECOÑA
A4: Inquilino : | B4: =LOOKUP(B2,#REF!,#REF!) -> #REF!
A5: Teléfono : | B5: =LOOKUP(B2,#REF!,#REF!) -> #REF!
A6: Celular : | B6: =LOOKUP(B2,#REF!,#REF!) -> #REF!
A7: Correo : | B7: =LOOKUP(B2,#REF!,#REF!) -> #REF! | H7: Resumen
A8: INQULINO: | B8: RAUL QUIÑONES
A9: Fecha | B9: Concepto | C9: Recibo | D9: Expensas | E9: Agua | F9: Multa | G9: Total | H9: Deuda | I9: Pagado
B10: DEUDA GESTION 2017-2020 | H10: 0 | I10: =IF(T_T1345[[#This Row],[Total]]<0,T_T1345[[#This Row],[Total]]*-1,0) -> 0
B11: DEUDA GESTION 2021 | H11: =H10+G11 -> 0 | I11: =IF(T_T1345[[#This Row],[Total]]<0,T_T1345[[#This Row],[Total]]*-1,0) -> 0
B12: DEUDA GESTION 2022 | H12: =H11+G12 -> 0 | I12: =IF(T_T1345[[#This Row],[Total]]<0,T_T1345[[#This Row],[Total]]*-1,0) -> 0
B13: DEUDA GESTION 2023 | H13: =H11+G13 -> 0 | I13: =IF(T_T1345[[#This Row],[Total]]<0,T_T1345[[#This Row],[Total]]*-1,0) -> 0
B14: DEUDA GESTION 2024 | H14: =H13+G14 -> 0 | I14: =IF(T_T1345[[#This Row],[Total]]<0,T_T1345[[#This Row],[Total]]*-1,0) -> 0
A15: 46052 | B15: Mantenimiento enero/2026 | D15: 101 | E15: 13 | G15: =SUM(D15:F15) -> 114 | H15: =H13+G15 -> 114 | I15: =IF(T_T1345[[#This Row],[Total]]<0,T_T1345[[#This Row],[Total]]*-1,0) -> 0
B16: Pago mantenimiento enero/2026 | C16: 8555 | D16: -101 | E16: -13 | G16: =SUM(D16:F16) -> -114 | H16: =H15+G16 -> 0 | I16: =IF(T_T1345[[#This Row],[Total]]<0,T_T1345[[#This Row],[Total]]*-1,0) -> 114
A17: 45715 | B17: Mantenimiento febrero/2025 | D17: 101 | E17: 13 | G17: =SUM(D17:F17) -> 114 | H17: =H16+G17 -> 114 | I17: =IF(T_T1345[[#This Row],[Total]]<0,T_T1345[[#This Row],[Total]]*-1,0) -> 0
B18: Pago mantenimiento febrero/2025 | C18: 8736 | D18: -101 | E18: -13 | G18: =SUM(D18:F18) -> -114 | H18: =H17+G18 -> 0 | I18: =IF(T_T1345[[#This Row],[Total]]<0,T_T1345[[#This Row],[Total]]*-1,0) -> 114
A19: 45747 | B19: Mantenimiento marzo/2025 | D19: 121 | E19: 13 | G19: =SUM(D19:F19) -> 134 | H19: =H18+G19 -> 134 | I19: =IF(T_T1345[[#This Row],[Total]]<0,T_T1345[[#This Row],[Total]]*-1,0) -> 0
B20: Pago matenimiento marzo/2025 | C20: 8815 | D20: -121 | E20: -13 | G20: =SUM(D20:F20) -> -134 | H20: =H19+G20 -> 0 | I20: =IF(T_T1345[[#This Row],[Total]]<0,T_T1345[[#This Row],[Total]]*-1,0) -> 134
A21: 45777 | B21: Mantenimiento abril/2025 | D21: 121 | E21: 13 | G21: =SUM(D21:F21) -> 134 | H21: =H20+G21 -> 134 | I21: =IF(T_T1345[[#This Row],[Total]]<0,T_T1345[[#This Row],[Total]]*-1,0) -> 0
B22: Pago mantenimiento abril/2025 | C22: 8951 | D22: -121 | E22: -13 | G22: =SUM(D22:F22) -> -134 | H22: =H21+G22 -> 0 | I22: =IF(T_T1345[[#This Row],[Total]]<0,T_T1345[[#This Row],[Total]]*-1,0) -> 134
A23: 45807 | B23: Mantenimiento mayo/2025 | G23: =SUM(D23:F23) -> 0 | H23: =H22+G23 -> 0 | I23: =IF(T_T1345[[#This Row],[Total]]<0,T_T1345[[#This Row],[Total]]*-1,0) -> 0
B24: Pago mantenimiento mayo/2025 | G24: =SUM(D24:F24) -> 0 | H24: =H23+G24 -> 0 | I24: =IF(T_T1345[[#This Row],[Total]]<0,T_T1345[[#This Row],[Total]]*-1,0) -> 0
A25: 45838 | B25: Mantenimiento junio/2025 | G25: =SUM(D25:F25) -> 0 | H25: =H24+G25 -> 0 | I25: =IF(T_T1345[[#This Row],[Total]]<0,T_T1345[[#This Row],[Total]]*-1,0) -> 0
B26: Pago mantenimiento junio/2025 | G26: =SUM(D26:F26) -> 0 | H26: =H25+G26 -> 0 | I26: =IF(T_T1345[[#This Row],[Total]]<0,T_T1345[[#This Row],[Total]]*-1,0) -> 0
A27: 45868 | B27: Mantenimiento julio/2025 | G27: =SUM(D27:F27) -> 0 | H27: =H26+G27 -> 0 | I27: =IF(T_T1345[[#This Row],[Total]]<0,T_T1345[[#This Row],[Total]]*-1,0) -> 0
B28: Pago mantenimient julio/2025 | G28: =SUM(D28:F28) -> 0 | H28: =H27+G28 -> 0 | I28: =IF(T_T1345[[#This Row],[Total]]<0,T_T1345[[#This Row],[Total]]*-1,0) -> 0
A29: 45899 | B29: Mantenimiento agosto/2025 | G29: =SUM(D29:F29) -> 0 | H29: =H28+G29 -> 0 | I29: =IF(T_T1345[[#This Row],[Total]]<0,T_T1345[[#This Row],[Total]]*-1,0) -> 0
B30: Pago mantenimiento agosto/2025 | G30: =SUM(D30:F30) -> 0 | H30: =H29+G30 -> 0 | I30: =IF(T_T1345[[#This Row],[Total]]<0,T_T1345[[#This Row],[Total]]*-1,0) -> 0
A31: 45930 | B31: Mantenimiento septiembre/2025 | G31: =SUM(D31:F31) -> 0 | H31: =H30+G31 -> 0 | I31: =IF(T_T1345[[#This Row],[Total]]<0,T_T1345[[#This Row],[Total]]*-1,0) -> 0
B32: Pago mantenimiento septiembre/2025 | G32: =SUM(D32:F32) -> 0 | H32: =H31+G32 -> 0 | I32: =IF(T_T1345[[#This Row],[Total]]<0,T_T1345[[#This Row],[Total]]*-1,0) -> 0
A33: 45960 | B33: Mantenimiento octubre /2025 | G33: =SUM(D33:F33) -> 0 | H33: =H32+G33 -> 0 | I33: =IF(T_T1345[[#This Row],[Total]]<0,T_T1345[[#This Row],[Total]]*-1,0) -> 0
B34: Pago mantenimiento octubre/2025 | G34: =SUM(D34:F34) -> 0 | H34: =H33+G34 -> 0 | I34: =IF(T_T1345[[#This Row],[Total]]<0,T_T1345[[#This Row],[Total]]*-1,0) -> 0
A35: 45991 | B35: Mantenimiento noviembre/2025 | G35: =SUM(D35:F35) -> 0 | H35: =H34+G35 -> 0 | I35: =IF(T_T1345[[#This Row],[Total]]<0,T_T1345[[#This Row],[Total]]*-1,0) -> 0
B36: Pago mantenimiento noviembre/2025 | G36: =SUM(D36:F36) -> 0 | H36: =H35+G36 -> 0 | I36: =IF(T_T1345[[#This Row],[Total]]<0,T_T1345[[#This Row],[Total]]*-1,0) -> 0
A37: 46021 | B37: Mantenimiento diciembre/2025 | G37: =SUM(D37:F37) -> 0 | H37: =H36+G37 -> 0 | I37: =IF(T_T1345[[#This Row],[Total]]<0,T_T1345[[#This Row],[Total]]*-1,0) -> 0
B38: Pago de Mantenimiento diciembre/2025 | G38: =SUM(D38:F38) -> 0 | H38: =H37+G38 -> 0 | I38: =IF(T_T1345[[#This Row],[Total]]<0,T_T1345[[#This Row],[Total]]*-1,0) -> 0
G39: =SUM(D39:F46) -> 0 | H39: =H38+G39 -> 0 | I39: =IF(T_T1345[[#This Row],[Total]]<0,T_T1345[[#This Row],[Total]]*-1,0) -> 0
G40: =SUM(D40:F47) -> 0 | H40: =H39+G40 -> 0 | I40: =IF(T_T1345[[#This Row],[Total]]<0,T_T1345[[#This Row],[Total]]*-1,0) -> 0

Sheet LOCAL 06
A2: Departamento : | B2: LOCAL 06
A3: Propietario : | B3: =LOOKUP(B2,#REF!,#REF!) -> #REF!
A4: Inquilino : | B4: =LOOKUP(B2,#REF!,#REF!) -> #REF!
A5: Teléfono : | B5: =LOOKUP(B2,#REF!,#REF!) -> #REF!
A6: Celular : | B6: =LOOKUP(B2,#REF!,#REF!) -> #REF!
A7: Correo : | B7: LOURDEZ CONDORI
A8: INQUILINO VERONICA RODRIGUEZ
A9: Fecha | B9: Concepto | C9: Recibo | D9: Expensas | E9: Agua | F9: Multa | G9: Total | H9: Deuda | I9: Pagado | J9: Columna1 | K9: Columna2
B10: DEUDA GESTION 2017-2020 | H10: 0 | I10: =IF(T_T1346[[#This Row],[Total]]<0,T_T1346[[#This Row],[Total]]*-1,0) -> 0
B11: DEUDA GESTION 2021 | H11: 0 | I11: =IF(T_T1346[[#This Row],[Total]]<0,T_T1346[[#This Row],[Total]]*-1,0) -> 0
B12: DEUDA GESTION 2022 | H12: 0 | I12: =IF(T_T1346[[#This Row],[Total]]<0,T_T1346[[#This Row],[Total]]*-1,0) -> 0
B13: DEUDA GESTION 2023 | H13: 0 | I13: =IF(T_T1346[[#This Row],[Total]]<0,T_T1346[[#This Row],[Total]]*-1,0) -> 0
B14: DEUDA GESTION 2024 | I14: =IF(T_T1346[[#This Row],[Total]]<0,T_T1346[[#This Row],[Total]]*-1,0) -> 0
A15: 46052 | B15: Mantenimiento enero/2026 | D15: 134 | E15: 5 | G15: =SUM(D15:F15) -> 139 | H15: =+H13+T_T1346[[#This Row],[Total]] -> 139 | I15: =IF(T_T1346[[#This Row],[Total]]<0,T_T1346[[#This Row],[Total]]*-1,0) -> 0
B16: Pago mantenimiento enero/2026 | C16: 8544- 8603 | D16: =-108-26 -> -134 | E16: -5 | G16: =SUM(D16:F16) -> -139 | H16: =H15+G16 -> 0 | I16: =IF(T_T1346[[#This Row],[Total]]<0,T_T1346[[#This Row],[Total]]*-1,0) -> 139 | K16: parqueo nfr
A17: 45715 | B17: Mantenimiento febrero/2025 | D17: 134 | E17: 18 | G17: =SUM(D17:F17) -> 152 | H17: =H16+G17 -> 152 | I17: =IF(T_T1346[[#This Row],[Total]]<0,T_T1346[[#This Row],[Total]]*-1,0) -> 0
B18: Pago mantenimiento febrero/2025 | C18: 8665-8699 | D18: =-108-26 -> -134 | E18: -18 | G18: =SUM(D18:F18) -> -152 | H18: =H17+G18 -> 0 | I18: =IF(T_T1346[[#This Row],[Total]]<0,T_T1346[[#This Row],[Total]]*-1,0) -> 152
A19: 45747 | B19: Mantenimiento marzo/2025 | D19: =129+30 -> 159 | E19: 45 | G19: =SUM(D19:F19) -> 204 | H19: =H18+G19 -> 204 | I19: =IF(T_T1346[[#This Row],[Total]]<0,T_T1346[[#This Row],[Total]]*-1,0) -> 0
B20: Pago matenimiento marzo/2025 | C20: 8797-8812 | D20: =-30-129 -> -159 | E20: -45 | G20: =SUM(D20:F20) -> -204 | H20: =H19+G20 -> 0 | I20: =IF(T_T1346[[#This Row],[Total]]<0,T_T1346[[#This Row],[Total]]*-1,0) -> 204
A21: 45777 | B21: Mantenimiento abril/2025 | D21: =129+30 -> 159 | E21: 70 | G21: =SUM(D21:F21) -> 229 | H21: =H20+G21 -> 229 | I21: =IF(T_T1346[[#This Row],[Total]]<0,T_T1346[[#This Row],[Total]]*-1,0) -> 0
B22: Pago mantenimiento abril/2025 | C22: 8928-8931 | D22: =-30-129 -> -159 | E22: -70 | G22: =SUM(D22:F22) -> -229 | H22: =H21+G22 -> 0 | I22: =IF(T_T1346[[#This Row],[Total]]<0,T_T1346[[#This Row],[Total]]*-1,0) -> 229
A23: 45807 | B23: Mantenimiento mayo/2025 | D23: 159 | E23: 72 | G23: =SUM(D23:F23) -> 231 | H23: =H22+G23 -> 231 | I23: =IF(T_T1346[[#This Row],[Total]]<0,T_T1346[[#This Row],[Total]]*-1,0) -> 0
B24: Pago mantenimiento mayo/2025 | G24: =SUM(D24:F24) -> 0 | H24: =H23+G24 -> 231 | I24: =IF(T_T1346[[#This Row],[Total]]<0,T_T1346[[#This Row],[Total]]*-1,0) -> 0
A25: 45838 | B25: Mantenimiento junio/2025 | G25: =SUM(D25:F25) -> 0 | H25: =H24+G25 -> 231 | I25: =IF(T_T1346[[#This Row],[Total]]<0,T_T1346[[#This Row],[Total]]*-1,0) -> 0
B26: Pago mantenimiento junio/2025 | G26: =SUM(D26:F26) -> 0 | H26: =H25+G26 -> 231 | I26: =IF(T_T1346[[#This Row],[Total]]<0,T_T1346[[#This Row],[Total]]*-1,0) -> 0 | L26: nuevo inquilino desde julio
A27: 45868 | B27: Mantenimiento julio/2025 | G27: =SUM(D27:F27) -> 0 | H27: =H26+G27 -> 231 | I27: =IF(T_T1346[[#This Row],[Total]]<0,T_T1346[[#This Row],[Total]]*-1,0) -> 0 | L27: DORIS SAAVEDRA
B28: Pago mantenimient julio/2025 | G28: =SUM(D28:F28) -> 0 | H28: =H27+G28 -> 231 | I28: =IF(T_T1346[[#This Row],[Total]]<0,T_T1346[[#This Row],[Total]]*-1,0) -> 0
A29: 45899 | B29: Mantenimiento agosto/2025 | G29: =SUM(D29:F29) -> 0 | H29: =H28+G29 -> 231 | I29: =IF(T_T1346[[#This Row],[Total]]<0,T_T1346[[#This Row],[Total]]*-1,0) -> 0
B30: Pago mantenimiento agosto/2025 | G30: =SUM(D30:F30) -> 0 | H30: =H29+G30 -> 231 | I30: =IF(T_T1346[[#This Row],[Total]]<0,T_T1346[[#This Row],[Total]]*-1,0) -> 0
A31: 45930 | B31: Mantenimiento septiembre/2025 | G31: =SUM(D31:F31) -> 0 | H31: =H30+G31 -> 231 | I31: =IF(T_T1346[[#This Row],[Total]]<0,T_T1346[[#This Row],[Total]]*-1,0) -> 0
B32: Pago mantenimiento septiembre/2025 | G32: =SUM(D32:F32) -> 0 | H32: =H31+G32 -> 231 | I32: =IF(T_T1346[[#This Row],[Total]]<0,T_T1346[[#This Row],[Total]]*-1,0) -> 0
A33: 45960 | B33: Mantenimiento octubre /2025 | G33: =SUM(D33:F33) -> 0 | H33: =H32+G33 -> 231 | I33: =IF(T_T1346[[#This Row],[Total]]<0,T_T1346[[#This Row],[Total]]*-1,0) -> 0
B34: Pago mantenimiento octubre/2025 | G34: =SUM(D34:F34) -> 0 | H34: =H33+G34 -> 231 | I34: =IF(T_T1346[[#This Row],[Total]]<0,T_T1346[[#This Row],[Total]]*-1,0) -> 0
A35: 45991 | B35: Mantenimiento noviembre/2025 | G35: =SUM(D35:F35) -> 0 | H35: =H34+G35 -> 231 | I35: =IF(T_T1346[[#This Row],[Total]]<0,T_T1346[[#This Row],[Total]]*-1,0) -> 0
B36: Pago mantenimiento noviembre/2025 | G36: =SUM(D36:F36) -> 0 | H36: =H35+G36 -> 231 | I36: =IF(T_T1346[[#This Row],[Total]]<0,T_T1346[[#This Row],[Total]]*-1,0) -> 0
A37: 46021 | B37: Mantenimiento diciembre/2025 | G37: =SUM(D37:F37) -> 0 | H37: =H36+G37 -> 231 | I37: =IF(T_T1346[[#This Row],[Total]]<0,T_T1346[[#This Row],[Total]]*-1,0) -> 0
B38: Pago de Mantenimiento diciembre/2025 | G38: =SUM(D38:F38) -> 0 | H38: =H37+G38 -> 231 | I38: =IF(T_T1346[[#This Row],[Total]]<0,T_T1346[[#This Row],[Total]]*-1,0) -> 0
G39: =SUM(D39:F47) -> 0 | H39: =H38+G39 -> 231 | I39: =IF(T_T1346[[#This Row],[Total]]<0,T_T1346[[#This Row],[Total]]*-1,0) -> 0
I40: =IF(T_T1346[[#This Row],[Total]]<0,T_T1346[[#This Row],[Total]]*-1,0) -> 0
I41: =IF(T_T1346[[#This Row],[Total]]<0,T_T1346[[#This Row],[Total]]*-1,0) -> 0

Sheet LOCAL 07
A2: Departamento : | B2: LOCAL 07
A3: Propietario : | B3: =LOOKUP(B2,#REF!,#REF!) -> #REF!
A4: Inquilino : | B4: =LOOKUP(B2,#REF!,#REF!) -> #REF!
A5: Teléfono : | B5: =LOOKUP(B2,#REF!,#REF!) -> #REF!
A6: Celular : | B6: =LOOKUP(B2,#REF!,#REF!) -> #REF!
A7: Inquilino : | B7: =LOOKUP(B2,#REF!,#REF!) -> #REF! | H7: Resumen
A9: Fecha | B9: Concepto | C9: Recibo | D9: Expensas | E9: Agua | F9: Multa | G9: Total | H9: Deuda | I9: Pagado | J9: Columna1
B10: DEUDA GESTION 2017-2020 | H10: 0 | I10: =IF(T_T1347[[#This Row],[Total]]<0,T_T1347[[#This Row],[Total]]*-1,0) -> 0
B11: DEUDA GESTION 2021 | H11: 0 | I11: =IF(T_T1347[[#This Row],[Total]]<0,T_T1347[[#This Row],[Total]]*-1,0) -> 0
B12: DEUDA GESTION 2022 | H12: 0 | I12: =IF(T_T1347[[#This Row],[Total]]<0,T_T1347[[#This Row],[Total]]*-1,0) -> 0
B13: DEUDA GESTION 2023 | H13: 0 | I13: =IF(T_T1347[[#This Row],[Total]]<0,T_T1347[[#This Row],[Total]]*-1,0) -> 0
B14: DEUDA GESTION 2024 | I14: =IF(T_T1347[[#This Row],[Total]]<0,T_T1347[[#This Row],[Total]]*-1,0) -> 0
A15: 46052 | B15: Mantenimiento enero/2026 | D15: 74 | E15: 13 | G15: =SUM(D15:F15) -> 87 | H15: =+H13+T_T1347[[#This Row],[Total]] -> 87 | I15: =IF(T_T1347[[#This Row],[Total]]<0,T_T1347[[#This Row],[Total]]*-1,0) -> 0
B16: Pago mantenimiento enero/2026 | G16: =SUM(D16:F16) -> 0 | H16: =H15+G16 -> 87 | I16: =IF(T_T1347[[#This Row],[Total]]<0,T_T1347[[#This Row],[Total]]*-1,0) -> 0
A17: 45715 | B17: Mantenimiento febrero/2025 | D17: 74 | E17: 13 | G17: =SUM(D17:F17) -> 87 | H17: =H16+G17 -> 174 | I17: =IF(T_T1347[[#This Row],[Total]]<0,T_T1347[[#This Row],[Total]]*-1,0) -> 0
B18: Pago mantenimiento febrero/2025 | G18: =SUM(D18:F18) -> 0 | H18: =H17+G18 -> 174 | I18: =IF(T_T1347[[#This Row],[Total]]<0,T_T1347[[#This Row],[Total]]*-1,0) -> 0
A19: 45747 | B19: Mantenimiento marzo/2025 | D19: 89 | E19: 13 | G19: =SUM(D19:F19) -> 102 | H19: =H18+G19 -> 276 | I19: =IF(T_T1347[[#This Row],[Total]]<0,T_T1347[[#This Row],[Total]]*-1,0) -> 0
B20: Pago matenimiento marzo/2025 | G20: =SUM(D20:F20) -> 0 | H20: =H19+G20 -> 276 | I20: =IF(T_T1347[[#This Row],[Total]]<0,T_T1347[[#This Row],[Total]]*-1,0) -> 0
A21: 45777 | B21: Mantenimiento abril/2025 | D21: 89 | E21: 13 | G21: =SUM(D21:F21) -> 102 | H21: =H20+G21 -> 378 | I21: =IF(T_T1347[[#This Row],[Total]]<0,T_T1347[[#This Row],[Total]]*-1,0) -> 0
B22: Pago mantenimiento abril/2025 | G22: =SUM(D22:F22) -> 0 | H22: =H21+G22 -> 378 | I22: =IF(T_T1347[[#This Row],[Total]]<0,T_T1347[[#This Row],[Total]]*-1,0) -> 0
A23: 45807 | B23: Mantenimiento mayo/2025 | D23: 89 | E23: 13 | G23: =SUM(D23:F23) -> 102 | H23: =H22+G23 -> 480 | I23: =IF(T_T1347[[#This Row],[Total]]<0,T_T1347[[#This Row],[Total]]*-1,0) -> 0
B24: Pago mantenimiento mayo/2025 | G24: =SUM(D24:F24) -> 0 | H24: =H23+G24 -> 480 | I24: =IF(T_T1347[[#This Row],[Total]]<0,T_T1347[[#This Row],[Total]]*-1,0) -> 0
A25: 45838 | B25: Mantenimiento junio/2025 | G25: =SUM(D25:F25) -> 0 | H25: =H24+G25 -> 480 | I25: =IF(T_T1347[[#This Row],[Total]]<0,T_T1347[[#This Row],[Total]]*-1,0) -> 0
B26: Pago mantenimiento junio/2025 | G26: =SUM(D26:F26) -> 0 | H26: =H25+G26 -> 480 | I26: =IF(T_T1347[[#This Row],[Total]]<0,T_T1347[[#This Row],[Total]]*-1,0) -> 0
A27: 45868 | B27: Mantenimiento julio/2025 | G27: =SUM(D27:F27) -> 0 | H27: =H26+G27 -> 480 | I27: =IF(T_T1347[[#This Row],[Total]]<0,T_T1347[[#This Row],[Total]]*-1,0) -> 0
B28: Pago mantenimient julio/2025 | G28: =SUM(D28:F28) -> 0 | H28: =H27+G28 -> 480 | I28: =IF(T_T1347[[#This Row],[Total]]<0,T_T1347[[#This Row],[Total]]*-1,0) -> 0
A29: 45899 | B29: Mantenimiento agosto/2025 | G29: =SUM(D29:F29) -> 0 | H29: =H28+G29 -> 480 | I29: =IF(T_T1347[[#This Row],[Total]]<0,T_T1347[[#This Row],[Total]]*-1,0) -> 0
B30: Pago mantenimiento agosto/2025 | G30: =SUM(D30:F30) -> 0 | H30: =H29+G30 -> 480 | I30: =IF(T_T1347[[#This Row],[Total]]<0,T_T1347[[#This Row],[Total]]*-1,0) -> 0
A31: 45930 | B31: Mantenimiento septiembre/2025 | G31: =SUM(D31:F31) -> 0 | H31: =H30+G31 -> 480 | I31: =IF(T_T1347[[#This Row],[Total]]<0,T_T1347[[#This Row],[Total]]*-1,0) -> 0
B32: Pago mantenimiento septiembre/2025 | G32: =SUM(D32:F32) -> 0 | H32: =H31+G32 -> 480 | I32: =IF(T_T1347[[#This Row],[Total]]<0,T_T1347[[#This Row],[Total]]*-1,0) -> 0
A33: 45960 | B33: Mantenimiento octubre /2025 | G33: =SUM(D33:F33) -> 0 | H33: =H32+G33 -> 480 | I33: =IF(T_T1347[[#This Row],[Total]]<0,T_T1347[[#This Row],[Total]]*-1,0) -> 0
B34: Pago mantenimiento octubre/2025 | G34: =SUM(D34:F34) -> 0 | H34: =H33+G34 -> 480 | I34: =IF(T_T1347[[#This Row],[Total]]<0,T_T1347[[#This Row],[Total]]*-1,0) -> 0
A35: 45991 | B35: Mantenimiento noviembre/2025 | G35: =SUM(D35:F35) -> 0 | H35: =H34+G35 -> 480 | I35: =IF(T_T1347[[#This Row],[Total]]<0,T_T1347[[#This Row],[Total]]*-1,0) -> 0
B36: Pago mantenimiento noviembre/2025 | G36: =SUM(D36:F36) -> 0 | H36: =H35+G36 -> 480 | I36: =IF(T_T1347[[#This Row],[Total]]<0,T_T1347[[#This Row],[Total]]*-1,0) -> 0
A37: 46021 | B37: Mantenimiento diciembre/2025 | G37: =SUM(D37:F37) -> 0 | H37: =H36+G37 -> 480 | I37: =IF(T_T1347[[#This Row],[Total]]<0,T_T1347[[#This Row],[Total]]*-1,0) -> 0
B38: Pago de Mantenimiento diciembre/2025 | G38: =SUM(D38:F38) -> 0 | H38: =H37+G38 -> 480 | I38: =IF(T_T1347[[#This Row],[Total]]<0,T_T1347[[#This Row],[Total]]*-1,0) -> 0
G39: =SUM(D39:F46) -> 0 | H39: =H38+G39 -> 480 | I39: =IF(T_T1347[[#This Row],[Total]]<0,T_T1347[[#This Row],[Total]]*-1,0) -> 0
G40: =SUM(D40:F47) -> 0 | H40: =H39+G40 -> 480 | I40: =IF(T_T1347[[#This Row],[Total]]<0,T_T1347[[#This Row],[Total]]*-1,0) -> 0
G45: =+G42-F46 -> 0
F46: =+C46+D46+E46 -> 0

Sheet lOCAL 8 
B3: Departamento : | C3: LOCAL 08
B5: Fecha | C5: Concepto | D5: Recibo | E5: Expensas | F5: Agua | G5: Multa | H5: Total | I5: Deuda
C6: DEUDA GESTION 2017-2020 | I6: 0
C7: DEUDA GESTION 2021 | I7: 0
C8: DEUDA GESTION 2022 | I8: 0
C9: DEUDA GESTION 2023 | I9: 0
C10: DEUDA GESTION 2024
B11: 46052 | C11: Mantenimiento enero/2026 | E11: 68 | F11: 13 | H11: =SUM(E11:G11) -> 81 | I11: =+I10+H11 -> 81
C12: Pago mantenimiento enero/2026 | D12: 8608 | E12: -68 | F12: -13 | H12: =SUM(E12:G12) -> -81 | I12: =I11+H12 -> 0
B13: 45715 | C13: Mantenimiento febrero/2025 | E13: 68 | F13: 13 | H13: =SUM(E13:G13) -> 81 | I13: =I12+H13 -> 81
C14: Pago mantenimiento febrero/2025 | D14: 8723 | E14: -68 | F14: -13 | H14: =SUM(E14:G14) -> -81 | I14: =I13+H14 -> 0
B15: 45747 | C15: Mantenimiento marzo/2025 | E15: 81 | F15: 13 | H15: =SUM(E15:G15) -> 94 | I15: =I14+H15 -> 94
C16: Pago matenimiento marzo/2025 | D16: 8890 | E16: -81 | F16: -13 | H16: =SUM(E16:G16) -> -94 | I16: =I15+H16 -> 0
B17: 45777 | C17: Mantenimiento abril/2025 | E17: 81 | F17: 13 | H17: =SUM(E17:G17) -> 94 | I17: =I16+H17 -> 94
C18: Pago mantenimiento abril/2025 | D18: 8890 | E18: -81 | F18: -13 | H18: =SUM(E18:G18) -> -94 | I18: =I17+H18 -> 0
B19: 45807 | C19: Mantenimiento mayo/2025 | E19: 81 | F19: 13 | H19: =SUM(E19:G19) -> 94 | I19: =I18+H19 -> 94
C20: Pago mantenimiento mayo/2025 | H20: =SUM(E20:G20) -> 0 | I20: =I19+H20 -> 94
B21: 45838 | C21: Mantenimiento junio/2025 | H21: =SUM(E21:G21) -> 0 | I21: =I20+H21 -> 94
C22: Pago mantenimiento junio/2025 | H22: =SUM(E22:G22) -> 0 | I22: =I21+H22 -> 94
B23: 45868 | C23: Mantenimiento julio/2025 | H23: =SUM(E23:G23) -> 0 | I23: =I22+H23 -> 94
C24: Pago mantenimient julio/2025 | H24: =SUM(E24:G24) -> 0 | I24: =I23+H24 -> 94
B25: 45899 | C25: Mantenimiento agosto/2025 | H25: =SUM(E25:G25) -> 0 | I25: =I24+H25 -> 94
C26: Pago mantenimiento agosto/2025 | H26: =SUM(E26:G26) -> 0 | I26: =I25+H26 -> 94
B27: 45930 | C27: Mantenimiento septiembre/2025 | H27: =SUM(E27:G27) -> 0 | I27: =I26+H27 -> 94
C28: Pago mantenimiento septiembre/2025 | H28: =SUM(E28:G28) -> 0 | I28: =I27+H28 -> 94
B29: 45960 | C29: Mantenimiento octubre /2025 | H29: =SUM(E29:G29) -> 0 | I29: =I28+H29 -> 94
C30: Pago mantenimiento octubre/2025 | H30: =SUM(E30:G30) -> 0 | I30: =I29+H30 -> 94
B31: 45991 | C31: Mantenimiento noviembre/2025 | H31: =SUM(E31:G31) -> 0 | I31: =I30+H31 -> 94
C32: Pago mantenimiento noviembre/2025 | H32: =SUM(E32:G32) -> 0 | I32: =I31+H32 -> 94
B33: 46021 | C33: Mantenimiento diciembre/2025 | H33: =SUM(E33:G33) -> 0 | I33: =I32+H33 -> 94
C34: Pago de Mantenimiento diciembre/2025 | H34: =SUM(E34:G34) -> 0 | I34: =I33+H34 -> 94
H35: =SUM(E35:G43) -> 0 | I35: =I34+H35 -> 94

Sheet LOCAL 09
A2: Departamento : | B2: LOCAL 09
A3: Propietario : | B3: =LOOKUP(B2,#REF!,#REF!) -> #REF!
A4: Inquilino : | B4: =LOOKUP(B2,#REF!,#REF!) -> #REF!
A5: Teléfono : | B5: =LOOKUP(B2,#REF!,#REF!) -> #REF!
A6: Celular : | B6: =LOOKUP(B2,#REF!,#REF!) -> #REF!
A7: Correo : | B7: =LOOKUP(B2,#REF!,#REF!) -> #REF! | H7: Resumen
B8: EVA LUCIANA ZEGARRA
A9: Fecha | B9: Concepto | C9: Recibo | D9: Expensas | E9: Agua | F9: Multa | G9: Total | H9: Deuda | I9: Pagado | J9: Columna1
B10: DEUDA GESTION 2017-2020 | H10: 0 | I10: =IF(T_T1349[[#This Row],[Total]]<0,T_T1349[[#This Row],[Total]]*-1,0) -> 0
B11: DEUDA GESTION 2021 | H11: 0 | I11: =IF(T_T1349[[#This Row],[Total]]<0,T_T1349[[#This Row],[Total]]*-1,0) -> 0
B12: DEUDA GESTION 2022 | H12: 0 | I12: =IF(T_T1349[[#This Row],[Total]]<0,T_T1349[[#This Row],[Total]]*-1,0) -> 0
B13: DEUDA GESTION 2023 | H13: 0 | I13: =IF(T_T1349[[#This Row],[Total]]<0,T_T1349[[#This Row],[Total]]*-1,0) -> 0
B14: DEUDA GESTION 2024 | I14: =IF(T_T1349[[#This Row],[Total]]<0,T_T1349[[#This Row],[Total]]*-1,0) -> 0
A15: 46052 | B15: Mantenimiento enero/2026 | D15: 75 | E15: 13 | G15: =SUM(D15:F15) -> 88 | H15: =+H13+H10+H11+H12+T_T1349[[#This Row],[Total]] -> 88 | I15: =IF(T_T1349[[#This Row],[Total]]<0,T_T1349[[#This Row],[Total]]*-1,0) -> 0 | L15: VIOLETA PARRA
B16: Pago mantenimiento enero/2026 | C16: 8754 | D16: -75 | E16: -13 | G16: =SUM(D16:F16) -> -88 | H16: =H15+G16 -> 0 | I16: =IF(T_T1349[[#This Row],[Total]]<0,T_T1349[[#This Row],[Total]]*-1,0) -> 88
A17: 46081 | B17: Mantenimiento febrero/2026 | D17: 75 | E17: 13 | G17: =SUM(D17:F17) -> 88 | H17: =H16+G17 -> 88 | I17: =IF(T_T1349[[#This Row],[Total]]<0,T_T1349[[#This Row],[Total]]*-1,0) -> 0
B18: Pago mantenimiento febrero/2026 | G18: =SUM(D18:F18) -> 0 | H18: =H17+G18 -> 88 | I18: =IF(T_T1349[[#This Row],[Total]]<0,T_T1349[[#This Row],[Total]]*-1,0) -> 0
A19: 45747 | B19: Mantenimiento marzo/2025 | D19: 90 | E19: 13 | G19: =SUM(D19:F19) -> 103 | H19: =H18+G19 -> 191 | I19: =IF(T_T1349[[#This Row],[Total]]<0,T_T1349[[#This Row],[Total]]*-1,0) -> 0
B20: Pago matenimiento marzo/2025 | G20: =SUM(D20:F20) -> 0 | H20: =H19+G20 -> 191 | I20: =IF(T_T1349[[#This Row],[Total]]<0,T_T1349[[#This Row],[Total]]*-1,0) -> 0
A21: 45777 | B21: Mantenimiento abril/2025 | D21: 90 | E21: 13 | G21: =SUM(D21:F21) -> 103 | H21: =H20+G21 -> 294 | I21: =IF(T_T1349[[#This Row],[Total]]<0,T_T1349[[#This Row],[Total]]*-1,0) -> 0
B22: Pago mantenimiento abril/2025 | G22: =SUM(D22:F22) -> 0 | H22: =H21+G22 -> 294 | I22: =IF(T_T1349[[#This Row],[Total]]<0,T_T1349[[#This Row],[Total]]*-1,0) -> 0
A23: 45807 | B23: Mantenimiento mayo/2025 | D23: 90 | E23: 13 | G23: =SUM(D23:F23) -> 103 | H23: =H22+G23 -> 397 | I23: =IF(T_T1349[[#This Row],[Total]]<0,T_T1349[[#This Row],[Total]]*-1,0) -> 0
B24: Pago mantenimiento mayo/2025 | G24: =SUM(D24:F24) -> 0 | H24: =H23+G24 -> 397 | I24: =IF(T_T1349[[#This Row],[Total]]<0,T_T1349[[#This Row],[Total]]*-1,0) -> 0
A25: 45838 | B25: Mantenimiento junio/2025 | G25: =SUM(D25:F25) -> 0 | H25: =H24+G25 -> 397 | I25: =IF(T_T1349[[#This Row],[Total]]<0,T_T1349[[#This Row],[Total]]*-1,0) -> 0
B26: Pago mantenimiento junio/2025 | G26: =SUM(D26:F26) -> 0 | H26: =H25+G26 -> 397 | I26: =IF(T_T1349[[#This Row],[Total]]<0,T_T1349[[#This Row],[Total]]*-1,0) -> 0
A27: 45868 | B27: Mantenimiento julio/2025 | G27: =SUM(D27:F27) -> 0 | H27: =H26+G27 -> 397 | I27: =IF(T_T1349[[#This Row],[Total]]<0,T_T1349[[#This Row],[Total]]*-1,0) -> 0
B28: Pago mantenimient julio/2025 | G28: =SUM(D28:F28) -> 0 | H28: =H27+G28 -> 397 | I28: =IF(T_T1349[[#This Row],[Total]]<0,T_T1349[[#This Row],[Total]]*-1,0) -> 0
A29: 45899 | B29: Mantenimiento agosto/2025 | G29: =SUM(D29:F29) -> 0 | H29: =H28+G29 -> 397 | I29: =IF(T_T1349[[#This Row],[Total]]<0,T_T1349[[#This Row],[Total]]*-1,0) -> 0
B30: Pago mantenimiento agosto/2025 | G30: =SUM(D30:F30) -> 0 | H30: =H29+G30 -> 397 | I30: =IF(T_T1349[[#This Row],[Total]]<0,T_T1349[[#This Row],[Total]]*-1,0) -> 0
A31: 45930 | B31: Mantenimiento septiembre/2025 | G31: =SUM(D31:F31) -> 0 | H31: =H30+G31 -> 397 | I31: =IF(T_T1349[[#This Row],[Total]]<0,T_T1349[[#This Row],[Total]]*-1,0) -> 0
B32: Pago mantenimiento septiembre/2025 | G32: =SUM(D32:F32) -> 0 | H32: =H31+G32 -> 397 | I32: =IF(T_T1349[[#This Row],[Total]]<0,T_T1349[[#This Row],[Total]]*-1,0) -> 0
A33: 45960 | B33: Mantenimiento octubre /2025 | G33: =SUM(D33:F33) -> 0 | H33: =H32+G33 -> 397 | I33: =IF(T_T1349[[#This Row],[Total]]<0,T_T1349[[#This Row],[Total]]*-1,0) -> 0
B34: Pago mantenimiento octubre/2025 | G34: =SUM(D34:F34) -> 0 | H34: =H33+G34 -> 397 | I34: =IF(T_T1349[[#This Row],[Total]]<0,T_T1349[[#This Row],[Total]]*-1,0) -> 0
A35: 45991 | B35: Mantenimiento noviembre/2025 | G35: =SUM(D35:F35) -> 0 | H35: =H34+G35 -> 397 | I35: =IF(T_T1349[[#This Row],[Total]]<0,T_T1349[[#This Row],[Total]]*-1,0) -> 0
B36: Pago mantenimiento noviembre/2025 | G36: =SUM(D36:F36) -> 0 | H36: =H35+G36 -> 397 | I36: =IF(T_T1349[[#This Row],[Total]]<0,T_T1349[[#This Row],[Total]]*-1,0) -> 0
A37: 46021 | B37: Mantenimiento diciembre/2025 | G37: =SUM(D37:F37) -> 0 | H37: =H36+G37 -> 397 | I37: =IF(T_T1349[[#This Row],[Total]]<0,T_T1349[[#This Row],[Total]]*-1,0) -> 0
B38: Pago de Mantenimiento diciembre/2025 | G38: =SUM(D38:F38) -> 0 | H38: =H37+G38 -> 397 | I38: =IF(T_T1349[[#This Row],[Total]]<0,T_T1349[[#This Row],[Total]]*-1,0) -> 0
G39: =SUM(D39:F47) -> 0 | H39: =H38+G39 -> 397 | I39: =IF(T_T1349[[#This Row],[Total]]<0,T_T1349[[#This Row],[Total]]*-1,0) -> 0
H40: =H39+G40 -> 397 | I40: =IF(T_T1349[[#This Row],[Total]]<0,T_T1349[[#This Row],[Total]]*-1,0) -> 0
H41: =H40+G41 -> 397 | I41: =IF(T_T1349[[#This Row],[Total]]<0,T_T1349[[#This Row],[Total]]*-1,0) -> 0

Sheet LOCAL 10
B3: Departamento : | C3: local 10
B4: Propietario : | C4: MANUEL AJATA
B10: Fecha | C10: Concepto | D10: Recibo | E10: Expensas | F10: Agua | G10: Multa | H10: Total | I10: Deuda
C11: DEUDA GESTION 2017-2020 | I11: 0
C12: DEUDA GESTION 2021 | I12: 0
C13: DEUDA GESTION 2022 | I13: 0
C14: DEUDA GESTION 2023 | I14: 0
C15: DEUDA GESTION 2024
B16: 46052 | C16: Mantenimiento enero/2026 | E16: 82 | F16: 75 | H16: =SUM(E16:G16) -> 157 | I16: =+I15+H16 -> 157
C17: Pago mantenimiento enero/2026 | D17: 8823 | E17: -82 | F17: -75 | H17: =SUM(E17:G17) -> -157 | I17: =I16+H17 -> 0
B18: 45716 | C18: Mantenimiento febrero/2026 | E18: 82 | F18: 61 | H18: =SUM(E18:G18) -> 143 | I18: =I17+H18 -> 143
C19: Pago mantenimiento febrero/2026 | D19: 8823 | E19: -82 | F19: -61 | H19: =SUM(E19:G19) -> -143 | I19: =I18+H19 -> 0
B20: 45747 | C20: Mantenimiento marzo/2025 | E20: 98 | F20: 54 | H20: =SUM(E20:G20) -> 152 | I20: =I19+H20 -> 152
C21: Pago matenimiento marzo/2025 | D21: 8823 | E21: -98 | F21: -54 | H21: =SUM(E21:G21) -> -152 | I21: =I20+H21 -> 0
B22: 45777 | C22: Mantenimiento abril/2025 | E22: 98 | F22: 57 | H22: =SUM(E22:G22) -> 155 | I22: =I21+H22 -> 155
C23: Pago mantenimiento abril/2025 | D23: 8945 | E23: -98 | F23: -57 | H23: =SUM(E23:G23) -> -155 | I23: =I22+H23 -> 0
B24: 45807 | C24: Mantenimiento mayo/2025 | E24: 98 | F24: 55 | H24: =SUM(E24:G24) -> 153 | I24: =I23+H24 -> 153
C25: Pago mantenimiento mayo/2025 | H25: =SUM(E25:G25) -> 0 | I25: =I24+H25 -> 153
B26: 45838 | C26: Mantenimiento junio/2025 | H26: =SUM(E26:G26) -> 0 | I26: =I25+H26 -> 153
C27: Pago mantenimiento junio/2025 | H27: =SUM(E27:G27) -> 0 | I27: =I26+H27 -> 153
B28: 45868 | C28: Mantenimiento julio/2025 | H28: =SUM(E28:G28) -> 0 | I28: =I27+H28 -> 153
C29: Pago mantenimient julio/2025 | H29: =SUM(E29:G29) -> 0 | I29: =I28+H29 -> 153
B30: 45899 | C30: Mantenimiento agosto/2025 | H30: =SUM(E30:G30) -> 0 | I30: =I29+H30 -> 153
C31: Pago mantenimiento agosto/2025 | H31: =SUM(E31:G31) -> 0 | I31: =I30+H31 -> 153
B32: 45930 | C32: Mantenimiento septiembre/2025 | H32: =SUM(E32:G32) -> 0 | I32: =I31+H32 -> 153
C33: Pago mantenimiento septiembre/2025 | H33: =SUM(E33:G33) -> 0 | I33: =I32+H33 -> 153
B34: 45960 | C34: Mantenimiento octubre /2025 | H34: =SUM(E34:G34) -> 0 | I34: =I33+H34 -> 153
C35: Pago mantenimiento octubre/2025 | H35: =SUM(E35:G35) -> 0 | I35: =I34+H35 -> 153
B36: 45991 | C36: Mantenimiento noviembre/2025 | H36: =SUM(E36:G36) -> 0 | I36: =I35+H36 -> 153
C37: Pago mantenimiento noviembre/2025 | H37: =SUM(E37:G37) -> 0 | I37: =I36+H37 -> 153
B38: 46021 | C38: Mantenimiento diciembre/2025 | H38: =SUM(E38:G38) -> 0 | I38: =I37+H38 -> 153
C39: Pago de Mantenimiento diciembre/2025 | H39: =SUM(E39:G39) -> 0 | I39: =I38+H39 -> 153
H40: =SUM(E40:G40) -> 0 | I40: =I39+H40 -> 153

Sheet LOCAL.11
A2: Departamento : | B2: LOCAL 11
A3: Propietario : | B3: FELIX RAMIREZ
A4: Inquilino : | B4: =LOOKUP(B2,#REF!,#REF!) -> #REF!
A5: Teléfono : | B5: =LOOKUP(B2,#REF!,#REF!) -> #REF!
A6: Celular : | B6: =LOOKUP(B2,#REF!,#REF!) -> #REF!
A7: Correo : | B7: =LOOKUP(B2,#REF!,#REF!) -> #REF! | H7: Resumen
B8: FRESIA C. FLORES
A9: Fecha | B9: Concepto | C9: Recibo | D9: Expensas | E9: Agua | F9: Multa | G9: Total | H9: Deuda | I9: Pagado | J9: Columna1 | K9: Columna2
B10: DEUDA GESTION 2017-2020 | H10: 0 | I10: =IF(T_T1341112131415161718[[#This Row],[Total]]<0,T_T1341112131415161718[[#This Row],[Total]]*-1,0) -> 0 | M10: 300
B11: DEUDA GESTION 2021 | H11: 0 | I11: =IF(T_T1341112131415161718[[#This Row],[Total]]<0,T_T1341112131415161718[[#This Row],[Total]]*-1,0) -> 0
B12: DEUDA GESTION 2022 | H12: 0 | I12: =IF(T_T1341112131415161718[[#This Row],[Total]]<0,T_T1341112131415161718[[#This Row],[Total]]*-1,0) -> 0
B13: DEUDA GESTION 2023 | H13: 0 | I13: =IF(T_T1341112131415161718[[#This Row],[Total]]<0,T_T1341112131415161718[[#This Row],[Total]]*-1,0) -> 0
B14: DEUDA GESTION 2024 | I14: =IF(T_T1341112131415161718[[#This Row],[Total]]<0,T_T1341112131415161718[[#This Row],[Total]]*-1,0) -> 0
A15: 46052 | B15: Mantenimiento enero/2026 | D15: 69 | E15: 5 | G15: =SUM(D15:F15) -> 74 | H15: =+H13+T_T1341112131415161718[[#This Row],[Total]]+H10 -> 74 | I15: =IF(T_T1341112131415161718[[#This Row],[Total]]<0,T_T1341112131415161718[[#This Row],[Total]]*-1,0) -> 0
B16: Pago mantenimiento enero/2026 | C16: 8578 | D16: -69 | E16: -5 | G16: =SUM(D16:F16) -> -74 | H16: =H15+G16 -> 0 | I16: =IF(T_T1341112131415161718[[#This Row],[Total]]<0,T_T1341112131415161718[[#This Row],[Total]]*-1,0) -> 74
A17: 46080 | B17: Mantenimiento febrero/2026 | D17: 69 | E17: 5 | G17: =SUM(D17:F17) -> 74 | H17: =H16+G17 -> 74 | I17: =IF(T_T1341112131415161718[[#This Row],[Total]]<0,T_T1341112131415161718[[#This Row],[Total]]*-1,0) -> 0
B18: Pago mantenimiento febrero/2026 | C18: 8720 | D18: -69 | E18: -5 | G18: =SUM(D18:F18) -> -74 | H18: =H17+G18 -> 0 | I18: =IF(T_T1341112131415161718[[#This Row],[Total]]<0,T_T1341112131415161718[[#This Row],[Total]]*-1,0) -> 74
A19: 45747 | B19: Mantenimiento marzo/2025 | D19: 83 | E19: 5 | G19: =SUM(D19:F19) -> 88 | H19: =H18+G19 -> 88 | I19: =IF(T_T1341112131415161718[[#This Row],[Total]]<0,T_T1341112131415161718[[#This Row],[Total]]*-1,0) -> 0
B20: Pago matenimiento marzo/2025 | C20: 8830 | D20: -83 | E20: -5 | G20: =SUM(D20:F20) -> -88 | H20: =H19+G20 -> 0 | I20: =IF(T_T1341112131415161718[[#This Row],[Total]]<0,T_T1341112131415161718[[#This Row],[Total]]*-1,0) -> 88
A21: 45777 | B21: Mantenimiento abril/2025 | D21: 83 | E21: 5 | G21: =SUM(D21:F21) -> 88 | H21: =H20+G21 -> 88 | I21: =IF(T_T1341112131415161718[[#This Row],[Total]]<0,T_T1341112131415161718[[#This Row],[Total]]*-1,0) -> 0
B22: Pago mantenimiento abril/2025 | C22: 8953 | D22: -83 | E22: -5 | G22: =SUM(D22:F22) -> -88 | H22: =H21+G22 -> 0 | I22: =IF(T_T1341112131415161718[[#This Row],[Total]]<0,T_T1341112131415161718[[#This Row],[Total]]*-1,0) -> 88
A23: 45807 | B23: Mantenimiento mayo/2025 | D23: 83 | E23: 10 | G23: =SUM(D23:F23) -> 93 | H23: =H22+G23 -> 93 | I23: =IF(T_T1341112131415161718[[#This Row],[Total]]<0,T_T1341112131415161718[[#This Row],[Total]]*-1,0) -> 0
B24: Pago mantenimiento mayo/2025 | G24: =SUM(D24:F24) -> 0 | H24: =H23+G24 -> 93 | I24: =IF(T_T1341112131415161718[[#This Row],[Total]]<0,T_T1341112131415161718[[#This Row],[Total]]*-1,0) -> 0
A25: 45838 | B25: Mantenimiento junio/2025 | G25: =SUM(D25:F25) -> 0 | H25: =H24+G25 -> 93 | I25: =IF(T_T1341112131415161718[[#This Row],[Total]]<0,T_T1341112131415161718[[#This Row],[Total]]*-1,0) -> 0
B26: Pago mantenimiento junio/2025 | G26: =SUM(D26:F26) -> 0 | H26: =H25+G26 -> 93 | I26: =IF(T_T1341112131415161718[[#This Row],[Total]]<0,T_T1341112131415161718[[#This Row],[Total]]*-1,0) -> 0
A27: 45868 | B27: Mantenimiento julio/2025 | G27: =SUM(D27:F27) -> 0 | H27: =H26+G27 -> 93 | I27: =IF(T_T1341112131415161718[[#This Row],[Total]]<0,T_T1341112131415161718[[#This Row],[Total]]*-1,0) -> 0
B28: Pago mantenimient julio/2025 | G28: =SUM(D28:F28) -> 0 | H28: =H27+G28 -> 93 | I28: =IF(T_T1341112131415161718[[#This Row],[Total]]<0,T_T1341112131415161718[[#This Row],[Total]]*-1,0) -> 0
A29: 45899 | B29: Mantenimiento agosto/2025 | G29: =SUM(D29:F29) -> 0 | H29: =H28+G29 -> 93 | I29: =IF(T_T1341112131415161718[[#This Row],[Total]]<0,T_T1341112131415161718[[#This Row],[Total]]*-1,0) -> 0
B30: Pago mantenimiento agosto/2025 | G30: =SUM(D30:F30) -> 0 | H30: =H29+G30 -> 93 | I30: =IF(T_T1341112131415161718[[#This Row],[Total]]<0,T_T1341112131415161718[[#This Row],[Total]]*-1,0) -> 0
A31: 45930 | B31: Mantenimiento septiembre/2025 | G31: =SUM(D31:F31) -> 0 | H31: =H30+G31 -> 93 | I31: =IF(T_T1341112131415161718[[#This Row],[Total]]<0,T_T1341112131415161718[[#This Row],[Total]]*-1,0) -> 0
B32: Pago mantenimiento septiembre/2025 | G32: =SUM(D32:F32) -> 0 | H32: =H31+G32 -> 93 | I32: =IF(T_T1341112131415161718[[#This Row],[Total]]<0,T_T1341112131415161718[[#This Row],[Total]]*-1,0) -> 0
A33: 45960 | B33: Mantenimiento octubre /2025 | G33: =SUM(D33:F33) -> 0 | H33: =H32+G33 -> 93 | I33: =IF(T_T1341112131415161718[[#This Row],[Total]]<0,T_T1341112131415161718[[#This Row],[Total]]*-1,0) -> 0
B34: Pago mantenimiento octubre/2025 | G34: =SUM(D34:F34) -> 0 | H34: =H33+G34 -> 93 | I34: =IF(T_T1341112131415161718[[#This Row],[Total]]<0,T_T1341112131415161718[[#This Row],[Total]]*-1,0) -> 0
A35: 45991 | B35: Mantenimiento noviembre/2025 | G35: =SUM(D35:F35) -> 0 | H35: =H34+G35 -> 93 | I35: =IF(T_T1341112131415161718[[#This Row],[Total]]<0,T_T1341112131415161718[[#This Row],[Total]]*-1,0) -> 0
B36: Pago mantenimiento noviembre/2025 | G36: =SUM(D36:F36) -> 0 | H36: =H35+G36 -> 93 | I36: =IF(T_T1341112131415161718[[#This Row],[Total]]<0,T_T1341112131415161718[[#This Row],[Total]]*-1,0) -> 0
A37: 46021 | B37: Mantenimiento diciembre/2025 | G37: =SUM(D37:F37) -> 0 | H37: =H36+G37 -> 93 | I37: =IF(T_T1341112131415161718[[#This Row],[Total]]<0,T_T1341112131415161718[[#This Row],[Total]]*-1,0) -> 0
B38: Pago de Mantenimiento diciembre/2025 | G38: =SUM(D38:F38) -> 0 | H38: =H37+G38 -> 93 | I38: =IF(T_T1341112131415161718[[#This Row],[Total]]<0,T_T1341112131415161718[[#This Row],[Total]]*-1,0) -> 0
G39: =SUM(D39:F47) -> 0 | H39: =H38+G39 -> 93 | I39: =IF(T_T1341112131415161718[[#This Row],[Total]]<0,T_T1341112131415161718[[#This Row],[Total]]*-1,0) -> 0
G40: =SUM(D40:F48) -> 0 | H40: =H39+G40 -> 93 | I40: =IF(T_T1341112131415161718[[#This Row],[Total]]<0,T_T1341112131415161718[[#This Row],[Total]]*-1,0) -> 0
I41: =IF(T_T1341112131415161718[[#This Row],[Total]]<0,T_T1341112131415161718[[#This Row],[Total]]*-1,0) -> 0

Sheet LOCAL 12-13
A2: Departamento : | B2: LOCAL 12-13
A3: Propietario : | B3: SANDRA SORIANO
A4: Inquilino : | B4: =LOOKUP(B2,#REF!,#REF!) -> #REF!
A5: Teléfono : | B5: =LOOKUP(B2,#REF!,#REF!) -> #REF!
A6: Celular : | B6: =LOOKUP(B2,#REF!,#REF!) -> #REF!
A7: Correo : | B7: =LOOKUP(B2,#REF!,#REF!) -> #REF! | H7: Resumen
A9: Fecha | B9: Concepto | C9: Recibo | D9: Expensas | E9: Agua | F9: Multa | G9: Total | H9: Deuda | I9: Pagado
B10: DEUDA GESTION 2017-2020 | H10: 0 | I10: =IF(T_T13411[[#This Row],[Total]]<0,T_T13411[[#This Row],[Total]]*-1,0) -> 0
B11: DEUDA GESTION 2021 | H11: 0 | I11: =IF(T_T13411[[#This Row],[Total]]<0,T_T13411[[#This Row],[Total]]*-1,0) -> 0
B12: DEUDA GESTION 2022 | G12: =SUM(D12:F12) -> 0 | H12: =H11+G12 -> 0 | I12: =IF(T_T13411[[#This Row],[Total]]<0,T_T13411[[#This Row],[Total]]*-1,0) -> 0
B13: DEUDA GESTION 2023 | H13: 0 | I13: =IF(T_T13411[[#This Row],[Total]]<0,T_T13411[[#This Row],[Total]]*-1,0) -> 0
B14: DEUDA GESTION 2024 | G14: =SUM(D14:F14) -> 0 | H14: =H13+G14 -> 0 | I14: =IF(T_T13411[[#This Row],[Total]]<0,T_T13411[[#This Row],[Total]]*-1,0) -> 0
A15: 46052 | B15: Mantenimiento enero/2026 | D15: 350 | E15: 98 | G15: =SUM(D15:F15) -> 448 | H15: =+H13+T_T13411[[#This Row],[Total]] -> 448 | I15: =IF(T_T13411[[#This Row],[Total]]<0,T_T13411[[#This Row],[Total]]*-1,0) -> 0
B16: Pago mantenimiento enero/2026 | C16: 8582 | D16: -350 | E16: -98 | G16: =SUM(D16:F16) -> -448 | H16: =H15+G16 -> 0 | I16: =IF(T_T13411[[#This Row],[Total]]<0,T_T13411[[#This Row],[Total]]*-1,0) -> 448
A17: 45716 | B17: Mantenimiento febrero/2026 | D17: 350 | E17: 88 | G17: =SUM(D17:F17) -> 438 | H17: =H16+G17 -> 438 | I17: =IF(T_T13411[[#This Row],[Total]]<0,T_T13411[[#This Row],[Total]]*-1,0) -> 0
B18: Pago mantenimiento febrero/2026 | C18: 8783 | D18: -350 | E18: -88 | G18: =SUM(D18:F18) -> -438 | H18: =H17+G18 -> 0 | I18: =IF(T_T13411[[#This Row],[Total]]<0,T_T13411[[#This Row],[Total]]*-1,0) -> 438
A19: 45747 | B19: Mantenimiento marzo/2025 | D19: 420 | E19: 75 | G19: =SUM(D19:F19) -> 495 | H19: =H18+G19 -> 495 | I19: =IF(T_T13411[[#This Row],[Total]]<0,T_T13411[[#This Row],[Total]]*-1,0) -> 0
B20: Pago matenimiento marzo/2025 | C20: 8784 | D20: -420 | E20: -75 | G20: =SUM(D20:F20) -> -495 | H20: =H19+G20 -> 0 | I20: =IF(T_T13411[[#This Row],[Total]]<0,T_T13411[[#This Row],[Total]]*-1,0) -> 495
A21: 45777 | B21: Mantenimiento abril/2025 | D21: 420 | E21: 92 | G21: =SUM(D21:F21) -> 512 | H21: =H20+G21 -> 512 | I21: =IF(T_T13411[[#This Row],[Total]]<0,T_T13411[[#This Row],[Total]]*-1,0) -> 0
B22: Pago mantenimiento abril/2025 | C22: 8924 | D22: -420 | E22: -92 | G22: =SUM(D22:F22) -> -512 | H22: =H21+G22 -> 0 | I22: =IF(T_T13411[[#This Row],[Total]]<0,T_T13411[[#This Row],[Total]]*-1,0) -> 512
A23: 45807 | B23: Mantenimiento mayo/2025 | D23: 420 | E23: 86 | G23: =SUM(D23:F23) -> 506 | H23: =H22+G23 -> 506 | I23: =IF(T_T13411[[#This Row],[Total]]<0,T_T13411[[#This Row],[Total]]*-1,0) -> 0
B24: Pago mantenimiento mayo/2025 | G24: =SUM(D24:F24) -> 0 | H24: =H23+G24 -> 506 | I24: =IF(T_T13411[[#This Row],[Total]]<0,T_T13411[[#This Row],[Total]]*-1,0) -> 0
A25: 45838 | B25: Mantenimiento junio/2025 | G25: =SUM(D25:F25) -> 0 | H25: =H24+G25 -> 506 | I25: =IF(T_T13411[[#This Row],[Total]]<0,T_T13411[[#This Row],[Total]]*-1,0) -> 0
B26: Pago mantenimiento junio/2025 | G26: =SUM(D26:F26) -> 0 | H26: =H25+G26 -> 506 | I26: =IF(T_T13411[[#This Row],[Total]]<0,T_T13411[[#This Row],[Total]]*-1,0) -> 0
A27: 45868 | B27: Mantenimiento julio/2025 | G27: =SUM(D27:F27) -> 0 | H27: =H26+G27 -> 506 | I27: =IF(T_T13411[[#This Row],[Total]]<0,T_T13411[[#This Row],[Total]]*-1,0) -> 0
B28: Pago mantenimient julio/2025 | G28: =SUM(D28:F28) -> 0 | H28: =H27+G28 -> 506 | I28: =IF(T_T13411[[#This Row],[Total]]<0,T_T13411[[#This Row],[Total]]*-1,0) -> 0
A29: 45899 | B29: Mantenimiento agosto/2025 | G29: =SUM(D29:F29) -> 0 | H29: =H28+G29 -> 506 | I29: =IF(T_T13411[[#This Row],[Total]]<0,T_T13411[[#This Row],[Total]]*-1,0) -> 0
B30: Pago mantenimiento agosto/2025 | G30: =SUM(D30:F30) -> 0 | H30: =H29+G30 -> 506 | I30: =IF(T_T13411[[#This Row],[Total]]<0,T_T13411[[#This Row],[Total]]*-1,0) -> 0
A31: 45930 | B31: Mantenimiento septiembre/2025 | G31: =SUM(D31:F31) -> 0 | H31: =H30+G31 -> 506 | I31: =IF(T_T13411[[#This Row],[Total]]<0,T_T13411[[#This Row],[Total]]*-1,0) -> 0
B32: Pago mantenimiento septiembre/2025 | G32: =SUM(D32:F32) -> 0 | H32: =H31+G32 -> 506 | I32: =IF(T_T13411[[#This Row],[Total]]<0,T_T13411[[#This Row],[Total]]*-1,0) -> 0
A33: 45960 | B33: Mantenimiento octubre /2025 | G33: =SUM(D33:F33) -> 0 | H33: =H32+G33 -> 506 | I33: =IF(T_T13411[[#This Row],[Total]]<0,T_T13411[[#This Row],[Total]]*-1,0) -> 0
B34: Pago mantenimiento octubre/2025 | G34: =SUM(D34:F34) -> 0 | H34: =H33+G34 -> 506 | I34: =IF(T_T13411[[#This Row],[Total]]<0,T_T13411[[#This Row],[Total]]*-1,0) -> 0
A35: 45991 | B35: Mantenimiento noviembre/2025 | G35: =SUM(D35:F35) -> 0 | H35: =H34+G35 -> 506 | I35: =IF(T_T13411[[#This Row],[Total]]<0,T_T13411[[#This Row],[Total]]*-1,0) -> 0
B36: Pago mantenimiento noviembre/2025 | G36: =SUM(D36:F36) -> 0 | H36: =H35+G36 -> 506 | I36: =IF(T_T13411[[#This Row],[Total]]<0,T_T13411[[#This Row],[Total]]*-1,0) -> 0
A37: 46021 | B37: Mantenimiento diciembre/2025 | G37: =SUM(D37:F37) -> 0 | H37: =H36+G37 -> 506 | I37: =IF(T_T13411[[#This Row],[Total]]<0,T_T13411[[#This Row],[Total]]*-1,0) -> 0
B38: Pago de Mantenimiento diciembre/2025 | G38: =SUM(D38:F38) -> 0 | H38: =H37+G38 -> 506 | I38: =IF(T_T13411[[#This Row],[Total]]<0,T_T13411[[#This Row],[Total]]*-1,0) -> 0
G39: =SUM(D39:F46) -> 0 | H39: =H38+G39 -> 506 | I39: =IF(T_T13411[[#This Row],[Total]]<0,T_T13411[[#This Row],[Total]]*-1,0) -> 0
I40: =IF(T_T13411[[#This Row],[Total]]<0,T_T13411[[#This Row],[Total]]*-1,0) -> 0
I41: =IF(T_T13411[[#This Row],[Total]]<0,T_T13411[[#This Row],[Total]]*-1,0) -> 0
I42: =IF(T_T13411[[#This Row],[Total]]<0,T_T13411[[#This Row],[Total]]*-1,0) -> 0
I43: =IF(T_T13411[[#This Row],[Total]]<0,T_T13411[[#This Row],[Total]]*-1,0) -> 0
I44: =IF(T_T13411[[#This Row],[Total]]<0,T_T13411[[#This Row],[Total]]*-1,0) -> 0
I45: =IF(T_T13411[[#This Row],[Total]]<0,T_T13411[[#This Row],[Total]]*-1,0) -> 0
I46: =IF(T_T13411[[#This Row],[Total]]<0,T_T13411[[#This Row],[Total]]*-1,0) -> 0
I47: =IF(T_T13411[[#This Row],[Total]]<0,T_T13411[[#This Row],[Total]]*-1,0) -> 0
I48: =IF(T_T13411[[#This Row],[Total]]<0,T_T13411[[#This Row],[Total]]*-1,0) -> 0
I49: =IF(T_T13411[[#This Row],[Total]]<0,T_T13411[[#This Row],[Total]]*-1,0) -> 0
I50: =IF(T_T13411[[#This Row],[Total]]<0,T_T13411[[#This Row],[Total]]*-1,0) -> 0
I51: =IF(T_T13411[[#This Row],[Total]]<0,T_T13411[[#This Row],[Total]]*-1,0) -> 0
I52: =IF(T_T13411[[#This Row],[Total]]<0,T_T13411[[#This Row],[Total]]*-1,0) -> 0

Sheet LOCAL 14
A2: Departamento : | B2: LOCAL 14
A3: Propietario : | B3: =LOOKUP(B2,#REF!,#REF!) -> #REF!
A4: Inquilino : | B4: =LOOKUP(B2,#REF!,#REF!) -> #REF!
A5: Teléfono : | B5: =LOOKUP(B2,#REF!,#REF!) -> #REF!
A6: Celular : | B6: =LOOKUP(B2,#REF!,#REF!) -> #REF!
A7: Correo : | B7: =LOOKUP(B2,#REF!,#REF!) -> #REF! | H7: Resumen
A9: Fecha | B9: Concepto | C9: Recibo | D9: Expensas | E9: Agua | F9: Multa | G9: Total | H9: Deuda | I9: Pagado | J9: Columna1
B10: DEUDA GESTION 2017-2020 | H10: 0 | I10: =IF(T_T1341112[[#This Row],[Total]]<0,T_T1341112[[#This Row],[Total]]*-1,0) -> 0
B11: DEUDA GESTION 2021 | H11: =H10+G11 -> 0 | I11: =IF(T_T1341112[[#This Row],[Total]]<0,T_T1341112[[#This Row],[Total]]*-1,0) -> 0
B12: DEUDA GESTION 2022 | H12: =H11+G12 -> 0 | I12: =IF(T_T1341112[[#This Row],[Total]]<0,T_T1341112[[#This Row],[Total]]*-1,0) -> 0
B13: DEUDA GESTION 2023 | H13: =H11+G13 -> 0 | I13: =IF(T_T1341112[[#This Row],[Total]]<0,T_T1341112[[#This Row],[Total]]*-1,0) -> 0
B14: DEUDA GESTION 2024 | H14: =H13+G14 -> 0 | I14: =IF(T_T1341112[[#This Row],[Total]]<0,T_T1341112[[#This Row],[Total]]*-1,0) -> 0
A15: 46052 | B15: Mantenimiento enero/2026 | D15: 123 | E15: 10 | G15: =SUM(D15:F15) -> 133 | H15: =H13+G15 -> 133 | I15: =IF(T_T1341112[[#This Row],[Total]]<0,T_T1341112[[#This Row],[Total]]*-1,0) -> 0
B16: Pago mantenimiento enero/2026 | C16: 8556-8625 | D16: =-97-26 -> -123 | E16: -10 | G16: =SUM(D16:F16) -> -133 | H16: =H15+G16 -> 0 | I16: =IF(T_T1341112[[#This Row],[Total]]<0,T_T1341112[[#This Row],[Total]]*-1,0) -> 133
A17: 45715 | B17: Mantenimiento febrero/2025 | D17: 123 | E17: 10 | G17: =SUM(D17:F17) -> 133 | H17: =H16+G17 -> 133 | I17: =IF(T_T1341112[[#This Row],[Total]]<0,T_T1341112[[#This Row],[Total]]*-1,0) -> 0 | L17: silvia machicado perez-aluminios de bolivia
B18: Pago mantenimiento febrero/2025 | C18: 8737 | D18: =-26 -> -26 | G18: =SUM(D18:F18) -> -26 | H18: =H17+G18 -> 107 | I18: =IF(T_T1341112[[#This Row],[Total]]<0,T_T1341112[[#This Row],[Total]]*-1,0) -> 26
A19: 45747 | B19: Mantenimiento marzo/2025 | D19: 146 | E19: 15 | G19: =SUM(D19:F19) -> 161 | H19: =H18+G19 -> 268 | I19: =IF(T_T1341112[[#This Row],[Total]]<0,T_T1341112[[#This Row],[Total]]*-1,0) -> 0
B20: Pago matenimiento marzo/2025 | C20: 8816 | D20: =-30 -> -30 | G20: =SUM(D20:F20) -> -30 | H20: =H19+G20 -> 238 | I20: =IF(T_T1341112[[#This Row],[Total]]<0,T_T1341112[[#This Row],[Total]]*-1,0) -> 30
A21: 45777 | B21: Mantenimiento abril/2025 | D21: =116+30 -> 146 | E21: 15 | G21: =SUM(D21:F21) -> 161 | H21: =H20+G21 -> 399 | I21: =IF(T_T1341112[[#This Row],[Total]]<0,T_T1341112[[#This Row],[Total]]*-1,0) -> 0
B22: Pago mantenimiento abril/2025 | C22: 8952 | D22: -30 | G22: =SUM(D22:F22) -> -30 | H22: =H21+G22 -> 369 | I22: =IF(T_T1341112[[#This Row],[Total]]<0,T_T1341112[[#This Row],[Total]]*-1,0) -> 30
A23: 45807 | B23: Mantenimiento mayo/2025 | D23: 146 | E23: 15 | G23: =SUM(D23:F23) -> 161 | H23: =H22+G23 -> 530 | I23: =IF(T_T1341112[[#This Row],[Total]]<0,T_T1341112[[#This Row],[Total]]*-1,0) -> 0
B24: Pago mantenimiento mayo/2025 | G24: =SUM(D24:F24) -> 0 | H24: =H23+G24 -> 530 | I24: =IF(T_T1341112[[#This Row],[Total]]<0,T_T1341112[[#This Row],[Total]]*-1,0) -> 0
A25: 45838 | B25: Mantenimiento junio/2025 | G25: =SUM(D25:F25) -> 0 | H25: =H24+G25 -> 530 | I25: =IF(T_T1341112[[#This Row],[Total]]<0,T_T1341112[[#This Row],[Total]]*-1,0) -> 0
B26: Pago mantenimiento junio/2025 | G26: =SUM(D26:F26) -> 0 | H26: =H25+G26 -> 530 | I26: =IF(T_T1341112[[#This Row],[Total]]<0,T_T1341112[[#This Row],[Total]]*-1,0) -> 0
A27: 45868 | B27: Mantenimiento julio/2025 | G27: =SUM(D27:F27) -> 0 | H27: =H26+G27 -> 530 | I27: =IF(T_T1341112[[#This Row],[Total]]<0,T_T1341112[[#This Row],[Total]]*-1,0) -> 0
B28: Pago mantenimient julio/2025 | G28: =SUM(D28:F28) -> 0 | H28: =H27+G28 -> 530 | I28: =IF(T_T1341112[[#This Row],[Total]]<0,T_T1341112[[#This Row],[Total]]*-1,0) -> 0
A29: 45899 | B29: Mantenimiento agosto/2025 | G29: =SUM(D29:F29) -> 0 | H29: =H28+G29 -> 530 | I29: =IF(T_T1341112[[#This Row],[Total]]<0,T_T1341112[[#This Row],[Total]]*-1,0) -> 0
B30: Pago mantenimiento agosto/2025 | G30: =SUM(D30:F30) -> 0 | H30: =H29+G30 -> 530 | I30: =IF(T_T1341112[[#This Row],[Total]]<0,T_T1341112[[#This Row],[Total]]*-1,0) -> 0
A31: 45930 | B31: Mantenimiento septiembre/2025 | G31: =SUM(D31:F31) -> 0 | H31: =H30+G31 -> 530 | I31: =IF(T_T1341112[[#This Row],[Total]]<0,T_T1341112[[#This Row],[Total]]*-1,0) -> 0
B32: Pago mantenimiento septiembre/2025 | G32: =SUM(D32:F32) -> 0 | H32: =H31+G32 -> 530 | I32: =IF(T_T1341112[[#This Row],[Total]]<0,T_T1341112[[#This Row],[Total]]*-1,0) -> 0
A33: 45960 | B33: Mantenimiento octubre /2025 | G33: =SUM(D33:F33) -> 0 | H33: =H32+G33 -> 530 | I33: =IF(T_T1341112[[#This Row],[Total]]<0,T_T1341112[[#This Row],[Total]]*-1,0) -> 0
B34: Pago mantenimiento octubre/2025 | G34: =SUM(D34:F34) -> 0 | H34: =H33+G34 -> 530 | I34: =IF(T_T1341112[[#This Row],[Total]]<0,T_T1341112[[#This Row],[Total]]*-1,0) -> 0
A35: 45991 | B35: Mantenimiento noviembre/2025 | G35: =SUM(D35:F35) -> 0 | H35: =H34+G35 -> 530 | I35: =IF(T_T1341112[[#This Row],[Total]]<0,T_T1341112[[#This Row],[Total]]*-1,0) -> 0
B36: Pago mantenimiento noviembre/2025 | G36: =SUM(D36:F36) -> 0 | H36: =H35+G36 -> 530 | I36: =IF(T_T1341112[[#This Row],[Total]]<0,T_T1341112[[#This Row],[Total]]*-1,0) -> 0
A37: 46021 | B37: Mantenimiento diciembre/2025 | G37: =SUM(D37:F37) -> 0 | H37: =H36+G37 -> 530 | I37: =IF(T_T1341112[[#This Row],[Total]]<0,T_T1341112[[#This Row],[Total]]*-1,0) -> 0
B38: Pago de Mantenimiento diciembre/2025 | G38: =SUM(D38:F38) -> 0 | H38: =H37+G38 -> 530 | I38: =IF(T_T1341112[[#This Row],[Total]]<0,T_T1341112[[#This Row],[Total]]*-1,0) -> 0
G39: =SUM(D39:F46) -> 0 | H39: =H38+G39 -> 530 | I39: =IF(T_T1341112[[#This Row],[Total]]<0,T_T1341112[[#This Row],[Total]]*-1,0) -> 0
G40: =SUM(D40:F47) -> 0 | H40: =H39+G40 -> 530 | I40: =IF(T_T1341112[[#This Row],[Total]]<0,T_T1341112[[#This Row],[Total]]*-1,0) -> 0

Sheet LOCAL 15
A2: Departamento : | B2: LOCAL 15
A3: Propietario : | B3: =LOOKUP(B2,#REF!,#REF!) -> #REF!
A4: Inquilino : | B4: =LOOKUP(B2,#REF!,#REF!) -> #REF!
A5: Teléfono : | B5: =LOOKUP(B2,#REF!,#REF!) -> #REF!
A6: Celular : | B6: =LOOKUP(B2,#REF!,#REF!) -> #REF!
A7: Correo : | B7: =LOOKUP(B2,#REF!,#REF!) -> #REF! | H7: Resumen
A9: Fecha | B9: Concepto | C9: Recibo | D9: Expensas | E9: Agua | F9: Multa | G9: Total | H9: Deuda | I9: Pagado | J9: Columna1
B10: DEUDA GESTION 2017-2020 | I10: =IF(T_T134111213[[#This Row],[Total]]<0,T_T134111213[[#This Row],[Total]]*-1,0) -> 0
B11: DEUDA GESTION 2021 | I11: =IF(T_T134111213[[#This Row],[Total]]<0,T_T134111213[[#This Row],[Total]]*-1,0) -> 0
B12: DEUDA GESTION 2022 | H12: 0 | I12: =IF(T_T134111213[[#This Row],[Total]]<0,T_T134111213[[#This Row],[Total]]*-1,0) -> 0
B13: DEUDA GESTION 2023 | H13: 0 | I13: =IF(T_T134111213[[#This Row],[Total]]<0,T_T134111213[[#This Row],[Total]]*-1,0) -> 0
B14: DEUDA GESTION 2024 | I14: =IF(T_T134111213[[#This Row],[Total]]<0,T_T134111213[[#This Row],[Total]]*-1,0) -> 0
A15: 46052 | B15: Mantenimiento enero/2026 | D15: 181 | E15: 10 | G15: =SUM(D15:F15) -> 191 | H15: =+H13+T_T134111213[[#This Row],[Total]]+H12 -> 191 | I15: =IF(T_T134111213[[#This Row],[Total]]<0,T_T134111213[[#This Row],[Total]]*-1,0) -> 0
B16: Pago mantenimiento enero/2026 | C16: 8825 | D16: -181 | E16: -10 | G16: =SUM(D16:F16) -> -191 | H16: =H15+G16 -> 0 | I16: =IF(T_T134111213[[#This Row],[Total]]<0,T_T134111213[[#This Row],[Total]]*-1,0) -> 191
A17: 45716 | B17: Mantenimiento febrero/2026 | D17: 181 | E17: 10 | G17: =SUM(D17:F17) -> 191 | H17: =H16+G17 -> 191 | I17: =IF(T_T134111213[[#This Row],[Total]]<0,T_T134111213[[#This Row],[Total]]*-1,0) -> 0
B18: Pago mantenimiento febrero/2026 | C18: 8825 | D18: -181 | E18: -10 | G18: =SUM(D18:F18) -> -191 | H18: =H17+G18 -> 0 | I18: =IF(T_T134111213[[#This Row],[Total]]<0,T_T134111213[[#This Row],[Total]]*-1,0) -> 191
A19: 45747 | B19: Mantenimiento marzo/2025 | D19: 217 | E19: 15 | G19: =SUM(D19:F19) -> 232 | H19: =H18+G19 -> 232 | I19: =IF(T_T134111213[[#This Row],[Total]]<0,T_T134111213[[#This Row],[Total]]*-1,0) -> 0
B20: Pago matenimiento marzo/2025 | C20: 8825 | D20: -217 | E20: -15 | G20: =SUM(D20:F20) -> -232 | H20: =H19+G20 -> 0 | I20: =IF(T_T134111213[[#This Row],[Total]]<0,T_T134111213[[#This Row],[Total]]*-1,0) -> 232
A21: 45777 | B21: Mantenimiento abril/2025 | D21: 217 | E21: 15 | G21: =SUM(D21:F21) -> 232 | H21: =H20+G21 -> 232 | I21: =IF(T_T134111213[[#This Row],[Total]]<0,T_T134111213[[#This Row],[Total]]*-1,0) -> 0
B22: Pago mantenimiento abril/2025 | C22: 8946 | D22: -217 | E22: -15 | G22: =SUM(D22:F22) -> -232 | H22: =H21+G22 -> 0 | I22: =IF(T_T134111213[[#This Row],[Total]]<0,T_T134111213[[#This Row],[Total]]*-1,0) -> 232
A23: 45807 | B23: Mantenimiento mayo/2025 | D23: 217 | E23: 10 | G23: =SUM(D23:F23) -> 227 | H23: =H22+G23 -> 227 | I23: =IF(T_T134111213[[#This Row],[Total]]<0,T_T134111213[[#This Row],[Total]]*-1,0) -> 0
B24: Pago mantenimiento mayo/2025 | G24: =SUM(D24:F24) -> 0 | H24: =H23+G24 -> 227 | I24: =IF(T_T134111213[[#This Row],[Total]]<0,T_T134111213[[#This Row],[Total]]*-1,0) -> 0
A25: 45838 | B25: Mantenimiento junio/2025 | G25: =SUM(D25:F25) -> 0 | H25: =H24+G25 -> 227 | I25: =IF(T_T134111213[[#This Row],[Total]]<0,T_T134111213[[#This Row],[Total]]*-1,0) -> 0
B26: Pago mantenimiento junio/2025 | G26: =SUM(D26:F26) -> 0 | H26: =H25+G26 -> 227 | I26: =IF(T_T134111213[[#This Row],[Total]]<0,T_T134111213[[#This Row],[Total]]*-1,0) -> 0
A27: 45868 | B27: Mantenimiento julio/2025 | G27: =SUM(D27:F27) -> 0 | H27: =H26+G27 -> 227 | I27: =IF(T_T134111213[[#This Row],[Total]]<0,T_T134111213[[#This Row],[Total]]*-1,0) -> 0
B28: Pago mantenimient julio/2025 | G28: =SUM(D28:F28) -> 0 | H28: =H27+G28 -> 227 | I28: =IF(T_T134111213[[#This Row],[Total]]<0,T_T134111213[[#This Row],[Total]]*-1,0) -> 0
A29: 45899 | B29: Mantenimiento agosto/2025 | G29: =SUM(D29:F29) -> 0 | H29: =H28+G29 -> 227 | I29: =IF(T_T134111213[[#This Row],[Total]]<0,T_T134111213[[#This Row],[Total]]*-1,0) -> 0
B30: Pago mantenimiento agosto/2025 | G30: =SUM(D30:F30) -> 0 | H30: =H29+G30 -> 227 | I30: =IF(T_T134111213[[#This Row],[Total]]<0,T_T134111213[[#This Row],[Total]]*-1,0) -> 0
A31: 45930 | B31: Mantenimiento septiembre/2025 | G31: =SUM(D31:F31) -> 0 | H31: =H30+G31 -> 227 | I31: =IF(T_T134111213[[#This Row],[Total]]<0,T_T134111213[[#This Row],[Total]]*-1,0) -> 0
B32: Pago mantenimiento septiembre/2025 | G32: =SUM(D32:F32) -> 0 | H32: =H31+G32 -> 227 | I32: =IF(T_T134111213[[#This Row],[Total]]<0,T_T134111213[[#This Row],[Total]]*-1,0) -> 0
A33: 45960 | B33: Mantenimiento octubre /2025 | G33: =SUM(D33:F33) -> 0 | H33: =H32+G33 -> 227 | I33: =IF(T_T134111213[[#This Row],[Total]]<0,T_T134111213[[#This Row],[Total]]*-1,0) -> 0
B34: Pago mantenimiento octubre/2025 | G34: =SUM(D34:F34) -> 0 | H34: =H33+G34 -> 227 | I34: =IF(T_T134111213[[#This Row],[Total]]<0,T_T134111213[[#This Row],[Total]]*-1,0) -> 0
A35: 45991 | B35: Mantenimiento noviembre/2025 | G35: =SUM(D35:F35) -> 0 | H35: =H34+G35 -> 227 | I35: =IF(T_T134111213[[#This Row],[Total]]<0,T_T134111213[[#This Row],[Total]]*-1,0) -> 0
B36: Pago mantenimiento noviembre/2025 | G36: =SUM(D36:F36) -> 0 | H36: =H35+G36 -> 227 | I36: =IF(T_T134111213[[#This Row],[Total]]<0,T_T134111213[[#This Row],[Total]]*-1,0) -> 0
A37: 46021 | B37: Mantenimiento diciembre/2025 | G37: =SUM(D37:F37) -> 0 | H37: =H36+G37 -> 227 | I37: =IF(T_T134111213[[#This Row],[Total]]<0,T_T134111213[[#This Row],[Total]]*-1,0) -> 0
B38: Pago de Mantenimiento diciembre/2025 | G38: =SUM(D38:F38) -> 0 | H38: =H37+G38 -> 227 | I38: =IF(T_T134111213[[#This Row],[Total]]<0,T_T134111213[[#This Row],[Total]]*-1,0) -> 0
G39: =SUM(D39:F47) -> 0 | H39: =H38+G39 -> 227 | I39: =IF(T_T134111213[[#This Row],[Total]]<0,T_T134111213[[#This Row],[Total]]*-1,0) -> 0
I40: =IF(T_T134111213[[#This Row],[Total]]<0,T_T134111213[[#This Row],[Total]]*-1,0) -> 0
I41: =IF(T_T134111213[[#This Row],[Total]]<0,T_T134111213[[#This Row],[Total]]*-1,0) -> 0

Sheet LOCAL 16
A2: Departamento : | B2: LOCAL 16
A3: Propietario : | B3: =LOOKUP(B2,#REF!,#REF!) -> #REF!
A4: Inquilino : | B4: =LOOKUP(B2,#REF!,#REF!) -> #REF!
A5: Teléfono : | B5: =LOOKUP(B2,#REF!,#REF!) -> #REF!
A6: Celular : | B6: =LOOKUP(B2,#REF!,#REF!) -> #REF!
A7: Correo : | B7: =LOOKUP(B2,#REF!,#REF!) -> #REF! | H7: Resumen
A9: Fecha | B9: Concepto | C9: Recibo | D9: Expensas | E9: Agua | F9: Multa | G9: Total | H9: Deuda | I9: Pagado
B10: DEUDA GESTION 2017-2020 | H10: 0 | I10: =IF(T_T13411121314[[#This Row],[Total]]<0,T_T13411121314[[#This Row],[Total]]*-1,0) -> 0
B11: DEUDA GESTION 2021 | H11: 0 | I11: =IF(T_T13411121314[[#This Row],[Total]]<0,T_T13411121314[[#This Row],[Total]]*-1,0) -> 0
B12: DEUDA GESTION 2022 | H12: 0 | I12: =IF(T_T13411121314[[#This Row],[Total]]<0,T_T13411121314[[#This Row],[Total]]*-1,0) -> 0
B13: DEUDA GESTION 2023 | H13: 0 | I13: =IF(T_T13411121314[[#This Row],[Total]]<0,T_T13411121314[[#This Row],[Total]]*-1,0) -> 0
B14: DEUDA GESTION 2024 | I14: =IF(T_T13411121314[[#This Row],[Total]]<0,T_T13411121314[[#This Row],[Total]]*-1,0) -> 0
A15: 46052 | B15: Mantenimiento enero/2026 | D15: 93 | E15: 10 | G15: =SUM(D15:F15) -> 103 | H15: =+H13+T_T13411121314[[#This Row],[Total]] -> 103 | I15: =IF(T_T13411121314[[#This Row],[Total]]<0,T_T13411121314[[#This Row],[Total]]*-1,0) -> 0
B16: Pago mantenimiento enero/2026 | C16: 8568 | D16: -93 | E16: -10 | G16: =SUM(D16:F16) -> -103 | H16: =H15+G16 -> 0 | I16: =IF(T_T13411121314[[#This Row],[Total]]<0,T_T13411121314[[#This Row],[Total]]*-1,0) -> 103
A17: 45716 | B17: Mantenimiento febrero/2026 | D17: 93 | E17: 10 | G17: =SUM(D17:F17) -> 103 | H17: =H16+G17 -> 103 | I17: =IF(T_T13411121314[[#This Row],[Total]]<0,T_T13411121314[[#This Row],[Total]]*-1,0) -> 0
B18: Pago mantenimiento febrero/2026 | C18: 8760 | D18: -93 | E18: -10 | G18: =SUM(D18:F18) -> -103 | H18: =H17+G18 -> 0 | I18: =IF(T_T13411121314[[#This Row],[Total]]<0,T_T13411121314[[#This Row],[Total]]*-1,0) -> 103
A19: 45747 | B19: Mantenimiento marzo/2025 | D19: 111 | E19: 15 | G19: =SUM(D19:F19) -> 126 | H19: =H18+G19 -> 126 | I19: =IF(T_T13411121314[[#This Row],[Total]]<0,T_T13411121314[[#This Row],[Total]]*-1,0) -> 0
B20: Pago matenimiento marzo/2025 | C20: 8936 | D20: -111 | E20: -15 | G20: =SUM(D20:F20) -> -126 | H20: =H19+G20 -> 0 | I20: =IF(T_T13411121314[[#This Row],[Total]]<0,T_T13411121314[[#This Row],[Total]]*-1,0) -> 126
A21: 45777 | B21: Mantenimiento abril/2025 | D21: 111 | E21: 15 | G21: =SUM(D21:F21) -> 126 | H21: =H20+G21 -> 126 | I21: =IF(T_T13411121314[[#This Row],[Total]]<0,T_T13411121314[[#This Row],[Total]]*-1,0) -> 0
B22: Pago mantenimiento abril/2025 | C22: 8936 | D22: -111 | E22: -15 | G22: =SUM(D22:F22) -> -126 | H22: =H21+G22 -> 0 | I22: =IF(T_T13411121314[[#This Row],[Total]]<0,T_T13411121314[[#This Row],[Total]]*-1,0) -> 126
A23: 45807 | B23: Mantenimiento mayo/2025 | D23: 111 | E23: 15 | G23: =SUM(D23:F23) -> 126 | H23: =H22+G23 -> 126 | I23: =IF(T_T13411121314[[#This Row],[Total]]<0,T_T13411121314[[#This Row],[Total]]*-1,0) -> 0
B24: Pago mantenimiento mayo/2025 | G24: =SUM(D24:F24) -> 0 | H24: =H23+G24 -> 126 | I24: =IF(T_T13411121314[[#This Row],[Total]]<0,T_T13411121314[[#This Row],[Total]]*-1,0) -> 0
A25: 45838 | B25: Mantenimiento junio/2025 | G25: =SUM(D25:F25) -> 0 | H25: =H24+G25 -> 126 | I25: =IF(T_T13411121314[[#This Row],[Total]]<0,T_T13411121314[[#This Row],[Total]]*-1,0) -> 0
B26: Pago mantenimiento junio/2025 | G26: =SUM(D26:F26) -> 0 | H26: =H25+G26 -> 126 | I26: =IF(T_T13411121314[[#This Row],[Total]]<0,T_T13411121314[[#This Row],[Total]]*-1,0) -> 0
A27: 45868 | B27: Mantenimiento julio/2025 | G27: =SUM(D27:F27) -> 0 | H27: =H26+G27 -> 126 | I27: =IF(T_T13411121314[[#This Row],[Total]]<0,T_T13411121314[[#This Row],[Total]]*-1,0) -> 0
B28: Pago mantenimient julio/2025 | G28: =SUM(D28:F28) -> 0 | H28: =H27+G28 -> 126 | I28: =IF(T_T13411121314[[#This Row],[Total]]<0,T_T13411121314[[#This Row],[Total]]*-1,0) -> 0
A29: 45899 | B29: Mantenimiento agosto/2025 | G29: =SUM(D29:F29) -> 0 | H29: =H28+G29 -> 126 | I29: =IF(T_T13411121314[[#This Row],[Total]]<0,T_T13411121314[[#This Row],[Total]]*-1,0) -> 0
B30: Pago mantenimiento agosto/2025 | G30: =SUM(D30:F30) -> 0 | H30: =H29+G30 -> 126 | I30: =IF(T_T13411121314[[#This Row],[Total]]<0,T_T13411121314[[#This Row],[Total]]*-1,0) -> 0
A31: 45930 | B31: Mantenimiento septiembre/2025 | G31: =SUM(D31:F31) -> 0 | H31: =H30+G31 -> 126 | I31: =IF(T_T13411121314[[#This Row],[Total]]<0,T_T13411121314[[#This Row],[Total]]*-1,0) -> 0
B32: Pago mantenimiento septiembre/2025 | G32: =SUM(D32:F32) -> 0 | H32: =H31+G32 -> 126 | I32: =IF(T_T13411121314[[#This Row],[Total]]<0,T_T13411121314[[#This Row],[Total]]*-1,0) -> 0
A33: 45960 | B33: Mantenimiento octubre /2025 | G33: =SUM(D33:F33) -> 0 | H33: =H32+G33 -> 126 | I33: =IF(T_T13411121314[[#This Row],[Total]]<0,T_T13411121314[[#This Row],[Total]]*-1,0) -> 0
B34: Pago mantenimiento octubre/2025 | G34: =SUM(D34:F34) -> 0 | H34: =H33+G34 -> 126 | I34: =IF(T_T13411121314[[#This Row],[Total]]<0,T_T13411121314[[#This Row],[Total]]*-1,0) -> 0
A35: 45991 | B35: Mantenimiento noviembre/2025 | G35: =SUM(D35:F35) -> 0 | H35: =H34+G35 -> 126 | I35: =IF(T_T13411121314[[#This Row],[Total]]<0,T_T13411121314[[#This Row],[Total]]*-1,0) -> 0
B36: Pago mantenimiento noviembre/2025 | G36: =SUM(D36:F36) -> 0 | H36: =H35+G36 -> 126 | I36: =IF(T_T13411121314[[#This Row],[Total]]<0,T_T13411121314[[#This Row],[Total]]*-1,0) -> 0
A37: 46021 | B37: Mantenimiento diciembre/2025 | G37: =SUM(D37:F37) -> 0 | H37: =H36+G37 -> 126 | I37: =IF(T_T13411121314[[#This Row],[Total]]<0,T_T13411121314[[#This Row],[Total]]*-1,0) -> 0
B38: Pago de Mantenimiento diciembre/2025 | G38: =SUM(D38:F38) -> 0 | H38: =H37+G38 -> 126 | I38: =IF(T_T13411121314[[#This Row],[Total]]<0,T_T13411121314[[#This Row],[Total]]*-1,0) -> 0
G39: =SUM(D39:F47) -> 0 | H39: =H38+G39 -> 126 | I39: =IF(T_T13411121314[[#This Row],[Total]]<0,T_T13411121314[[#This Row],[Total]]*-1,0) -> 0
G40: =SUM(D40:F48) -> 0 | H40: =H39+G40 -> 126 | I40: =IF(T_T13411121314[[#This Row],[Total]]<0,T_T13411121314[[#This Row],[Total]]*-1,0) -> 0
I41: =IF(T_T13411121314[[#This Row],[Total]]<0,T_T13411121314[[#This Row],[Total]]*-1,0) -> 0

Sheet LOCAL 17
A2: Departamento : | B2: LOCAL 17
A3: Propietario : | B3: =LOOKUP(B2,#REF!,#REF!) -> #REF!
A4: Inquilino : | B4: =LOOKUP(B2,#REF!,#REF!) -> #REF!
A5: Teléfono : | B5: =LOOKUP(B2,#REF!,#REF!) -> #REF!
A6: Celular : | B6: =LOOKUP(B2,#REF!,#REF!) -> #REF!
A7: Correo : | B7: =LOOKUP(B2,#REF!,#REF!) -> #REF! | H7: Resumen
A9: Fecha | B9: Concepto | C9: Recibo | D9: Expensas | E9: Agua | F9: Multa | G9: Total | H9: Deuda | I9: Pagado
B10: DEUDA GESTION 2017-2020 | H10: 0 | I10: =IF(T_T1341112131415[[#This Row],[Total]]<0,T_T1341112131415[[#This Row],[Total]]*-1,0) -> 0
B11: DEUDA GESTION 2021 | H11: 0 | I11: =IF(T_T1341112131415[[#This Row],[Total]]<0,T_T1341112131415[[#This Row],[Total]]*-1,0) -> 0
B12: DEUDA GESTION 2022 | H12: 0 | I12: =IF(T_T1341112131415[[#This Row],[Total]]<0,T_T1341112131415[[#This Row],[Total]]*-1,0) -> 0
B13: DEUDA GESTION 2023 | H13: 0 | I13: =IF(T_T1341112131415[[#This Row],[Total]]<0,T_T1341112131415[[#This Row],[Total]]*-1,0) -> 0
B14: DEUDA GESTION 2024 | I14: =IF(T_T1341112131415[[#This Row],[Total]]<0,T_T1341112131415[[#This Row],[Total]]*-1,0) -> 0
A15: 46052 | B15: Mantenimiento enero/2026 | D15: 70 | E15: 10 | G15: =SUM(D15:F15) -> 80 | H15: =+H13+T_T1341112131415[[#This Row],[Total]] -> 80 | I15: =IF(T_T1341112131415[[#This Row],[Total]]<0,T_T1341112131415[[#This Row],[Total]]*-1,0) -> 0 | K15: DALETH ROMERO
B16: Pago mantenimiento enero/2026 | C16: 8594 | D16: -70 | E16: -10 | G16: =SUM(D16:F16) -> -80 | H16: =H15+G16 -> 0 | I16: =IF(T_T1341112131415[[#This Row],[Total]]<0,T_T1341112131415[[#This Row],[Total]]*-1,0) -> 80
A17: 45715 | B17: Mantenimiento febrero/2025 | D17: 70 | E17: 10 | G17: =SUM(D17:F17) -> 80 | H17: =H16+G17 -> 80 | I17: =IF(T_T1341112131415[[#This Row],[Total]]<0,T_T1341112131415[[#This Row],[Total]]*-1,0) -> 0
B18: Pago mantenimiento febrero/2025 | C18: 8674 | D18: -70 | E18: -10 | G18: =SUM(D18:F18) -> -80 | H18: =H17+G18 -> 0 | I18: =IF(T_T1341112131415[[#This Row],[Total]]<0,T_T1341112131415[[#This Row],[Total]]*-1,0) -> 80
A19: 45747 | B19: Mantenimiento marzo/2025 | D19: 84 | E19: 15 | G19: =SUM(D19:F19) -> 99 | H19: =H18+G19 -> 99 | I19: =IF(T_T1341112131415[[#This Row],[Total]]<0,T_T1341112131415[[#This Row],[Total]]*-1,0) -> 0
B20: Pago matenimiento marzo/2025 | C20: 8856 | D20: -84 | E20: -15 | G20: =SUM(D20:F20) -> -99 | H20: =H19+G20 -> 0 | I20: =IF(T_T1341112131415[[#This Row],[Total]]<0,T_T1341112131415[[#This Row],[Total]]*-1,0) -> 99
A21: 45777 | B21: Mantenimiento abril/2025 | D21: 84 | E21: 15 | G21: =SUM(D21:F21) -> 99 | H21: =H20+G21 -> 99 | I21: =IF(T_T1341112131415[[#This Row],[Total]]<0,T_T1341112131415[[#This Row],[Total]]*-1,0) -> 0
B22: Pago mantenimiento abril/2025 | C22: 8943 | D22: -84 | E22: -15 | G22: =SUM(D22:F22) -> -99 | H22: =H21+G22 -> 0 | I22: =IF(T_T1341112131415[[#This Row],[Total]]<0,T_T1341112131415[[#This Row],[Total]]*-1,0) -> 99
A23: 45807 | B23: Mantenimiento mayo/2025 | D23: 84 | E23: 10 | G23: =SUM(D23:F23) -> 94 | H23: =H22+G23 -> 94 | I23: =IF(T_T1341112131415[[#This Row],[Total]]<0,T_T1341112131415[[#This Row],[Total]]*-1,0) -> 0
B24: Pago mantenimiento mayo/2025 | G24: =SUM(D24:F24) -> 0 | H24: =H23+G24 -> 94 | I24: =IF(T_T1341112131415[[#This Row],[Total]]<0,T_T1341112131415[[#This Row],[Total]]*-1,0) -> 0
A25: 45838 | B25: Mantenimiento junio/2025 | G25: =SUM(D25:F25) -> 0 | H25: =H24+G25 -> 94 | I25: =IF(T_T1341112131415[[#This Row],[Total]]<0,T_T1341112131415[[#This Row],[Total]]*-1,0) -> 0
B26: Pago mantenimiento junio/2025 | G26: =SUM(D26:F26) -> 0 | H26: =H25+G26 -> 94 | I26: =IF(T_T1341112131415[[#This Row],[Total]]<0,T_T1341112131415[[#This Row],[Total]]*-1,0) -> 0
A27: 45868 | B27: Mantenimiento julio/2025 | G27: =SUM(D27:F27) -> 0 | H27: =H26+G27 -> 94 | I27: =IF(T_T1341112131415[[#This Row],[Total]]<0,T_T1341112131415[[#This Row],[Total]]*-1,0) -> 0
B28: Pago mantenimient julio/2025 | G28: =SUM(D28:F28) -> 0 | H28: =H27+G28 -> 94 | I28: =IF(T_T1341112131415[[#This Row],[Total]]<0,T_T1341112131415[[#This Row],[Total]]*-1,0) -> 0
A29: 45899 | B29: Mantenimiento agosto/2025 | G29: =SUM(D29:F29) -> 0 | H29: =H28+G29 -> 94 | I29: =IF(T_T1341112131415[[#This Row],[Total]]<0,T_T1341112131415[[#This Row],[Total]]*-1,0) -> 0
B30: Pago mantenimiento agosto/2025 | G30: =SUM(D30:F30) -> 0 | H30: =H29+G30 -> 94 | I30: =IF(T_T1341112131415[[#This Row],[Total]]<0,T_T1341112131415[[#This Row],[Total]]*-1,0) -> 0
A31: 45930 | B31: Mantenimiento septiembre/2025 | G31: =SUM(D31:F31) -> 0 | H31: =H30+G31 -> 94 | I31: =IF(T_T1341112131415[[#This Row],[Total]]<0,T_T1341112131415[[#This Row],[Total]]*-1,0) -> 0
B32: Pago mantenimiento septiembre/2025 | G32: =SUM(D32:F32) -> 0 | H32: =H31+G32 -> 94 | I32: =IF(T_T1341112131415[[#This Row],[Total]]<0,T_T1341112131415[[#This Row],[Total]]*-1,0) -> 0
A33: 45960 | B33: Mantenimiento octubre /2025 | G33: =SUM(D33:F33) -> 0 | H33: =H32+G33 -> 94 | I33: =IF(T_T1341112131415[[#This Row],[Total]]<0,T_T1341112131415[[#This Row],[Total]]*-1,0) -> 0
B34: Pago mantenimiento octubre/2025 | G34: =SUM(D34:F34) -> 0 | H34: =H33+G34 -> 94 | I34: =IF(T_T1341112131415[[#This Row],[Total]]<0,T_T1341112131415[[#This Row],[Total]]*-1,0) -> 0
A35: 45991 | B35: Mantenimiento noviembre/2025 | G35: =SUM(D35:F35) -> 0 | H35: =H34+G35 -> 94 | I35: =IF(T_T1341112131415[[#This Row],[Total]]<0,T_T1341112131415[[#This Row],[Total]]*-1,0) -> 0
B36: Pago mantenimiento noviembre/2025 | G36: =SUM(D36:F36) -> 0 | H36: =H35+G36 -> 94 | I36: =IF(T_T1341112131415[[#This Row],[Total]]<0,T_T1341112131415[[#This Row],[Total]]*-1,0) -> 0
A37: 46021 | B37: Mantenimiento diciembre/2025 | G37: =SUM(D37:F37) -> 0 | H37: =H36+G37 -> 94 | I37: =IF(T_T1341112131415[[#This Row],[Total]]<0,T_T1341112131415[[#This Row],[Total]]*-1,0) -> 0
B38: Pago de Mantenimiento diciembre/2025 | G38: =SUM(D38:F38) -> 0 | H38: =H37+G38 -> 94 | I38: =IF(T_T1341112131415[[#This Row],[Total]]<0,T_T1341112131415[[#This Row],[Total]]*-1,0) -> 0
G39: =SUM(D39:F46) -> 0 | H39: =H38+G39 -> 94 | I39: =IF(T_T1341112131415[[#This Row],[Total]]<0,T_T1341112131415[[#This Row],[Total]]*-1,0) -> 0
G40: =SUM(D40:F47) -> 0 | H40: =H39+G40 -> 94 | I40: =IF(T_T1341112131415[[#This Row],[Total]]<0,T_T1341112131415[[#This Row],[Total]]*-1,0) -> 0
D44: =+T_T1341112131415[[#Totals],[Expensas]]-D43 -> 0 | E44: =+T_T1341112131415[[#Totals],[Expensas]]-E43 -> 0

Sheet LOCAL 18
A2: Departamento : | B2: LOCAL 18
A3: Propietario : | B3: MARTHA HOYOS RODAS
A4: Inquilino : | B4: =LOOKUP(B2,#REF!,#REF!) -> #REF!
A5: Teléfono : | B5: =LOOKUP(B2,#REF!,#REF!) -> #REF!
A6: Celular : | B6: =LOOKUP(B2,#REF!,#REF!) -> #REF!
A7: Correo : | B7: =LOOKUP(B2,#REF!,#REF!) -> #REF! | H7: Resumen
A9: Fecha | B9: Concepto | C9: Recibo | D9: Expensas | E9: Agua | F9: Multa | G9: Total | H9: Deuda | I9: Pagado | J9: Columna1
B10: DEUDA GESTION 2017-2020 | H10: 0
B11: DEUDA GESTION 2021 | H11: 0 | I11: =IF(T_T134111213141516[[#This Row],[Total]]<0,T_T134111213141516[[#This Row],[Total]]*-1,0) -> 0
B12: DEUDA GESTION 2022 | H12: 0 | I12: =IF(T_T134111213141516[[#This Row],[Total]]<0,T_T134111213141516[[#This Row],[Total]]*-1,0) -> 0
B13: DEUDA GESTION 2023 | H13: 0 | I13: =IF(T_T134111213141516[[#This Row],[Total]]<0,T_T134111213141516[[#This Row],[Total]]*-1,0) -> 0
B14: DEUDA GESTION 2024 | I14: =IF(T_T134111213141516[[#This Row],[Total]]<0,T_T134111213141516[[#This Row],[Total]]*-1,0) -> 0
A15: 46052 | B15: Mantenimiento enero/2026 | D15: 134 | G15: =SUM(D15:F15) -> 134 | H15: =+H13+T_T134111213141516[[#This Row],[Total]] -> 134 | I15: =IF(T_T134111213141516[[#This Row],[Total]]<0,T_T134111213141516[[#This Row],[Total]]*-1,0) -> 0
B16: Pago mantenimiento enero/2026 | C16: 8730 | D16: -134 | G16: =SUM(D16:F16) -> -134 | H16: =+H15+T_T134111213141516[[#This Row],[Total]] -> 0 | I16: =IF(T_T134111213141516[[#This Row],[Total]]<0,T_T134111213141516[[#This Row],[Total]]*-1,0) -> 134 | M16: DESTINAGRO SRL
A17: 45715 | B17: Mantenimiento febrero/2025 | D17: 134 | G17: =SUM(D17:F17) -> 134 | H17: =+H16+T_T134111213141516[[#This Row],[Total]] -> 134 | I17: =IF(T_T134111213141516[[#This Row],[Total]]<0,T_T134111213141516[[#This Row],[Total]]*-1,0) -> 0
B18: Pago mantenimiento febrero/2025 | C18: 8730 | D18: -134 | G18: =SUM(D18:F18) -> -134 | H18: =+H17+T_T134111213141516[[#This Row],[Total]] -> 0 | I18: =IF(T_T134111213141516[[#This Row],[Total]]<0,T_T134111213141516[[#This Row],[Total]]*-1,0) -> 134
A19: 45747 | B19: Mantenimiento marzo/2025 | D19: 160 | G19: =SUM(D19:F19) -> 160 | H19: =+H18+T_T134111213141516[[#This Row],[Total]] -> 160 | I19: =IF(T_T134111213141516[[#This Row],[Total]]<0,T_T134111213141516[[#This Row],[Total]]*-1,0) -> 0
B20: Pago matenimiento marzo/2025 | G20: =SUM(D20:F20) -> 0 | H20: =+H19+T_T134111213141516[[#This Row],[Total]] -> 160 | I20: =IF(T_T134111213141516[[#This Row],[Total]]<0,T_T134111213141516[[#This Row],[Total]]*-1,0) -> 0
A21: 45777 | B21: Mantenimiento abril/2025 | D21: 160 | G21: =SUM(D21:F21) -> 160 | H21: =+H20+T_T134111213141516[[#This Row],[Total]] -> 320 | I21: =IF(T_T134111213141516[[#This Row],[Total]]<0,T_T134111213141516[[#This Row],[Total]]*-1,0) -> 0
B22: Pago mantenimiento abril/2025 | G22: =SUM(D22:F22) -> 0 | H22: =+H21+T_T134111213141516[[#This Row],[Total]] -> 320 | I22: =IF(T_T134111213141516[[#This Row],[Total]]<0,T_T134111213141516[[#This Row],[Total]]*-1,0) -> 0
A23: 45807 | B23: Mantenimiento mayo/2025 | D23: 160 | G23: =SUM(D23:F23) -> 160 | H23: =+H22+T_T134111213141516[[#This Row],[Total]] -> 480 | I23: =IF(T_T134111213141516[[#This Row],[Total]]<0,T_T134111213141516[[#This Row],[Total]]*-1,0) -> 0
B24: Pago mantenimiento mayo/2025 | G24: =SUM(D24:F24) -> 0 | H24: =+H23+T_T134111213141516[[#This Row],[Total]] -> 480 | I24: =IF(T_T134111213141516[[#This Row],[Total]]<0,T_T134111213141516[[#This Row],[Total]]*-1,0) -> 0
A25: 45838 | B25: Mantenimiento junio/2025 | G25: =SUM(D25:F25) -> 0 | H25: =+H24+T_T134111213141516[[#This Row],[Total]] -> 480 | I25: =IF(T_T134111213141516[[#This Row],[Total]]<0,T_T134111213141516[[#This Row],[Total]]*-1,0) -> 0
B26: Pago mantenimiento junio/2025 | G26: =SUM(D26:F26) -> 0 | H26: =+H25+T_T134111213141516[[#This Row],[Total]] -> 480 | I26: =IF(T_T134111213141516[[#This Row],[Total]]<0,T_T134111213141516[[#This Row],[Total]]*-1,0) -> 0
A27: 45868 | B27: Mantenimiento julio/2025 | G27: =SUM(D27:F27) -> 0 | H27: =+H26+T_T134111213141516[[#This Row],[Total]] -> 480 | I27: =IF(T_T134111213141516[[#This Row],[Total]]<0,T_T134111213141516[[#This Row],[Total]]*-1,0) -> 0
B28: Pago mantenimient julio/2025 | G28: =SUM(D28:F28) -> 0 | H28: =+H27+T_T134111213141516[[#This Row],[Total]] -> 480 | I28: =IF(T_T134111213141516[[#This Row],[Total]]<0,T_T134111213141516[[#This Row],[Total]]*-1,0) -> 0
A29: 45899 | B29: Mantenimiento agosto/2025 | G29: =SUM(D29:F29) -> 0 | H29: =+H28+T_T134111213141516[[#This Row],[Total]] -> 480 | I29: =IF(T_T134111213141516[[#This Row],[Total]]<0,T_T134111213141516[[#This Row],[Total]]*-1,0) -> 0
B30: Pago mantenimiento agosto/2025 | G30: =SUM(D30:F30) -> 0 | H30: =+H29+T_T134111213141516[[#This Row],[Total]] -> 480 | I30: =IF(T_T134111213141516[[#This Row],[Total]]<0,T_T134111213141516[[#This Row],[Total]]*-1,0) -> 0
A31: 45930 | B31: Mantenimiento septiembre/2025 | G31: =SUM(D31:F31) -> 0 | H31: =+H30+T_T134111213141516[[#This Row],[Total]] -> 480 | I31: =IF(T_T134111213141516[[#This Row],[Total]]<0,T_T134111213141516[[#This Row],[Total]]*-1,0) -> 0
B32: Pago mantenimiento septiembre/2025 | G32: =SUM(D32:F32) -> 0 | H32: =H31+G32 -> 480 | I32: =IF(T_T134111213141516[[#This Row],[Total]]<0,T_T134111213141516[[#This Row],[Total]]*-1,0) -> 0
A33: 45960 | B33: Mantenimiento octubre /2025 | G33: =SUM(D33:F33) -> 0 | H33: =H32+G33 -> 480 | I33: =IF(T_T134111213141516[[#This Row],[Total]]<0,T_T134111213141516[[#This Row],[Total]]*-1,0) -> 0
B34: Pago mantenimiento octubre/2025 | G34: =SUM(D34:F34) -> 0 | H34: =H33+G34 -> 480 | I34: =IF(T_T134111213141516[[#This Row],[Total]]<0,T_T134111213141516[[#This Row],[Total]]*-1,0) -> 0
A35: 45991 | B35: Mantenimiento noviembre/2025 | G35: =SUM(D35:F35) -> 0 | H35: =H34+G35 -> 480 | I35: =IF(T_T134111213141516[[#This Row],[Total]]<0,T_T134111213141516[[#This Row],[Total]]*-1,0) -> 0
B36: Pago mantenimiento noviembre/2025 | G36: =SUM(D36:F36) -> 0 | H36: =H35+G36 -> 480 | I36: =IF(T_T134111213141516[[#This Row],[Total]]<0,T_T134111213141516[[#This Row],[Total]]*-1,0) -> 0
A37: 46021 | B37: Mantenimiento diciembre/2025 | G37: =SUM(D37:F37) -> 0 | H37: =H36+G37 -> 480 | I37: =IF(T_T134111213141516[[#This Row],[Total]]<0,T_T134111213141516[[#This Row],[Total]]*-1,0) -> 0
B38: Pago de Mantenimiento diciembre/2025 | G38: =SUM(D38:F38) -> 0 | H38: =H37+G38 -> 480 | I38: =IF(T_T134111213141516[[#This Row],[Total]]<0,T_T134111213141516[[#This Row],[Total]]*-1,0) -> 0
G39: =SUM(D39:F46) -> 0 | H39: =H38+G39 -> 480 | I39: =IF(T_T134111213141516[[#This Row],[Total]]<0,T_T134111213141516[[#This Row],[Total]]*-1,0) -> 0
G40: =SUM(D40:F47) -> 0 | H40: =H39+G40 -> 480 | I40: =IF(T_T134111213141516[[#This Row],[Total]]<0,T_T134111213141516[[#This Row],[Total]]*-1,0) -> 0

Sheet LOCAL 19
A2: Departamento : | B2: LOCAL 19
A3: Propietario : | B3: =LOOKUP(B2,#REF!,#REF!) -> #REF!
A4: Inquilino : | B4: =LOOKUP(B2,#REF!,#REF!) -> #REF!
A5: Teléfono : | B5: =LOOKUP(B2,#REF!,#REF!) -> #REF!
A6: Celular : | B6: =LOOKUP(B2,#REF!,#REF!) -> #REF!
A7: Correo : | B7: =LOOKUP(B2,#REF!,#REF!) -> #REF! | H7: Resumen
A9: Fecha | B9: Concepto | C9: Recibo | D9: Expensas | E9: Agua | F9: Multa | G9: Total | H9: Deuda | I9: Pagado | J9: Columna1
B10: DEUDA GESTION 2017-2020 | H10: 0 | I10: =IF(T_T13411121314151617[[#This Row],[Total]]<0,T_T13411121314151617[[#This Row],[Total]]*-1,0) -> 0
B11: DEUDA GESTION 2021 | H11: 0 | I11: =IF(T_T13411121314151617[[#This Row],[Total]]<0,T_T13411121314151617[[#This Row],[Total]]*-1,0) -> 0
B12: DEUDA GESTION 2022 | H12: 0 | I12: =IF(T_T13411121314151617[[#This Row],[Total]]<0,T_T13411121314151617[[#This Row],[Total]]*-1,0) -> 0
B13: DEUDA GESTION 2023 | H13: 0 | I13: =IF(T_T13411121314151617[[#This Row],[Total]]<0,T_T13411121314151617[[#This Row],[Total]]*-1,0) -> 0
B14: DEUDA GESTION 2024 | I14: =IF(T_T13411121314151617[[#This Row],[Total]]<0,T_T13411121314151617[[#This Row],[Total]]*-1,0) -> 0
A15: 46052 | B15: Mantenimiento enero/2026 | D15: 117 | E15: 10 | G15: =SUM(D15:F15) -> 127 | H15: =+H13+T_T13411121314151617[[#This Row],[Total]] -> 127 | I15: =IF(T_T13411121314151617[[#This Row],[Total]]<0,T_T13411121314151617[[#This Row],[Total]]*-1,0) -> 0
B16: Pago mantenimiento enero/2026 | C16: 8940 | D16: =-82-35 -> -117 | E16: -10 | G16: =SUM(D16:F16) -> -127 | H16: =H15+G16 -> 0 | I16: =IF(T_T13411121314151617[[#This Row],[Total]]<0,T_T13411121314151617[[#This Row],[Total]]*-1,0) -> 127
A17: 45715 | B17: Mantenimiento febrero/2025 | D17: 117 | E17: 10 | G17: =SUM(D17:F17) -> 127 | H17: =H16+G17 -> 127 | I17: =IF(T_T13411121314151617[[#This Row],[Total]]<0,T_T13411121314151617[[#This Row],[Total]]*-1,0) -> 0
B18: Pago mantenimiento febrero/2025 | C18: 8941 | D18: =-82-35 -> -117 | E18: -10 | G18: =SUM(D18:F18) -> -127 | H18: =H17+G18 -> 0 | I18: =IF(T_T13411121314151617[[#This Row],[Total]]<0,T_T13411121314151617[[#This Row],[Total]]*-1,0) -> 127
A19: 45747 | B19: Mantenimiento marzo/2025 | D19: =99+40 -> 139 | E19: 15 | G19: =SUM(D19:F19) -> 154 | H19: =H18+G19 -> 154 | I19: =IF(T_T13411121314151617[[#This Row],[Total]]<0,T_T13411121314151617[[#This Row],[Total]]*-1,0) -> 0
B20: Pago matenimiento marzo/2025 | C20: 8942 | D20: =-99-35 -> -134 | E20: -15 | G20: =SUM(D20:F20) -> -149 | H20: =H19+G20 -> 5 | I20: =IF(T_T13411121314151617[[#This Row],[Total]]<0,T_T13411121314151617[[#This Row],[Total]]*-1,0) -> 149
A21: 45777 | B21: Mantenimiento abril/2025 | D21: 139 | E21: 15 | G21: =SUM(D21:F21) -> 154 | H21: =H20+G21 -> 159 | I21: =IF(T_T13411121314151617[[#This Row],[Total]]<0,T_T13411121314151617[[#This Row],[Total]]*-1,0) -> 0
B22: Pago mantenimiento abril/2025 | C22: 8944 | D22: =-99-35 -> -134 | E22: -15 | G22: =SUM(D22:F22) -> -149 | H22: =H21+G22 -> 10 | I22: =IF(T_T13411121314151617[[#This Row],[Total]]<0,T_T13411121314151617[[#This Row],[Total]]*-1,0) -> 149
A23: 45807 | B23: Mantenimiento mayo/2025 | D23: 139 | E23: 10 | G23: =SUM(D23:F23) -> 149 | H23: =H22+G23 -> 159 | I23: =IF(T_T13411121314151617[[#This Row],[Total]]<0,T_T13411121314151617[[#This Row],[Total]]*-1,0) -> 0
B24: Pago mantenimiento mayo/2025 | D24: -35 | G24: =SUM(D24:F24) -> -35 | H24: =H23+G24 -> 124 | I24: =IF(T_T13411121314151617[[#This Row],[Total]]<0,T_T13411121314151617[[#This Row],[Total]]*-1,0) -> 35
A25: 45838 | B25: Mantenimiento junio/2025 | G25: =SUM(D25:F25) -> 0 | H25: =H24+G25 -> 124 | I25: =IF(T_T13411121314151617[[#This Row],[Total]]<0,T_T13411121314151617[[#This Row],[Total]]*-1,0) -> 0
B26: Pago mantenimiento junio/2025 | D26: -35 | G26: =SUM(D26:F26) -> -35 | H26: =H25+G26 -> 89 | I26: =IF(T_T13411121314151617[[#This Row],[Total]]<0,T_T13411121314151617[[#This Row],[Total]]*-1,0) -> 35
A27: 45868 | B27: Mantenimiento julio/2025 | G27: =SUM(D27:F27) -> 0 | H27: =H26+G27 -> 89 | I27: =IF(T_T13411121314151617[[#This Row],[Total]]<0,T_T13411121314151617[[#This Row],[Total]]*-1,0) -> 0
B28: Pago mantenimient julio/2025 | D28: -35 | G28: =SUM(D28:F28) -> -35 | H28: =H27+G28 -> 54 | I28: =IF(T_T13411121314151617[[#This Row],[Total]]<0,T_T13411121314151617[[#This Row],[Total]]*-1,0) -> 35
A29: 45899 | B29: Mantenimiento agosto/2025 | G29: =SUM(D29:F29) -> 0 | H29: =H28+G29 -> 54 | I29: =IF(T_T13411121314151617[[#This Row],[Total]]<0,T_T13411121314151617[[#This Row],[Total]]*-1,0) -> 0
B30: Pago mantenimiento agosto/2025 | D30: -35 | G30: =SUM(D30:F30) -> -35 | H30: =H29+G30 -> 19 | I30: =IF(T_T13411121314151617[[#This Row],[Total]]<0,T_T13411121314151617[[#This Row],[Total]]*-1,0) -> 35
A31: 45930 | B31: Mantenimiento septiembre/2025 | G31: =SUM(D31:F31) -> 0 | H31: =H30+G31 -> 19 | I31: =IF(T_T13411121314151617[[#This Row],[Total]]<0,T_T13411121314151617[[#This Row],[Total]]*-1,0) -> 0
B32: Pago mantenimiento septiembre/2025 | D32: -35 | G32: =SUM(D32:F32) -> -35 | H32: =H31+G32 -> -16 | I32: =IF(T_T13411121314151617[[#This Row],[Total]]<0,T_T13411121314151617[[#This Row],[Total]]*-1,0) -> 35
A33: 45960 | B33: Mantenimiento octubre /2025 | G33: =SUM(D33:F33) -> 0 | H33: =H32+G33 -> -16 | I33: =IF(T_T13411121314151617[[#This Row],[Total]]<0,T_T13411121314151617[[#This Row],[Total]]*-1,0) -> 0
B34: Pago mantenimiento octubre/2025 | D34: -35 | G34: =SUM(D34:F34) -> -35 | H34: =H33+G34 -> -51 | I34: =IF(T_T13411121314151617[[#This Row],[Total]]<0,T_T13411121314151617[[#This Row],[Total]]*-1,0) -> 35
A35: 45991 | B35: Mantenimiento noviembre/2025 | G35: =SUM(D35:F35) -> 0 | H35: =H34+G35 -> -51 | I35: =IF(T_T13411121314151617[[#This Row],[Total]]<0,T_T13411121314151617[[#This Row],[Total]]*-1,0) -> 0
B36: Pago mantenimiento noviembre/2025 | D36: -35 | G36: =SUM(D36:F36) -> -35 | H36: =H35+G36 -> -86 | I36: =IF(T_T13411121314151617[[#This Row],[Total]]<0,T_T13411121314151617[[#This Row],[Total]]*-1,0) -> 35
A37: 46021 | B37: Mantenimiento diciembre/2025 | G37: =SUM(D37:F37) -> 0 | H37: =H36+G37 -> -86 | I37: =IF(T_T13411121314151617[[#This Row],[Total]]<0,T_T13411121314151617[[#This Row],[Total]]*-1,0) -> 0
B38: Pago de Mantenimiento diciembre/2025 | D38: -35 | G38: =SUM(D38:F38) -> -35 | H38: =H37+G38 -> -121 | I38: =IF(T_T13411121314151617[[#This Row],[Total]]<0,T_T13411121314151617[[#This Row],[Total]]*-1,0) -> 35
I39: =IF(T_T13411121314151617[[#This Row],[Total]]<0,T_T13411121314151617[[#This Row],[Total]]*-1,0) -> 0
I40: =IF(T_T13411121314151617[[#This Row],[Total]]<0,T_T13411121314151617[[#This Row],[Total]]*-1,0) -> 0
I41: =IF(T_T13411121314151617[[#This Row],[Total]]<0,T_T13411121314151617[[#This Row],[Total]]*-1,0) -> 0
I42: =IF(T_T13411121314151617[[#This Row],[Total]]<0,T_T13411121314151617[[#This Row],[Total]]*-1,0) -> 0

Sheet RESUMEN LOCALES
B1: EDIFICIO TORRE FAITH
B2: LISTA DE DEUDORES LOCALES
B3: AL 30/12/2026
B5: UNIDAD | C5: DETALLE | D5: PAGO UNICO | E5: MUDANZA | F5: ENERO | G5: FEBRERO | H5: MARZO | I5: ABRIL | J5: MAYO | K5: JUNIO | L5: JULIO | M5: AGOSTO | N5: SEPTIEMBRE | O5: OCTUBRE | P5: NOVIEMBRE | Q5: DICIEMBRE | R5: TOTAL | S5: TOTAL PAGADO | T5: TOTAL DEUDA
B7: Departamento | C7: Nombre
A8: 1 | B8: LOCAL 01 | C8: ANA CAROLINA ZALLES REYES | E8: 0 | F8: =+'LOCAL 01'!D11+'LOCAL 01'!E11 -> 93 | G8: =+'LOCAL 01'!D13+'LOCAL 01'!E13 -> 95 | H8: =+'LOCAL 01'!D15+'LOCAL 01'!E15 -> 112 | I8: =+'LOCAL 01'!D17+'LOCAL 01'!E17 -> 117 | J8: =+'LOCAL 01'!D19+'LOCAL 01'!E19 -> 117 | R8: =SUM(E8:Q8) -> 534 | S8: =-(+'LOCAL 01'!G12+'LOCAL 01'!G14+'LOCAL 01'!G16+'LOCAL 01'!G18+'LOCAL 01'!G20) -> 417 | T8: =+R8-S8 -> 117 | U8: LOCAL 01
A9: =+A8+1 -> 2 | B9: LOCAL 02 | C9: JOSE BENJAMIN ORGAZ ZAVALETA | E9: 0 | F9: =+'LOCAL 02'!D11+'LOCAL 02'!E11 -> 83 | G9: =+'LOCAL 02'!D13+'LOCAL 02'!E13 -> 83 | H9: =+'LOCAL 02'!D15+'LOCAL 02'!E15 -> 97 | I9: =+'LOCAL 02'!D17+'LOCAL 02'!E17 -> 97 | J9: =+'LOCAL 02'!D19+'LOCAL 02'!E19 -> 97 | R9: =SUM(E9:Q9) -> 457 | S9: =-(+'LOCAL 02'!G12+'LOCAL 02'!G14+'LOCAL 02'!G16+'LOCAL 02'!G18+'LOCAL 02'!G20+'LOCAL 02'!G22+'LOCAL 02'!G24+'LOCAL 02'!G26+'LOCAL 02'!G28+'LOCAL 02'!G30+'LOCAL 02'!G32+'LOCAL 02'!G34) -> 0 | T9: =+R9-S9 -> 457 | U9: LOCAL 02
A10: =+A9+1 -> 3 | B10: LOCAL 03 | C10: SIMCORT / APRINTEL SRL | E10: 0 | F10: =+'LOCAL 03'!D15+'LOCAL 03'!E15 -> 117 | G10: =+'LOCAL 03'!D17+'LOCAL 03'!E17 -> 115 | H10: =+'LOCAL 03'!D19+'LOCAL 03'!E19 -> 131 | I10: =+'LOCAL 03'!D21+'LOCAL 03'!E21 -> 123 | J10: =+'LOCAL 03'!D23+'LOCAL 03'!E23 -> 130 | R10: =SUM(E10:Q10) -> 616 | S10: =-(+'LOCAL 03'!G16+'LOCAL 03'!G18+'LOCAL 03'!G20+'LOCAL 03'!G22) -> 117 | T10: =+R10-S10 -> 499 | U10: LOCAL 03
A11: =+A10+1 -> 4 | B11: LOCAL 04 | C11: CELIA POMA /APRINTEL SRL | E11: 0 | F11: =+'LOCAL 04'!D15+'LOCAL 04'!E15 -> 205 | G11: =+'LOCAL 04'!D17+'LOCAL 04'!E17 -> 360 | H11: =+'LOCAL 04'!D19+'LOCAL 04'!E19 -> 151 | I11: =+'LOCAL 04'!D21+'LOCAL 04'!E21 -> 124 | J11: =+'LOCAL 04'!D23+'LOCAL 04'!E23 -> 138 | R11: =SUM(E11:Q11) -> 978 | S11: =+'LOCAL 04'!G16+'LOCAL 04'!G18+'LOCAL 04'!G20+'LOCAL 04'!G22 -> 0 | T11: =+R11-S11 -> 978 | U11: LOCAL 04
A12: =+A11+1 -> 5 | B12: LOCAL 05 | C12: RAUL QUIÑONES MARQUEZ | E12: 0 | F12: =+'LOCAL 05'!D15+'LOCAL 05'!E15 -> 114 | G12: =+'LOCAL 05'!D17+'LOCAL 05'!E17 -> 114 | H12: =+'LOCAL 05'!D19+'LOCAL 05'!E19 -> 134 | I12: =+'LOCAL 05'!D21+'LOCAL 05'!E21 -> 134 | J12: =+'LOCAL 05'!D23+'LOCAL 05'!E23 -> 0 | R12: =SUM(E12:Q12) -> 496 | S12: =-(+'LOCAL 05'!G16+'LOCAL 05'!G18+'LOCAL 05'!G20+'LOCAL 05'!G22+'LOCAL 05'!G24) -> 496 | T12: =+R12-S12 -> 0 | U12: LOCAL 05
A13: =+A12+1 -> 6 | B13: LOCAL 06 | C13: VERONICA SOLEDAD RODRIGUEZ PIMENTEL | E13: 0 | F13: =+'LOCAL 06'!D15+'LOCAL 06'!E15 -> 139 | G13: =+'LOCAL 06'!D17+'LOCAL 06'!E17 -> 152 | H13: =+'LOCAL 06'!D19+'LOCAL 06'!E19 -> 204 | I13: =+'LOCAL 06'!D21+'LOCAL 06'!E21 -> 229 | J13: =+'LOCAL 06'!D23+'LOCAL 06'!E23 -> 231 | R13: =SUM(E13:Q13) -> 955 | S13: =-(+'LOCAL 06'!G16+'LOCAL 06'!G18+'LOCAL 06'!G20+'LOCAL 06'!G22+'LOCAL 06'!G24) -> 724 | T13: =+R13-S13 -> 231 | U13: LOCAL 06
A14: =+A13+1 -> 7 | B14: LOCAL 07 | C14: ROXANA JOSEFINA CHAVEZ TORREZ | E14: 0 | F14: =+'LOCAL 07'!D15+'LOCAL 07'!E15 -> 87 | G14: =+'LOCAL 07'!D17+'LOCAL 07'!E17 -> 87 | H14: =+'LOCAL 07'!D19+'LOCAL 07'!E19 -> 102 | I14: =+'LOCAL 07'!D21+'LOCAL 07'!E21 -> 102 | J14: =+'LOCAL 07'!D23+'LOCAL 07'!E23 -> 102 | R14: =SUM(E14:Q14) -> 480 | S14: =+'LOCAL 07'!G16+'LOCAL 07'!G18+'LOCAL 07'!G20+'LOCAL 07'!G22 -> 0 | T14: =+R14-S14 -> 480 | U14: LOCAL 07
A15: =+A14+1 -> 8 | B15: LOCAL 08 | C15: LOURDES BARRIENTOS - RODRIGO ALMARAZ BARRIENTOS | E15: 0 | F15: =+'lOCAL 8 '!E11+'lOCAL 8 '!F11 -> 81 | G15: =+'lOCAL 8 '!E13+'lOCAL 8 '!F13 -> 81 | H15: =+'lOCAL 8 '!E15+'lOCAL 8 '!F15 -> 94 | I15: =+'lOCAL 8 '!E17+'lOCAL 8 '!F17 -> 94 | J15: =+'lOCAL 8 '!E19+'lOCAL 8 '!F19 -> 94 | R15: =SUM(E15:Q15) -> 444 | S15: =-(+'lOCAL 8 '!H12+'lOCAL 8 '!H14+'lOCAL 8 '!H16+'lOCAL 8 '!H18+'lOCAL 8 '!H20) -> 350 | T15: =+R15-S15 -> 94 | U15: LOCAL 08
A16: =+A15+1 -> 9 | B16: LOCAL 09 | C16: EVA LUCIANA ZEGARRA CHOQUE | E16: 0 | F16: =+'LOCAL 09'!D15+'LOCAL 09'!E15 -> 88 | G16: =+'LOCAL 09'!D17+'LOCAL 09'!E17 -> 88 | H16: =+'LOCAL 09'!D19+'LOCAL 09'!E19 -> 103 | I16: =+'LOCAL 09'!D21+'LOCAL 09'!E21 -> 103 | J16: =+'LOCAL 09'!D23+'LOCAL 09'!E23 -> 103 | R16: =SUM(E16:Q16) -> 485 | S16: =-(+T_T1349[[#This Row],[Total]]+'LOCAL 09'!G18+'LOCAL 09'!G20+'LOCAL 09'!G22+'LOCAL 09'!G24) -> 88 | T16: =+R16-S16 -> 397 | U16: LOCAL 09
A17: =+A16+1 -> 10 | B17: LOCAL 10 | C17: JESICA AJATA | E17: 0 | F17: =+'LOCAL 10'!E16+'LOCAL 10'!F16 -> 157 | G17: =+'LOCAL 10'!E18+'LOCAL 10'!F18 -> 143 | H17: =+'LOCAL 10'!E20+'LOCAL 10'!F20 -> 152 | I17: =+'LOCAL 10'!E22+'LOCAL 10'!F22 -> 155 | J17: =+'LOCAL 10'!E24+'LOCAL 10'!F24 -> 153 | R17: =SUM(E17:Q17) -> 760 | S17: =-(+'lOCAL 8 '!H14+'lOCAL 8 '!H16+'lOCAL 8 '!H18+'lOCAL 8 '!H20+'lOCAL 8 '!H22) -> 269 | T17: =+R17-S17 -> 491 | U17: LOCAL 10
B18: LOCAL 11 | C18: FRESIA FLORES | F18: =+LOCAL.11!D15+LOCAL.11!E15 -> 74 | G18: =+LOCAL.11!D17+LOCAL.11!E17 -> 74 | H18: =+LOCAL.11!D19+LOCAL.11!E19 -> 88 | I18: =+LOCAL.11!D21+LOCAL.11!E21 -> 88 | J18: =+LOCAL.11!D24+LOCAL.11!E24 -> 0 | R18: =SUM(E18:Q18) -> 324 | S18: =-(+LOCAL.11!G16+T_T1341112131415161718[[#This Row],[Total]]+LOCAL.11!G20+LOCAL.11!G22+LOCAL.11!G24) -> 324 | T18: =+R18-S18 -> 0 | U18: LOCAL 11
A19: =+A17+1 -> 11 | B19: LOCAL 12-13 | C19: JOSE BENJAMIN ORGAZ ZAVALETA | E19: 0 | F19: =+'LOCAL 12-13'!D15+'LOCAL 12-13'!E15 -> 448 | G19: =+'LOCAL 12-13'!D17+'LOCAL 12-13'!E17 -> 438 | H19: =+T_T13411[[#This Row],[Expensas]]+T_T13411[[#This Row],[Agua]] -> 495 | I19: =+'LOCAL 12-13'!D21+'LOCAL 12-13'!E21 -> 512 | J19: =+'LOCAL 12-13'!D23+'LOCAL 12-13'!E23 -> 506 | R19: =SUM(E19:Q19) -> 2399 | S19: =-(+'LOCAL 12-13'!G16+'LOCAL 12-13'!G18+'LOCAL 12-13'!G20+'LOCAL 12-13'!G22+'LOCAL 12-13'!G24) -> 1893 | T19: =+R19-S19 -> 506 | U19: LOCAL 12-13
A20: =+A19+1 -> 12 | B20: LOCAL 14 | C20: RAUL QUIÑONES MARQUEZ | E20: 0 | F20: =+'LOCAL 14'!D15+'LOCAL 14'!E15 -> 133 | G20: =+'LOCAL 14'!D17+'LOCAL 14'!E17 -> 133 | H20: =+'LOCAL 14'!D19+'LOCAL 14'!E19 -> 161 | I20: =+'LOCAL 14'!D21+'LOCAL 14'!E21 -> 161 | J20: =+'LOCAL 14'!D23+'LOCAL 14'!E23 -> 161 | R20: =SUM(E20:Q20) -> 749 | S20: =-(+'LOCAL 14'!G16+'LOCAL 14'!G18++T_T1341112[[#This Row],[Total]]+'LOCAL 14'!G22+'LOCAL 14'!G24) -> 219 | T20: =+R20-S20 -> 530 | U20: LOCAL 14
A21: =+A20+1 -> 13 | B21: LOCAL 15 | C21: JESICA AJATA | E21: 0 | F21: =+'LOCAL 15'!D15+'LOCAL 15'!E15 -> 191 | G21: =+'LOCAL 15'!D17+'LOCAL 15'!E17 -> 191 | H21: =+'LOCAL 15'!D19+'LOCAL 15'!E19 -> 232 | I21: =+T_T134111213[[#This Row],[Expensas]]+T_T134111213[[#This Row],[Agua]] -> 232 | J21: =+'LOCAL 15'!D23+'LOCAL 15'!E23 -> 227 | R21: =SUM(E21:Q21) -> 1073 | S21: =-(+'LOCAL 15'!G16+'LOCAL 15'!G18+'LOCAL 15'!G20+'LOCAL 15'!G22+'LOCAL 15'!G24) -> 846 | T21: =+R21-S21 -> 227 | U21: LOCAL 15
A22: =+A21+1 -> 14 | B22: LOCAL 16 | C22: RENE BLACUT MAMANI | E22: 0 | F22: =+'LOCAL 16'!D15+'LOCAL 16'!E15 -> 103 | G22: =+'LOCAL 16'!D17+'LOCAL 16'!E17 -> 103 | H22: =+'LOCAL 16'!D19+'LOCAL 16'!E19 -> 126 | I22: =+'LOCAL 16'!D21+'LOCAL 16'!E21 -> 126 | J22: =+'LOCAL 16'!D23+'LOCAL 16'!E23 -> 126 | R22: =SUM(E22:Q22) -> 584 | S22: =-(+'LOCAL 16'!G16+'LOCAL 16'!G18+'LOCAL 16'!G20+T_T13411121314[[#This Row],[Total]]+'LOCAL 16'!G24) -> 458 | T22: =+R22-S22 -> 126 | U22: LOCAL 16
A23: =+A22+1 -> 15 | B23: LOCAL 17 | C23: NELSON ERMES ROMERO ARMATA | E23: 0 | F23: =+'LOCAL 17'!D15+'LOCAL 17'!E15 -> 80 | G23: =+'LOCAL 17'!D17+'LOCAL 17'!E17 -> 80 | H23: =+'LOCAL 17'!D19+'LOCAL 17'!E19 -> 99 | I23: =+'LOCAL 17'!D21+'LOCAL 17'!E21 -> 99 | J23: =+T_T1341112131415[[#This Row],[Expensas]]+T_T1341112131415[[#This Row],[Agua]] -> 94 | R23: =SUM(E23:Q23) -> 452 | S23: =-(+'LOCAL 17'!G16+'LOCAL 17'!G18+'LOCAL 17'!G20+'LOCAL 17'!G22+'LOCAL 17'!G24) -> 358 | T23: =+R23-S23 -> 94 | U23: LOCAL 17
A24: =+A23+1 -> 16 | B24: LOCAL 18 | C24: MARTHA HOYOS RODAS | E24: 0 | F24: =+'LOCAL 18'!D15+'LOCAL 18'!E15 -> 134 | G24: =+'LOCAL 18'!D17+'LOCAL 18'!E17 -> 134 | H24: =+'LOCAL 18'!D19+'LOCAL 18'!E19 -> 160 | I24: =+'LOCAL 18'!D21+'LOCAL 18'!E21 -> 160 | J24: =+'LOCAL 18'!D23+'LOCAL 18'!E23 -> 160 | R24: =SUM(E24:Q24) -> 748 | S24: =-(+'LOCAL 18'!G16+'LOCAL 18'!G18+'LOCAL 18'!G20+'LOCAL 18'!G22) -> 268 | T24: =+R24-S24 -> 480 | U24: LOCAL 18
A25: =+A24+1 -> 17 | B25: LOCAL 19 | C25: LILIAN GISELA ESPEJO SEJAS | E25: 0 | F25: =+'LOCAL 19'!D15+'LOCAL 19'!E15 -> 127 | G25: =+'LOCAL 19'!D17+'LOCAL 19'!E17 -> 127 | H25: =+'LOCAL 19'!D19+'LOCAL 19'!E19 -> 154 | I25: =+'LOCAL 19'!D21+'LOCAL 19'!E21 -> 154 | J25: =+'LOCAL 19'!D23+'LOCAL 19'!E23 -> 149 | R25: =SUM(E25:Q25) -> 711 | S25: =-(+'LOCAL 19'!G16+'LOCAL 19'!G18+'LOCAL 19'!G20+'LOCAL 19'!G22) -> 552 | T25: =+R25-S25 -> 159 | U25: LOCAL 19
A26: =+A25+1 -> 18 | E26: 0 | R26: =SUM(E26:Q26) -> 0 | T26: =+R26-S26 -> 0 | U26: LOCAL 11
C27: TOTAL | E27: 0 | F27: =SUM(F8:F26) -> 2454 | G27: =SUM(G8:G26) -> 2598 | R27: =SUM(R8:R26) -> 13245 | S27: =SUM(S8:S26) -> 7379 | T27: =SUM(T8:T26) -> 5866
B29: NOTA : La deuda deberá ser cancelada hasta el 21/01/2021 impostergablemente caso
B30: contrario se tomara las medidas que aconseja el caso, según acordado en Asamblea
B31: General de fecha 10/12/2021.
B32: Copropietarios que apoyaran a el cobro de expensas según acta:
B33: Lic. Cristina R. Inofuentes Depto. 26-D
B34: Sra. Ana Llerena Uria Depto 13-A
B36: La Paz, 14 de enero de 2021

Sheet OF.3A
A2: Departamento : | B2: OF.3A
A3: Propietario : | B3: LUPE LECOÑA
A4: Inquilino : | B4: =LOOKUP(B2,#REF!,#REF!) -> #REF!
A5: Teléfono : | B5: =LOOKUP(B2,#REF!,#REF!) -> #REF!
A6: Celular : | B6: =LOOKUP(B2,#REF!,#REF!) -> #REF!
A7: Correo : | B7: =LOOKUP(B2,#REF!,#REF!) -> #REF! | H7: Resumen
A9: Fecha | B9: Concepto | C9: Recibo | D9: Expensas | E9: Agua | F9: Multa | G9: Total | H9: Deuda | I9: Pagado | J9: Columna1 | K9: Columna2
B10: DEUDA GESTION 2017-2020 | H10: 0 | I10: =IF(T_T134111213141516171819[[#This Row],[Total]]<0,T_T134111213141516171819[[#This Row],[Total]]*-1,0) -> 0
B11: DEUDA GESTION 2021 | H11: 0 | I11: =IF(T_T134111213141516171819[[#This Row],[Total]]<0,T_T134111213141516171819[[#This Row],[Total]]*-1,0) -> 0
B12: DEUDA GESTION 2022 | H12: 0 | I12: =IF(T_T134111213141516171819[[#This Row],[Total]]<0,T_T134111213141516171819[[#This Row],[Total]]*-1,0) -> 0
B13: DEUDA GESTION 2023 | H13: 0 | I13: =IF(T_T134111213141516171819[[#This Row],[Total]]<0,T_T134111213141516171819[[#This Row],[Total]]*-1,0) -> 0
B14: MUDANZA | G14: =SUM(D14:F14) -> 0 | H14: =+H13+T_T134111213141516171819[[#This Row],[Total]] -> 0 | I14: =IF(T_T134111213141516171819[[#This Row],[Total]]<0,T_T134111213141516171819[[#This Row],[Total]]*-1,0) -> 0
B15: PAGO POR MUDANZA | G15: =SUM(D15:F15) -> 0 | H15: =H14+G15 -> 0 | I15: =IF(T_T134111213141516171819[[#This Row],[Total]]<0,T_T134111213141516171819[[#This Row],[Total]]*-1,0) -> 0
B16: DEUDA GESTION 2024 | I16: =IF(T_T134111213141516171819[[#This Row],[Total]]<0,T_T134111213141516171819[[#This Row],[Total]]*-1,0) -> 0
A17: 46052 | B17: Mantenimiento enero/2026 | D17: 176 | E17: 193 | G17: =SUM(D17:F17) -> 369 | H17: =H15+G17 -> 369 | I17: =IF(T_T134111213141516171819[[#This Row],[Total]]<0,T_T134111213141516171819[[#This Row],[Total]]*-1,0) -> 0
B18: Pago mantenimiento enero/2026 | C18: 8599 | D18: -176 | E18: -193 | G18: =SUM(D18:F18) -> -369 | H18: =H17+G18 -> 0 | I18: =IF(T_T134111213141516171819[[#This Row],[Total]]<0,T_T134111213141516171819[[#This Row],[Total]]*-1,0) -> 369
B19: MUDANZA | D19: 200 | G19: =SUM(D19:F19) -> 200 | H19: =H18+G19 -> 200 | I19: =IF(T_T134111213141516171819[[#This Row],[Total]]<0,T_T134111213141516171819[[#This Row],[Total]]*-1,0) -> 0
C20: 8694 | D20: -200 | G20: =SUM(D20:F20) -> -200 | H20: =H19+G20 -> 0 | I20: =IF(T_T134111213141516171819[[#This Row],[Total]]<0,T_T134111213141516171819[[#This Row],[Total]]*-1,0) -> 200
A21: 46080 | B21: Mantenimiento febrero/2026 | D21: 176 | E21: 27 | G21: =SUM(D21:F21) -> 203 | H21: =H20+G21 -> 203 | I21: =IF(T_T134111213141516171819[[#This Row],[Total]]<0,T_T134111213141516171819[[#This Row],[Total]]*-1,0) -> 0 | L21: vania iturri
B22: Pago mantenimiento febrero/2026 | G22: =SUM(D22:F22) -> 0 | H22: =H21+G22 -> 203 | I22: =IF(T_T134111213141516171819[[#This Row],[Total]]<0,T_T134111213141516171819[[#This Row],[Total]]*-1,0) -> 0
A23: 45747 | B23: Mantenimiento marzo/2025 | D23: 212 | E23: 4 | G23: =SUM(D23:F23) -> 216 | H23: =H22+G23 -> 419 | I23: =IF(T_T134111213141516171819[[#This Row],[Total]]<0,T_T134111213141516171819[[#This Row],[Total]]*-1,0) -> 0
B24: Pago matenimiento marzo/2025 | G24: =SUM(D24:F24) -> 0 | H24: =H23+G24 -> 419 | I24: =IF(T_T134111213141516171819[[#This Row],[Total]]<0,T_T134111213141516171819[[#This Row],[Total]]*-1,0) -> 0
A25: 45777 | B25: Mantenimiento abril/2025 | D25: 212 | E25: 49 | G25: =SUM(D25:F25) -> 261 | H25: =H24+G25 -> 680 | I25: =IF(T_T134111213141516171819[[#This Row],[Total]]<0,T_T134111213141516171819[[#This Row],[Total]]*-1,0) -> 0
B26: Pago mantenimiento abril/2025 | G26: =SUM(D26:F26) -> 0 | H26: =H25+G26 -> 680 | I26: =IF(T_T134111213141516171819[[#This Row],[Total]]<0,T_T134111213141516171819[[#This Row],[Total]]*-1,0) -> 0
A27: 45807 | B27: Mantenimiento mayo/2025 | D27: 212 | E27: 123 | G27: =SUM(D27:F27) -> 335 | H27: =H26+G27 -> 1015 | I27: =IF(T_T134111213141516171819[[#This Row],[Total]]<0,T_T134111213141516171819[[#This Row],[Total]]*-1,0) -> 0
B28: Pago mantenimiento mayo/2025 | G28: =SUM(D28:F28) -> 0 | H28: =H27+G28 -> 1015 | I28: =IF(T_T134111213141516171819[[#This Row],[Total]]<0,T_T134111213141516171819[[#This Row],[Total]]*-1,0) -> 0
A29: 45838 | B29: Mantenimiento junio/2025 | G29: =SUM(D29:F29) -> 0 | H29: =H28+G29 -> 1015 | I29: =IF(T_T134111213141516171819[[#This Row],[Total]]<0,T_T134111213141516171819[[#This Row],[Total]]*-1,0) -> 0
B30: Pago mantenimiento junio/2025 | G30: =SUM(D30:F30) -> 0 | H30: =H29+G30 -> 1015 | I30: =IF(T_T134111213141516171819[[#This Row],[Total]]<0,T_T134111213141516171819[[#This Row],[Total]]*-1,0) -> 0
A31: 45868 | B31: Mantenimiento julio/2025 | G31: =SUM(D31:F31) -> 0 | H31: =H30+G31 -> 1015 | I31: =IF(T_T134111213141516171819[[#This Row],[Total]]<0,T_T134111213141516171819[[#This Row],[Total]]*-1,0) -> 0
B32: Pago mantenimient julio/2025 | G32: =SUM(D32:F32) -> 0 | H32: =H31+G32 -> 1015 | I32: =IF(T_T134111213141516171819[[#This Row],[Total]]<0,T_T134111213141516171819[[#This Row],[Total]]*-1,0) -> 0
A33: 45899 | B33: Mantenimiento agosto/2025 | G33: =SUM(D33:F33) -> 0 | H33: =H32+G33 -> 1015 | I33: =IF(T_T134111213141516171819[[#This Row],[Total]]<0,T_T134111213141516171819[[#This Row],[Total]]*-1,0) -> 0
B34: Pago mantenimiento agosto/2025 | G34: =SUM(D34:F34) -> 0 | H34: =H33+G34 -> 1015 | I34: =IF(T_T134111213141516171819[[#This Row],[Total]]<0,T_T134111213141516171819[[#This Row],[Total]]*-1,0) -> 0
A35: 45930 | B35: Mantenimiento septiembre/2025 | G35: =SUM(D35:F35) -> 0 | H35: =H34+G35 -> 1015 | I35: =IF(T_T134111213141516171819[[#This Row],[Total]]<0,T_T134111213141516171819[[#This Row],[Total]]*-1,0) -> 0
B36: Pago mantenimiento septiembre/2025 | G36: =SUM(D36:F36) -> 0 | H36: =H35+G36 -> 1015 | I36: =IF(T_T134111213141516171819[[#This Row],[Total]]<0,T_T134111213141516171819[[#This Row],[Total]]*-1,0) -> 0
A37: 45960 | B37: Mantenimiento octubre /2025 | G37: =SUM(D37:F37) -> 0 | H37: =H36+G37 -> 1015 | I37: =IF(T_T134111213141516171819[[#This Row],[Total]]<0,T_T134111213141516171819[[#This Row],[Total]]*-1,0) -> 0
B38: Pago mantenimiento octubre/2025 | G38: =SUM(D38:F38) -> 0 | H38: =H37+G38 -> 1015 | I38: =IF(T_T134111213141516171819[[#This Row],[Total]]<0,T_T134111213141516171819[[#This Row],[Total]]*-1,0) -> 0
A39: 45991 | B39: Mantenimiento noviembre/2025 | G39: =SUM(D39:F39) -> 0 | H39: =H38+G39 -> 1015 | I39: =IF(T_T134111213141516171819[[#This Row],[Total]]<0,T_T134111213141516171819[[#This Row],[Total]]*-1,0) -> 0
B40: Pago mantenimiento noviembre/2025 | G40: =SUM(D40:F40) -> 0 | H40: =H39+G40 -> 1015 | I40: =IF(T_T134111213141516171819[[#This Row],[Total]]<0,T_T134111213141516171819[[#This Row],[Total]]*-1,0) -> 0
A41: 46021 | B41: Mantenimiento diciembre/2025 | G41: =SUM(D41:F41) -> 0 | H41: =H40+G41 -> 1015 | I41: =IF(T_T134111213141516171819[[#This Row],[Total]]<0,T_T134111213141516171819[[#This Row],[Total]]*-1,0) -> 0
B42: Pago de Mantenimiento diciembre/2025 | G42: =SUM(D42:F42) -> 0 | H42: =H41+G42 -> 1015 | I42: =IF(T_T134111213141516171819[[#This Row],[Total]]<0,T_T134111213141516171819[[#This Row],[Total]]*-1,0) -> 0

Sheet OF.3B
A2: Departamento : | B2: OF.3B
A3: Propietario : | B3: LUPE MARCELA LECOÑA
A4: Inquilino : | B4: =LOOKUP(B2,#REF!,#REF!) -> #REF!
A5: Teléfono : | B5: =LOOKUP(B2,#REF!,#REF!) -> #REF!
A6: Celular : | B6: =LOOKUP(B2,#REF!,#REF!) -> #REF!
A7: Correo : | B7: =LOOKUP(B2,#REF!,#REF!) -> #REF! | H7: Resumen
A9: Fecha | B9: Concepto | C9: Recibo | D9: Expensas | E9: Agua | F9: Multa | G9: Total | H9: Deuda | I9: Pagado | J9: Columna1 | K9: Columna2
B10: DEUDA GESTION 2017-2020 | H10: 0 | I10: =IF(T_T13411121314151617181920[[#This Row],[Total]]<0,T_T13411121314151617181920[[#This Row],[Total]]*-1,0) -> 0
B11: DEUDA GESTION 2021 | H11: 0 | I11: =IF(T_T13411121314151617181920[[#This Row],[Total]]<0,T_T13411121314151617181920[[#This Row],[Total]]*-1,0) -> 0
B12: DEUDA GESTION 2022 | H12: 0 | I12: =IF(T_T13411121314151617181920[[#This Row],[Total]]<0,T_T13411121314151617181920[[#This Row],[Total]]*-1,0) -> 0
B13: DEUDA GESTION 2023 | H13: 0 | I13: =IF(T_T13411121314151617181920[[#This Row],[Total]]<0,T_T13411121314151617181920[[#This Row],[Total]]*-1,0) -> 0
B14: DEUDA GESTION 2024 | I14: =IF(T_T13411121314151617181920[[#This Row],[Total]]<0,T_T13411121314151617181920[[#This Row],[Total]]*-1,0) -> 0
A15: 46052 | B15: Mantenimiento enero/2026 | D15: 176 | E15: 9 | G15: =SUM(D15:F15) -> 185 | H15: =+H13+T_T13411121314151617181920[[#This Row],[Total]] -> 185 | I15: =IF(T_T13411121314151617181920[[#This Row],[Total]]<0,T_T13411121314151617181920[[#This Row],[Total]]*-1,0) -> 0
B16: Pago mantenimiento enero/2026 | G16: =SUM(D16:F16) -> 0 | H16: =H15+G16 -> 185 | I16: =IF(T_T13411121314151617181920[[#This Row],[Total]]<0,T_T13411121314151617181920[[#This Row],[Total]]*-1,0) -> 0
A17: 46080 | B17: Mantenimiento febrero/2026 | D17: 176 | E17: 17 | G17: =SUM(D17:F17) -> 193 | H17: =H16+G17 -> 378 | I17: =IF(T_T13411121314151617181920[[#This Row],[Total]]<0,T_T13411121314151617181920[[#This Row],[Total]]*-1,0) -> 0
B18: Pago mantenimiento febrero/2026 | G18: =SUM(D18:F18) -> 0 | H18: =H17+G18 -> 378 | I18: =IF(T_T13411121314151617181920[[#This Row],[Total]]<0,T_T13411121314151617181920[[#This Row],[Total]]*-1,0) -> 0
A19: 45747 | B19: Mantenimiento marzo/2025 | D19: 211 | E19: 21 | G19: =SUM(D19:F19) -> 232 | H19: =H18+G19 -> 610 | I19: =IF(T_T13411121314151617181920[[#This Row],[Total]]<0,T_T13411121314151617181920[[#This Row],[Total]]*-1,0) -> 0
B20: Pago matenimiento marzo/2025 | G20: =SUM(D20:F20) -> 0 | H20: =H19+G20 -> 610 | I20: =IF(T_T13411121314151617181920[[#This Row],[Total]]<0,T_T13411121314151617181920[[#This Row],[Total]]*-1,0) -> 0
A21: 45777 | B21: Mantenimiento abril/2025 | D21: 211 | E21: 19 | G21: =SUM(D21:F21) -> 230 | H21: =H20+G21 -> 840 | I21: =IF(T_T13411121314151617181920[[#This Row],[Total]]<0,T_T13411121314151617181920[[#This Row],[Total]]*-1,0) -> 0
B22: Pago mantenimiento abril/2025 | G22: =SUM(D22:F22) -> 0 | H22: =H21+G22 -> 840 | I22: =IF(T_T13411121314151617181920[[#This Row],[Total]]<0,T_T13411121314151617181920[[#This Row],[Total]]*-1,0) -> 0
A23: 45807 | B23: Mantenimiento mayo/2025 | D23: 211 | E23: 23 | G23: =SUM(D23:F23) -> 234 | H23: =H22+G23 -> 1074 | I23: =IF(T_T13411121314151617181920[[#This Row],[Total]]<0,T_T13411121314151617181920[[#This Row],[Total]]*-1,0) -> 0
B24: Pago mantenimiento mayo/2025 | G24: =SUM(D24:F24) -> 0 | H24: =H23+G24 -> 1074 | I24: =IF(T_T13411121314151617181920[[#This Row],[Total]]<0,T_T13411121314151617181920[[#This Row],[Total]]*-1,0) -> 0
A25: 45838 | B25: Mantenimiento junio/2025 | G25: =SUM(D25:F25) -> 0 | H25: =H24+G25 -> 1074 | I25: =IF(T_T13411121314151617181920[[#This Row],[Total]]<0,T_T13411121314151617181920[[#This Row],[Total]]*-1,0) -> 0
B26: Pago mantenimiento junio/2025 | G26: =SUM(D26:F26) -> 0 | H26: =H25+G26 -> 1074 | I26: =IF(T_T13411121314151617181920[[#This Row],[Total]]<0,T_T13411121314151617181920[[#This Row],[Total]]*-1,0) -> 0
A27: 45868 | B27: Mantenimiento julio/2025 | G27: =SUM(D27:F27) -> 0 | H27: =H26+G27 -> 1074 | I27: =IF(T_T13411121314151617181920[[#This Row],[Total]]<0,T_T13411121314151617181920[[#This Row],[Total]]*-1,0) -> 0
B28: Pago mantenimient julio/2025 | G28: =SUM(D28:F28) -> 0 | H28: =H27+G28 -> 1074 | I28: =IF(T_T13411121314151617181920[[#This Row],[Total]]<0,T_T13411121314151617181920[[#This Row],[Total]]*-1,0) -> 0
A29: 45899 | B29: Mantenimiento agosto/2025 | G29: =SUM(D29:F29) -> 0 | H29: =H28+G29 -> 1074 | I29: =IF(T_T13411121314151617181920[[#This Row],[Total]]<0,T_T13411121314151617181920[[#This Row],[Total]]*-1,0) -> 0
B30: Pago mantenimiento agosto/2025 | G30: =SUM(D30:F30) -> 0 | H30: =H29+G30 -> 1074 | I30: =IF(T_T13411121314151617181920[[#This Row],[Total]]<0,T_T13411121314151617181920[[#This Row],[Total]]*-1,0) -> 0
A31: 45930 | B31: Mantenimiento septiembre/2025 | G31: =SUM(D31:F31) -> 0 | H31: =H30+G31 -> 1074 | I31: =IF(T_T13411121314151617181920[[#This Row],[Total]]<0,T_T13411121314151617181920[[#This Row],[Total]]*-1,0) -> 0
B32: Pago mantenimiento septiembre/2025 | G32: =SUM(D32:F32) -> 0 | H32: =H31+G32 -> 1074 | I32: =IF(T_T13411121314151617181920[[#This Row],[Total]]<0,T_T13411121314151617181920[[#This Row],[Total]]*-1,0) -> 0
A33: 45960 | B33: Mantenimiento octubre /2025 | G33: =SUM(D33:F33) -> 0 | H33: =H32+G33 -> 1074 | I33: =IF(T_T13411121314151617181920[[#This Row],[Total]]<0,T_T13411121314151617181920[[#This Row],[Total]]*-1,0) -> 0
B34: Pago mantenimiento octubre/2025 | G34: =SUM(D34:F34) -> 0 | H34: =H33+G34 -> 1074 | I34: =IF(T_T13411121314151617181920[[#This Row],[Total]]<0,T_T13411121314151617181920[[#This Row],[Total]]*-1,0) -> 0
A35: 45991 | B35: Mantenimiento noviembre/2025 | G35: =SUM(D35:F35) -> 0 | H35: =H34+G35 -> 1074 | I35: =IF(T_T13411121314151617181920[[#This Row],[Total]]<0,T_T13411121314151617181920[[#This Row],[Total]]*-1,0) -> 0
B36: Pago mantenimiento noviembre/2025 | G36: =SUM(D36:F36) -> 0 | H36: =H35+G36 -> 1074 | I36: =IF(T_T13411121314151617181920[[#This Row],[Total]]<0,T_T13411121314151617181920[[#This Row],[Total]]*-1,0) -> 0
A37: 46021 | B37: Mantenimiento diciembre/2025 | G37: =SUM(D37:F37) -> 0 | H37: =H36+G37 -> 1074 | I37: =IF(T_T13411121314151617181920[[#This Row],[Total]]<0,T_T13411121314151617181920[[#This Row],[Total]]*-1,0) -> 0
B38: Pago de Mantenimiento diciembre/2025 | G38: =SUM(D38:F38) -> 0 | H38: =H37+G38 -> 1074 | I38: =IF(T_T13411121314151617181920[[#This Row],[Total]]<0,T_T13411121314151617181920[[#This Row],[Total]]*-1,0) -> 0
G39: =SUM(D39:F47) -> 0 | H39: =H38+G39 -> 1074 | I39: =IF(T_T13411121314151617181920[[#This Row],[Total]]<0,T_T13411121314151617181920[[#This Row],[Total]]*-1,0) -> 0
H40: =H39+G40 -> 1074 | I40: =IF(T_T13411121314151617181920[[#This Row],[Total]]<0,T_T13411121314151617181920[[#This Row],[Total]]*-1,0) -> 0
I41: =IF(T_T13411121314151617181920[[#This Row],[Total]]<0,T_T13411121314151617181920[[#This Row],[Total]]*-1,0) -> 0

Sheet OF.3C
A2: Departamento : | B2: OF.3C
A3: Propietario : | B3: APRINTEL SRL
A4: Inquilino : | B4: =LOOKUP(B2,#REF!,#REF!) -> #REF!
A5: Teléfono : | B5: =LOOKUP(B2,#REF!,#REF!) -> #REF!
A6: Celular : | B6: =LOOKUP(B2,#REF!,#REF!) -> #REF!
A7: Correo : | B7: =LOOKUP(B2,#REF!,#REF!) -> #REF! | H7: Resumen
A9: Fecha | B9: Concepto | C9: Recibo | D9: Expensas | E9: Agua | F9: Multa | G9: Total | H9: Deuda | I9: Pagado | J9: Columna1
B10: DEUDA GESTION 2017-2020 | H10: 0 | I10: =IF(T_T1341112131415161718192021[[#This Row],[Total]]<0,T_T1341112131415161718192021[[#This Row],[Total]]*-1,0) -> 0
B11: DEUDA GESTION 2021 | H11: 0 | I11: =IF(T_T1341112131415161718192021[[#This Row],[Total]]<0,T_T1341112131415161718192021[[#This Row],[Total]]*-1,0) -> 0
B12: DEUDA GESTION 2022 | H12: 0 | I12: =IF(T_T1341112131415161718192021[[#This Row],[Total]]<0,T_T1341112131415161718192021[[#This Row],[Total]]*-1,0) -> 0
B13: DEUDA GESTION 2023 | I13: =IF(T_T1341112131415161718192021[[#This Row],[Total]]<0,T_T1341112131415161718192021[[#This Row],[Total]]*-1,0) -> 0
B14: DEUDA GESTION 2024 | I14: =IF(T_T1341112131415161718192021[[#This Row],[Total]]<0,T_T1341112131415161718192021[[#This Row],[Total]]*-1,0) -> 0
A15: 46052 | B15: Mantenimiento enero/2026 | D15: 189 | G15: =SUM(D15:F15) -> 189 | H15: =+H13+T_T1341112131415161718192021[[#This Row],[Total]] -> 189 | I15: =IF(T_T1341112131415161718192021[[#This Row],[Total]]<0,T_T1341112131415161718192021[[#This Row],[Total]]*-1,0) -> 0
B16: Pago mantenimiento enero/2026 | C16: 8629 | D16: -189 | G16: =SUM(D16:F16) -> -189 | H16: =H15+G16 -> 0 | I16: =IF(T_T1341112131415161718192021[[#This Row],[Total]]<0,T_T1341112131415161718192021[[#This Row],[Total]]*-1,0) -> 189
A17: 45715 | B17: Mantenimiento febrero/2025 | D17: 189 | G17: =SUM(D17:F17) -> 189 | H17: =H16+G17 -> 189 | I17: =IF(T_T1341112131415161718192021[[#This Row],[Total]]<0,T_T1341112131415161718192021[[#This Row],[Total]]*-1,0) -> 0
B18: Pago mantenimiento febrero/2025 | G18: =SUM(D18:F18) -> 0 | H18: =H17+G18 -> 189 | I18: =IF(T_T1341112131415161718192021[[#This Row],[Total]]<0,T_T1341112131415161718192021[[#This Row],[Total]]*-1,0) -> 0
A19: 45747 | B19: Mantenimiento marzo/2025 | D19: 227 | G19: =SUM(D19:F19) -> 227 | H19: =H18+G19 -> 416 | I19: =IF(T_T1341112131415161718192021[[#This Row],[Total]]<0,T_T1341112131415161718192021[[#This Row],[Total]]*-1,0) -> 0
B20: Pago matenimiento marzo/2025 | G20: =SUM(D20:F20) -> 0 | H20: =H19+G20 -> 416 | I20: =IF(T_T1341112131415161718192021[[#This Row],[Total]]<0,T_T1341112131415161718192021[[#This Row],[Total]]*-1,0) -> 0
A21: 45777 | B21: Mantenimiento abril/2025 | D21: 227 | E21: 15 | G21: =SUM(D21:F21) -> 242 | H21: =H20+G21 -> 658 | I21: =IF(T_T1341112131415161718192021[[#This Row],[Total]]<0,T_T1341112131415161718192021[[#This Row],[Total]]*-1,0) -> 0
B22: Pago mantenimiento abril/2025 | G22: =SUM(D22:F22) -> 0 | H22: =H21+G22 -> 658 | I22: =IF(T_T1341112131415161718192021[[#This Row],[Total]]<0,T_T1341112131415161718192021[[#This Row],[Total]]*-1,0) -> 0
A23: 45807 | B23: Mantenimiento mayo/2025 | D23: 227 | E23: 12 | G23: =SUM(D23:F23) -> 239 | H23: =H22+G23 -> 897 | I23: =IF(T_T1341112131415161718192021[[#This Row],[Total]]<0,T_T1341112131415161718192021[[#This Row],[Total]]*-1,0) -> 0
B24: Pago mantenimiento mayo/2025 | G24: =SUM(D24:F24) -> 0 | H24: =H23+G24 -> 897 | I24: =IF(T_T1341112131415161718192021[[#This Row],[Total]]<0,T_T1341112131415161718192021[[#This Row],[Total]]*-1,0) -> 0
A25: 45838 | B25: Mantenimiento junio/2025 | G25: =SUM(D25:F25) -> 0 | H25: =H24+G25 -> 897 | I25: =IF(T_T1341112131415161718192021[[#This Row],[Total]]<0,T_T1341112131415161718192021[[#This Row],[Total]]*-1,0) -> 0
B26: Pago mantenimiento junio/2025 | G26: =SUM(D26:F26) -> 0 | H26: =H25+G26 -> 897 | I26: =IF(T_T1341112131415161718192021[[#This Row],[Total]]<0,T_T1341112131415161718192021[[#This Row],[Total]]*-1,0) -> 0
A27: 45868 | B27: Mantenimiento julio/2025 | G27: =SUM(D27:F27) -> 0 | H27: =H26+G27 -> 897 | I27: =IF(T_T1341112131415161718192021[[#This Row],[Total]]<0,T_T1341112131415161718192021[[#This Row],[Total]]*-1,0) -> 0
B28: Pago mantenimient julio/2025 | G28: =SUM(D28:F28) -> 0 | H28: =H27+G28 -> 897 | I28: =IF(T_T1341112131415161718192021[[#This Row],[Total]]<0,T_T1341112131415161718192021[[#This Row],[Total]]*-1,0) -> 0
A29: 45899 | B29: Mantenimiento agosto/2025 | G29: =SUM(D29:F29) -> 0 | H29: =H28+G29 -> 897 | I29: =IF(T_T1341112131415161718192021[[#This Row],[Total]]<0,T_T1341112131415161718192021[[#This Row],[Total]]*-1,0) -> 0
B30: Pago mantenimiento agosto/2025 | G30: =SUM(D30:F30) -> 0 | H30: =H29+G30 -> 897 | I30: =IF(T_T1341112131415161718192021[[#This Row],[Total]]<0,T_T1341112131415161718192021[[#This Row],[Total]]*-1,0) -> 0
A31: 45930 | B31: Mantenimiento septiembre/2025 | G31: =SUM(D31:F31) -> 0 | H31: =H30+G31 -> 897 | I31: =IF(T_T1341112131415161718192021[[#This Row],[Total]]<0,T_T1341112131415161718192021[[#This Row],[Total]]*-1,0) -> 0
B32: Pago mantenimiento septiembre/2025 | G32: =SUM(D32:F32) -> 0 | H32: =H31+G32 -> 897 | I32: =IF(T_T1341112131415161718192021[[#This Row],[Total]]<0,T_T1341112131415161718192021[[#This Row],[Total]]*-1,0) -> 0
A33: 45960 | B33: Mantenimiento octubre /2025 | G33: =SUM(D33:F33) -> 0 | H33: =H32+G33 -> 897 | I33: =IF(T_T1341112131415161718192021[[#This Row],[Total]]<0,T_T1341112131415161718192021[[#This Row],[Total]]*-1,0) -> 0
B34: Pago mantenimiento octubre/2025 | G34: =SUM(D34:F34) -> 0 | H34: =H33+G34 -> 897 | I34: =IF(T_T1341112131415161718192021[[#This Row],[Total]]<0,T_T1341112131415161718192021[[#This Row],[Total]]*-1,0) -> 0
A35: 45991 | B35: Mantenimiento noviembre/2025 | G35: =SUM(D35:F35) -> 0 | H35: =H34+G35 -> 897 | I35: =IF(T_T1341112131415161718192021[[#This Row],[Total]]<0,T_T1341112131415161718192021[[#This Row],[Total]]*-1,0) -> 0
B36: Pago mantenimiento noviembre/2025 | G36: =SUM(D36:F36) -> 0 | H36: =H35+G36 -> 897 | I36: =IF(T_T1341112131415161718192021[[#This Row],[Total]]<0,T_T1341112131415161718192021[[#This Row],[Total]]*-1,0) -> 0
A37: 46021 | B37: Mantenimiento diciembre/2025 | G37: =SUM(D37:F37) -> 0 | H37: =H36+G37 -> 897 | I37: =IF(T_T1341112131415161718192021[[#This Row],[Total]]<0,T_T1341112131415161718192021[[#This Row],[Total]]*-1,0) -> 0
B38: Pago de Mantenimiento diciembre/2025 | G38: =SUM(D38:F38) -> 0 | H38: =H37+G38 -> 897 | I38: =IF(T_T1341112131415161718192021[[#This Row],[Total]]<0,T_T1341112131415161718192021[[#This Row],[Total]]*-1,0) -> 0
G39: =SUM(D39:F39) -> 0 | H39: =H38+G39 -> 897 | I39: =IF(T_T1341112131415161718192021[[#This Row],[Total]]<0,T_T1341112131415161718192021[[#This Row],[Total]]*-1,0) -> 0
G40: =SUM(D40:F40) -> 0 | H40: =H39+G40 -> 897 | I40: =IF(T_T1341112131415161718192021[[#This Row],[Total]]<0,T_T1341112131415161718192021[[#This Row],[Total]]*-1,0) -> 0
G41: =SUM(D41:F48) -> 0 | H41: =H40+G41 -> 897 | I41: =IF(T_T1341112131415161718192021[[#This Row],[Total]]<0,T_T1341112131415161718192021[[#This Row],[Total]]*-1,0) -> 0
G42: =SUM(D42:F49) -> 0 | H42: =H41+G42 -> 897 | I42: =IF(T_T1341112131415161718192021[[#This Row],[Total]]<0,T_T1341112131415161718192021[[#This Row],[Total]]*-1,0) -> 0

Sheet OF.3D
A2: Departamento : | B2: OF.3D
A3: Propietario : | B3: APRINTEL SRL
A4: Inquilino : | B4: =LOOKUP(B2,#REF!,#REF!) -> #REF!
A5: Teléfono : | B5: =LOOKUP(B2,#REF!,#REF!) -> #REF!
A6: Celular : | B6: =LOOKUP(B2,#REF!,#REF!) -> #REF!
A7: Correo : | B7: =LOOKUP(B2,#REF!,#REF!) -> #REF! | H7: Resumen
A9: Fecha | B9: Concepto | C9: Recibo | D9: Expensas | E9: Agua | F9: Multa | G9: Total | H9: Deuda | I9: Pagado | J9: Columna1
B10: DEUDA GESTION 2017-2020 | I10: =IF(T_T134111213141516171819202122[[#This Row],[Total]]<0,T_T134111213141516171819202122[[#This Row],[Total]]*-1,0) -> 0
B11: DEUDA GESTION 2021 | H11: 0 | I11: =IF(T_T134111213141516171819202122[[#This Row],[Total]]<0,T_T134111213141516171819202122[[#This Row],[Total]]*-1,0) -> 0
B12: DEUDA GESTION 2022 | H12: 0 | I12: =IF(T_T134111213141516171819202122[[#This Row],[Total]]<0,T_T134111213141516171819202122[[#This Row],[Total]]*-1,0) -> 0
B13: DEUDA GESTION 2023 | H13: 0 | I13: =IF(T_T134111213141516171819202122[[#This Row],[Total]]<0,T_T134111213141516171819202122[[#This Row],[Total]]*-1,0) -> 0
B14: DEUDA GESTION 2024 | I14: =IF(T_T134111213141516171819202122[[#This Row],[Total]]<0,T_T134111213141516171819202122[[#This Row],[Total]]*-1,0) -> 0
A15: 46052 | B15: Mantenimiento enero/2026 | D15: 184 | E15: 13 | G15: =SUM(D15:F15) -> 197 | H15: =+H13+T_T134111213141516171819202122[[#This Row],[Total]] -> 197 | I15: =IF(T_T134111213141516171819202122[[#This Row],[Total]]<0,T_T134111213141516171819202122[[#This Row],[Total]]*-1,0) -> 0
B16: Pago mantenimiento enero/2026 | C16: 8630 | D16: -184 | E16: -13 | G16: =SUM(D16:F16) -> -197 | H16: =H15+G16 -> 0 | I16: =IF(T_T134111213141516171819202122[[#This Row],[Total]]<0,T_T134111213141516171819202122[[#This Row],[Total]]*-1,0) -> 197
A17: 46081 | B17: Mantenimiento febrero/2026 | D17: 184 | E17: 18 | G17: =SUM(D17:F17) -> 202 | H17: =H16+G17 -> 202 | I17: =IF(T_T134111213141516171819202122[[#This Row],[Total]]<0,T_T134111213141516171819202122[[#This Row],[Total]]*-1,0) -> 0
B18: Pago mantenimiento febrero/2026 | G18: =SUM(D18:F18) -> 0 | H18: =H17+G18 -> 202 | I18: =IF(T_T134111213141516171819202122[[#This Row],[Total]]<0,T_T134111213141516171819202122[[#This Row],[Total]]*-1,0) -> 0
A19: 45747 | B19: Mantenimiento marzo/2025 | D19: 221 | E19: 15 | G19: =SUM(D19:F19) -> 236 | H19: =H18+G19 -> 438 | I19: =IF(T_T134111213141516171819202122[[#This Row],[Total]]<0,T_T134111213141516171819202122[[#This Row],[Total]]*-1,0) -> 0
B20: Pago matenimiento marzo/2025 | G20: =SUM(D20:F20) -> 0 | H20: =H19+G20 -> 438 | I20: =IF(T_T134111213141516171819202122[[#This Row],[Total]]<0,T_T134111213141516171819202122[[#This Row],[Total]]*-1,0) -> 0
A21: 45777 | B21: Mantenimiento abril/2025 | D21: 221 | E21: 8 | G21: =SUM(D21:F21) -> 229 | H21: =H20+G21 -> 667 | I21: =IF(T_T134111213141516171819202122[[#This Row],[Total]]<0,T_T134111213141516171819202122[[#This Row],[Total]]*-1,0) -> 0
B22: Pago mantenimiento abril/2025 | G22: =SUM(D22:F22) -> 0 | H22: =H21+G22 -> 667 | I22: =IF(T_T134111213141516171819202122[[#This Row],[Total]]<0,T_T134111213141516171819202122[[#This Row],[Total]]*-1,0) -> 0
A23: 45807 | B23: Mantenimiento mayo/2025 | D23: 221 | E23: 0 | G23: =SUM(D23:F23) -> 221 | H23: =H22+G23 -> 888 | I23: =IF(T_T134111213141516171819202122[[#This Row],[Total]]<0,T_T134111213141516171819202122[[#This Row],[Total]]*-1,0) -> 0
B24: Pago mantenimiento mayo/2025 | G24: =SUM(D24:F24) -> 0 | H24: =H23+G24 -> 888 | I24: =IF(T_T134111213141516171819202122[[#This Row],[Total]]<0,T_T134111213141516171819202122[[#This Row],[Total]]*-1,0) -> 0
A25: 45838 | B25: Mantenimiento junio/2025 | G25: =SUM(D25:F25) -> 0 | H25: =H24+G25 -> 888 | I25: =IF(T_T134111213141516171819202122[[#This Row],[Total]]<0,T_T134111213141516171819202122[[#This Row],[Total]]*-1,0) -> 0
B26: Pago mantenimiento junio/2025 | G26: =SUM(D26:F26) -> 0 | H26: =H25+G26 -> 888 | I26: =IF(T_T134111213141516171819202122[[#This Row],[Total]]<0,T_T134111213141516171819202122[[#This Row],[Total]]*-1,0) -> 0
A27: 45868 | B27: Mantenimiento julio/2025 | G27: =SUM(D27:F27) -> 0 | H27: =H26+G27 -> 888 | I27: =IF(T_T134111213141516171819202122[[#This Row],[Total]]<0,T_T134111213141516171819202122[[#This Row],[Total]]*-1,0) -> 0
B28: Pago mantenimient julio/2025 | G28: =SUM(D28:F28) -> 0 | H28: =H27+G28 -> 888 | I28: =IF(T_T134111213141516171819202122[[#This Row],[Total]]<0,T_T134111213141516171819202122[[#This Row],[Total]]*-1,0) -> 0
A29: 45899 | B29: Mantenimiento agosto/2025 | G29: =SUM(D29:F29) -> 0 | H29: =H28+G29 -> 888 | I29: =IF(T_T134111213141516171819202122[[#This Row],[Total]]<0,T_T134111213141516171819202122[[#This Row],[Total]]*-1,0) -> 0
B30: Pago mantenimiento agosto/2025 | G30: =SUM(D30:F30) -> 0 | H30: =H29+G30 -> 888 | I30: =IF(T_T134111213141516171819202122[[#This Row],[Total]]<0,T_T134111213141516171819202122[[#This Row],[Total]]*-1,0) -> 0
A31: 45930 | B31: Mantenimiento septiembre/2025 | G31: =SUM(D31:F31) -> 0 | H31: =H30+G31 -> 888 | I31: =IF(T_T134111213141516171819202122[[#This Row],[Total]]<0,T_T134111213141516171819202122[[#This Row],[Total]]*-1,0) -> 0
B32: Pago mantenimiento septiembre/2025 | G32: =SUM(D32:F32) -> 0 | H32: =H31+G32 -> 888 | I32: =IF(T_T134111213141516171819202122[[#This Row],[Total]]<0,T_T134111213141516171819202122[[#This Row],[Total]]*-1,0) -> 0
A33: 45960 | B33: Mantenimiento octubre /2025 | G33: =SUM(D33:F33) -> 0 | H33: =H32+G33 -> 888 | I33: =IF(T_T134111213141516171819202122[[#This Row],[Total]]<0,T_T134111213141516171819202122[[#This Row],[Total]]*-1,0) -> 0
B34: Pago mantenimiento octubre/2025 | G34: =SUM(D34:F34) -> 0 | H34: =H33+G34 -> 888 | I34: =IF(T_T134111213141516171819202122[[#This Row],[Total]]<0,T_T134111213141516171819202122[[#This Row],[Total]]*-1,0) -> 0
A35: 45991 | B35: Mantenimiento noviembre/2025 | G35: =SUM(D35:F35) -> 0 | H35: =H34+G35 -> 888 | I35: =IF(T_T134111213141516171819202122[[#This Row],[Total]]<0,T_T134111213141516171819202122[[#This Row],[Total]]*-1,0) -> 0
B36: Pago mantenimiento noviembre/2025 | G36: =SUM(D36:F36) -> 0 | H36: =H35+G36 -> 888 | I36: =IF(T_T134111213141516171819202122[[#This Row],[Total]]<0,T_T134111213141516171819202122[[#This Row],[Total]]*-1,0) -> 0
A37: 46021 | B37: Mantenimiento diciembre/2025 | G37: =SUM(D37:F37) -> 0 | H37: =H36+G37 -> 888 | I37: =IF(T_T134111213141516171819202122[[#This Row],[Total]]<0,T_T134111213141516171819202122[[#This Row],[Total]]*-1,0) -> 0
B38: Pago de Mantenimiento diciembre/2025 | G38: =SUM(D38:F38) -> 0 | H38: =H37+G38 -> 888 | I38: =IF(T_T134111213141516171819202122[[#This Row],[Total]]<0,T_T134111213141516171819202122[[#This Row],[Total]]*-1,0) -> 0
G39: =SUM(D39:F47) -> 0 | H39: =H38+G39 -> 888 | I39: =IF(T_T134111213141516171819202122[[#This Row],[Total]]<0,T_T134111213141516171819202122[[#This Row],[Total]]*-1,0) -> 0
G40: =SUM(D40:F48) -> 0 | H40: =H39+G40 -> 888 | I40: =IF(T_T134111213141516171819202122[[#This Row],[Total]]<0,T_T134111213141516171819202122[[#This Row],[Total]]*-1,0) -> 0
I41: =IF(T_T134111213141516171819202122[[#This Row],[Total]]<0,T_T134111213141516171819202122[[#This Row],[Total]]*-1,0) -> 0

Sheet OF.4A
A2: Departamento : | B2: OF.4A
A3: Propietario : | B3: VICTOR CENTENO
A4: Inquilino : | B4: =LOOKUP(B2,#REF!,#REF!) -> #REF!
A9: Fecha | B9: Concepto | C9: Recibo | D9: Expensas | E9: Agua | F9: Multa | G9: Total | H9: Deuda | I9: Pagado | J9: Columna1 | K9: Columna2 | L9: Columna3
B10: DEUDA GESTION 2017-2020 | H10: 0 | I10: =IF(T_T13411121314151617181920212223[[#This Row],[Total]]<0,T_T13411121314151617181920212223[[#This Row],[Total]]*-1,0) -> 0
B14: MUDANZA | G14: =SUM(D14:F14) -> 0 | H14: =+H13+T_T13411121314151617181920212223[[#This Row],[Total]] -> 0 | I14: =IF(T_T13411121314151617181920212223[[#This Row],[Total]]<0,T_T13411121314151617181920212223[[#This Row],[Total]]*-1,0) -> 0
B15: PAGO POR MUDANZA | G15: =SUM(D15:F15) -> 0 | H15: =+H14+T_T13411121314151617181920212223[[#This Row],[Total]] -> 0 | I15: =IF(T_T13411121314151617181920212223[[#This Row],[Total]]<0,T_T13411121314151617181920212223[[#This Row],[Total]]*-1,0) -> 0
B16: DEUDA GESTION 2024 | I16: =IF(T_T13411121314151617181920212223[[#This Row],[Total]]<0,T_T13411121314151617181920212223[[#This Row],[Total]]*-1,0) -> 0
A17: 46052 | B17: Mantenimiento enero/2026 | D17: 184 | E17: 93 | G17: =SUM(D17:F17) -> 277 | H17: =+H15+T_T13411121314151617181920212223[[#This Row],[Total]] -> 277 | I17: =IF(T_T13411121314151617181920212223[[#This Row],[Total]]<0,T_T13411121314151617181920212223[[#This Row],[Total]]*-1,0) -> 0
B18: Pago mantenimiento enero/2026 | C18: 8540 | D18: -184 | E18: -93 | G18: =SUM(D18:F18) -> -277 | H18: =+H17+T_T13411121314151617181920212223[[#This Row],[Total]] -> 0 | I18: =IF(T_T13411121314151617181920212223[[#This Row],[Total]]<0,T_T13411121314151617181920212223[[#This Row],[Total]]*-1,0) -> 277
A19: 46080 | B19: Mantenimiento febrero/2026 | D19: 184 | E19: 2 | G19: =SUM(D19:F19) -> 186 | H19: =+H18+T_T13411121314151617181920212223[[#This Row],[Total]] -> 186 | I19: =IF(T_T13411121314151617181920212223[[#This Row],[Total]]<0,T_T13411121314151617181920212223[[#This Row],[Total]]*-1,0) -> 0
B20: Pago mantenimiento febrero/2026 | C20: 8718 | D20: -184 | E20: -2 | G20: =SUM(D20:F20) -> -186 | H20: =H19+G20 -> 0 | I20: =IF(T_T13411121314151617181920212223[[#This Row],[Total]]<0,T_T13411121314151617181920212223[[#This Row],[Total]]*-1,0) -> 186
A21: 45747 | B21: Mantenimiento marzo/2025 | D21: 221 | E21: 1 | G21: =SUM(D21:F21) -> 222 | H21: =H20+G21 -> 222 | I21: =IF(T_T13411121314151617181920212223[[#This Row],[Total]]<0,T_T13411121314151617181920212223[[#This Row],[Total]]*-1,0) -> 0
B22: Pago matenimiento marzo/2025 | C22: 8817 | D22: -221 | E22: -1 | G22: =SUM(D22:F22) -> -222 | H22: =H21+G22 -> 0 | I22: =IF(T_T13411121314151617181920212223[[#This Row],[Total]]<0,T_T13411121314151617181920212223[[#This Row],[Total]]*-1,0) -> 222
A23: 45777 | B23: Mantenimiento abril/2025 | D23: 221 | E23: 1 | G23: =SUM(D23:F23) -> 222 | H23: =H22+G23 -> 222 | I23: =IF(T_T13411121314151617181920212223[[#This Row],[Total]]<0,T_T13411121314151617181920212223[[#This Row],[Total]]*-1,0) -> 0 | M23: LUIS MAURICIO VASQUEZ GUZMAN
B24: Pago mantenimiento abril/2025 | C24: 8925 | D24: -221 | E24: -1 | G24: =SUM(D24:F24) -> -222 | H24: =H23+G24 -> 0 | I24: =IF(T_T13411121314151617181920212223[[#This Row],[Total]]<0,T_T13411121314151617181920212223[[#This Row],[Total]]*-1,0) -> 222
A25: 45807 | B25: Mantenimiento mayo/2025 | D25: 221 | E25: 1 | G25: =SUM(D25:F25) -> 222 | H25: =H24+G25 -> 222 | I25: =IF(T_T13411121314151617181920212223[[#This Row],[Total]]<0,T_T13411121314151617181920212223[[#This Row],[Total]]*-1,0) -> 0
B26: Pago mantenimiento mayo/2025 | G26: =SUM(D26:F26) -> 0 | H26: =H25+G26 -> 222 | I26: =IF(T_T13411121314151617181920212223[[#This Row],[Total]]<0,T_T13411121314151617181920212223[[#This Row],[Total]]*-1,0) -> 0
A27: 45838 | B27: Mantenimiento junio/2025 | G27: =SUM(D27:F27) -> 0 | H27: =H26+G27 -> 222 | I27: =IF(T_T13411121314151617181920212223[[#This Row],[Total]]<0,T_T13411121314151617181920212223[[#This Row],[Total]]*-1,0) -> 0
B28: Pago mantenimiento junio/2025 | G28: =SUM(D28:F28) -> 0 | H28: =H27+G28 -> 222 | I28: =IF(T_T13411121314151617181920212223[[#This Row],[Total]]<0,T_T13411121314151617181920212223[[#This Row],[Total]]*-1,0) -> 0
A29: 45868 | B29: Mantenimiento julio/2025 | G29: =SUM(D29:F29) -> 0 | H29: =H28+G29 -> 222 | I29: =IF(T_T13411121314151617181920212223[[#This Row],[Total]]<0,T_T13411121314151617181920212223[[#This Row],[Total]]*-1,0) -> 0
B30: Pago mantenimient julio/2025 | G30: =SUM(D30:F30) -> 0 | H30: =H29+G30 -> 222 | I30: =IF(T_T13411121314151617181920212223[[#This Row],[Total]]<0,T_T13411121314151617181920212223[[#This Row],[Total]]*-1,0) -> 0
A31: 45899 | B31: Mantenimiento agosto/2025 | G31: =SUM(D31:F31) -> 0 | H31: =H30+G31 -> 222 | I31: =IF(T_T13411121314151617181920212223[[#This Row],[Total]]<0,T_T13411121314151617181920212223[[#This Row],[Total]]*-1,0) -> 0
B32: Pago mantenimiento agosto/2025 | G32: =SUM(D32:F32) -> 0 | H32: =H31+G32 -> 222 | I32: =IF(T_T13411121314151617181920212223[[#This Row],[Total]]<0,T_T13411121314151617181920212223[[#This Row],[Total]]*-1,0) -> 0
A33: 45930 | B33: Mantenimiento septiembre/2025 | G33: =SUM(D33:F33) -> 0 | H33: =H32+G33 -> 222 | I33: =IF(T_T13411121314151617181920212223[[#This Row],[Total]]<0,T_T13411121314151617181920212223[[#This Row],[Total]]*-1,0) -> 0
B34: Pago mantenimiento septiembre/2025 | G34: =SUM(D34:F34) -> 0 | H34: =H33+G34 -> 222 | I34: =IF(T_T13411121314151617181920212223[[#This Row],[Total]]<0,T_T13411121314151617181920212223[[#This Row],[Total]]*-1,0) -> 0
A35: 45960 | B35: Mantenimiento octubre /2025 | G35: =SUM(D35:F35) -> 0 | H35: =H34+G35 -> 222 | I35: =IF(T_T13411121314151617181920212223[[#This Row],[Total]]<0,T_T13411121314151617181920212223[[#This Row],[Total]]*-1,0) -> 0
B36: Pago mantenimiento octubre/2025 | G36: =SUM(D36:F36) -> 0 | H36: =H35+G36 -> 222 | I36: =IF(T_T13411121314151617181920212223[[#This Row],[Total]]<0,T_T13411121314151617181920212223[[#This Row],[Total]]*-1,0) -> 0
A37: 45991 | B37: Mantenimiento noviembre/2025 | G37: =SUM(D37:F37) -> 0 | H37: =H36+G37 -> 222 | I37: =IF(T_T13411121314151617181920212223[[#This Row],[Total]]<0,T_T13411121314151617181920212223[[#This Row],[Total]]*-1,0) -> 0
B38: Pago mantenimiento noviembre/2025 | G38: =SUM(D38:F38) -> 0 | H38: =H37+G38 -> 222 | I38: =IF(T_T13411121314151617181920212223[[#This Row],[Total]]<0,T_T13411121314151617181920212223[[#This Row],[Total]]*-1,0) -> 0
A39: 46021 | B39: Mantenimiento diciembre/2025 | G39: =SUM(D39:F39) -> 0 | H39: =H38+G39 -> 222 | I39: =IF(T_T13411121314151617181920212223[[#This Row],[Total]]<0,T_T13411121314151617181920212223[[#This Row],[Total]]*-1,0) -> 0
B40: Pago de Mantenimiento diciembre/2025 | G40: =SUM(D40:F40) -> 0 | H40: =H39+G40 -> 222 | I40: =IF(T_T13411121314151617181920212223[[#This Row],[Total]]<0,T_T13411121314151617181920212223[[#This Row],[Total]]*-1,0) -> 0
G41: =SUM(D41:F41) -> 0 | H41: =H40+G41 -> 222 | I41: =IF(T_T13411121314151617181920212223[[#This Row],[Total]]<0,T_T13411121314151617181920212223[[#This Row],[Total]]*-1,0) -> 0
G42: =SUM(D42:F42) -> 0 | H42: =H41+G42 -> 222 | I42: =IF(T_T13411121314151617181920212223[[#This Row],[Total]]<0,T_T13411121314151617181920212223[[#This Row],[Total]]*-1,0) -> 0
G43: =SUM(D43:F50) -> 0 | H43: =H42+G43 -> 222 | I43: =IF(T_T13411121314151617181920212223[[#This Row],[Total]]<0,T_T13411121314151617181920212223[[#This Row],[Total]]*-1,0) -> 0
G44: =SUM(D44:F51) -> 0 | H44: =H43+G44 -> 222 | I44: =IF(T_T13411121314151617181920212223[[#This Row],[Total]]<0,T_T13411121314151617181920212223[[#This Row],[Total]]*-1,0) -> 0

Sheet OF.4B
B2: OF.4B
A3: Propietario : | B3: DENIS GONZALO MENA REVOLLO
A4: Inquilino : | B4: =LOOKUP(B2,#REF!,#REF!) -> #REF!
A5: Teléfono : | B5: =LOOKUP(B2,#REF!,#REF!) -> #REF!
A6: Celular : | B6: =LOOKUP(B2,#REF!,#REF!) -> #REF!
A7: Correo : | B7: =LOOKUP(B2,#REF!,#REF!) -> #REF! | H7: Resumen
A9: Fecha | B9: Concepto | C9: Recibo | D9: Expensas | E9: Agua | F9: Multa | G9: Total | H9: Deuda | I9: Pagado
B10: DEUDA GESTION 2017-2020 | H10: 0 | I10: =IF(T_T1341112131415161718192021222324[[#This Row],[Total]]<0,T_T1341112131415161718192021222324[[#This Row],[Total]]*-1,0) -> 0
B11: DEUDA GESTION 2021 | H11: 0 | I11: =IF(T_T1341112131415161718192021222324[[#This Row],[Total]]<0,T_T1341112131415161718192021222324[[#This Row],[Total]]*-1,0) -> 0
B12: DEUDA GESTION 2022 | H12: 0 | I12: =IF(T_T1341112131415161718192021222324[[#This Row],[Total]]<0,T_T1341112131415161718192021222324[[#This Row],[Total]]*-1,0) -> 0
B13: DEUDA GESTION 2023 | H13: 0 | I13: =IF(T_T1341112131415161718192021222324[[#This Row],[Total]]<0,T_T1341112131415161718192021222324[[#This Row],[Total]]*-1,0) -> 0
B14: DEUDA GESTION 2024 | I14: =IF(T_T1341112131415161718192021222324[[#This Row],[Total]]<0,T_T1341112131415161718192021222324[[#This Row],[Total]]*-1,0) -> 0
A15: 46052 | B15: Mantenimiento enero/2026 | D15: 378 | G15: =SUM(D15:F15) -> 378 | H15: =+H13+T_T1341112131415161718192021222324[[#This Row],[Total]] -> 378 | I15: =IF(T_T1341112131415161718192021222324[[#This Row],[Total]]<0,T_T1341112131415161718192021222324[[#This Row],[Total]]*-1,0) -> 0
B16: Pago mantenimiento enero/2026 | C16: 8529 | D16: -378 | G16: =SUM(D16:F16) -> -378 | H16: =H15+G16 -> 0 | I16: =IF(T_T1341112131415161718192021222324[[#This Row],[Total]]<0,T_T1341112131415161718192021222324[[#This Row],[Total]]*-1,0) -> 378
A17: 46081 | B17: Mantenimiento febrero/2026 | D17: 378 | G17: =SUM(D17:F17) -> 378 | H17: =H16+G17 -> 378 | I17: =IF(T_T1341112131415161718192021222324[[#This Row],[Total]]<0,T_T1341112131415161718192021222324[[#This Row],[Total]]*-1,0) -> 0
B18: Pago mantenimiento febrero/2026 | G18: =SUM(D18:F18) -> 0 | H18: =H17+G18 -> 378 | I18: =IF(T_T1341112131415161718192021222324[[#This Row],[Total]]<0,T_T1341112131415161718192021222324[[#This Row],[Total]]*-1,0) -> 0
A19: 45747 | B19: Mantenimiento marzo/2025 | D19: 453 | G19: =SUM(D19:F19) -> 453 | H19: =H18+G19 -> 831 | I19: =IF(T_T1341112131415161718192021222324[[#This Row],[Total]]<0,T_T1341112131415161718192021222324[[#This Row],[Total]]*-1,0) -> 0
B20: Pago matenimiento marzo/2025 | G20: =SUM(D20:F20) -> 0 | H20: =H19+G20 -> 831 | I20: =IF(T_T1341112131415161718192021222324[[#This Row],[Total]]<0,T_T1341112131415161718192021222324[[#This Row],[Total]]*-1,0) -> 0
A21: 45777 | B21: Mantenimiento abril/2025 | D21: 453 | E21: 1 | G21: =SUM(D21:F21) -> 454 | H21: =H20+G21 -> 1285 | I21: =IF(T_T1341112131415161718192021222324[[#This Row],[Total]]<0,T_T1341112131415161718192021222324[[#This Row],[Total]]*-1,0) -> 0
B22: Pago mantenimiento abril/2025 | G22: =SUM(D22:F22) -> 0 | H22: =H21+G22 -> 1285 | I22: =IF(T_T1341112131415161718192021222324[[#This Row],[Total]]<0,T_T1341112131415161718192021222324[[#This Row],[Total]]*-1,0) -> 0
A23: 45807 | B23: Mantenimiento mayo/2025 | D23: 453 | E23: 0 | G23: =SUM(D23:F23) -> 453 | H23: =H22+G23 -> 1738 | I23: =IF(T_T1341112131415161718192021222324[[#This Row],[Total]]<0,T_T1341112131415161718192021222324[[#This Row],[Total]]*-1,0) -> 0
B24: Pago mantenimiento mayo/2025 | G24: =SUM(D24:F24) -> 0 | H24: =H23+G24 -> 1738 | I24: =IF(T_T1341112131415161718192021222324[[#This Row],[Total]]<0,T_T1341112131415161718192021222324[[#This Row],[Total]]*-1,0) -> 0
A25: 45838 | B25: Mantenimiento junio/2025 | G25: =SUM(D25:F25) -> 0 | H25: =H24+G25 -> 1738 | I25: =IF(T_T1341112131415161718192021222324[[#This Row],[Total]]<0,T_T1341112131415161718192021222324[[#This Row],[Total]]*-1,0) -> 0
B26: Pago mantenimiento junio/2025 | G26: =SUM(D26:F26) -> 0 | H26: =H25+G26 -> 1738 | I26: =IF(T_T1341112131415161718192021222324[[#This Row],[Total]]<0,T_T1341112131415161718192021222324[[#This Row],[Total]]*-1,0) -> 0
A27: 45868 | B27: Mantenimiento julio/2025 | G27: =SUM(D27:F27) -> 0 | H27: =H26+G27 -> 1738 | I27: =IF(T_T1341112131415161718192021222324[[#This Row],[Total]]<0,T_T1341112131415161718192021222324[[#This Row],[Total]]*-1,0) -> 0
B28: Pago mantenimient julio/2025 | G28: =SUM(D28:F28) -> 0 | H28: =H27+G28 -> 1738 | I28: =IF(T_T1341112131415161718192021222324[[#This Row],[Total]]<0,T_T1341112131415161718192021222324[[#This Row],[Total]]*-1,0) -> 0
A29: 45899 | B29: Mantenimiento agosto/2025 | G29: =SUM(D29:F29) -> 0 | H29: =H28+G29 -> 1738 | I29: =IF(T_T1341112131415161718192021222324[[#This Row],[Total]]<0,T_T1341112131415161718192021222324[[#This Row],[Total]]*-1,0) -> 0
B30: Pago mantenimiento agosto/2025 | G30: =SUM(D30:F30) -> 0 | H30: =H29+G30 -> 1738 | I30: =IF(T_T1341112131415161718192021222324[[#This Row],[Total]]<0,T_T1341112131415161718192021222324[[#This Row],[Total]]*-1,0) -> 0
A31: 45930 | B31: Mantenimiento septiembre/2025 | G31: =SUM(D31:F31) -> 0 | H31: =H30+G31 -> 1738 | I31: =IF(T_T1341112131415161718192021222324[[#This Row],[Total]]<0,T_T1341112131415161718192021222324[[#This Row],[Total]]*-1,0) -> 0
B32: Pago mantenimiento septiembre/2025 | G32: =SUM(D32:F32) -> 0 | H32: =H31+G32 -> 1738 | I32: =IF(T_T1341112131415161718192021222324[[#This Row],[Total]]<0,T_T1341112131415161718192021222324[[#This Row],[Total]]*-1,0) -> 0
A33: 45960 | B33: Mantenimiento octubre /2025 | G33: =SUM(D33:F33) -> 0 | H33: =H32+G33 -> 1738 | I33: =IF(T_T1341112131415161718192021222324[[#This Row],[Total]]<0,T_T1341112131415161718192021222324[[#This Row],[Total]]*-1,0) -> 0
B34: Pago mantenimiento octubre/2025 | G34: =SUM(D34:F34) -> 0 | H34: =H33+G34 -> 1738 | I34: =IF(T_T1341112131415161718192021222324[[#This Row],[Total]]<0,T_T1341112131415161718192021222324[[#This Row],[Total]]*-1,0) -> 0
A35: 45991 | B35: Mantenimiento noviembre/2025 | G35: =SUM(D35:F35) -> 0 | H35: =H34+G35 -> 1738 | I35: =IF(T_T1341112131415161718192021222324[[#This Row],[Total]]<0,T_T1341112131415161718192021222324[[#This Row],[Total]]*-1,0) -> 0
B36: Pago mantenimiento noviembre/2025 | G36: =SUM(D36:F36) -> 0 | H36: =H35+G36 -> 1738 | I36: =IF(T_T1341112131415161718192021222324[[#This Row],[Total]]<0,T_T1341112131415161718192021222324[[#This Row],[Total]]*-1,0) -> 0
A37: 46021 | B37: Mantenimiento diciembre/2025 | G37: =SUM(D37:F37) -> 0 | H37: =H36+G37 -> 1738 | I37: =IF(T_T1341112131415161718192021222324[[#This Row],[Total]]<0,T_T1341112131415161718192021222324[[#This Row],[Total]]*-1,0) -> 0
B38: Pago de Mantenimiento diciembre/2025 | G38: =SUM(D38:F38) -> 0 | H38: =H37+G38 -> 1738 | I38: =IF(T_T1341112131415161718192021222324[[#This Row],[Total]]<0,T_T1341112131415161718192021222324[[#This Row],[Total]]*-1,0) -> 0
G39: =SUM(D39:F40) -> 0 | H39: =H38+G39 -> 1738 | I39: =IF(T_T1341112131415161718192021222324[[#This Row],[Total]]<0,T_T1341112131415161718192021222324[[#This Row],[Total]]*-1,0) -> 0
G40: =SUM(D40:F40) -> 0 | H40: =H39+G40 -> 1738 | I40: =IF(T_T1341112131415161718192021222324[[#This Row],[Total]]<0,T_T1341112131415161718192021222324[[#This Row],[Total]]*-1,0) -> 0
I41: =IF(T_T1341112131415161718192021222324[[#This Row],[Total]]<0,T_T1341112131415161718192021222324[[#This Row],[Total]]*-1,0) -> 0

Sheet OF.4C
A2: Departamento : | B2: OF.4C
A3: Propietario :
A4: Inquilino : | B4: =LOOKUP(B2,#REF!,#REF!) -> #REF!
A5: Teléfono : | B5: =LOOKUP(B2,#REF!,#REF!) -> #REF!
A6: Celular : | B6: =LOOKUP(B2,#REF!,#REF!) -> #REF!
A7: Correo : | B7: =LOOKUP(B2,#REF!,#REF!) -> #REF! | H7: Resumen
B8: NILDA VDA. DE LLANOS
A9: Fecha | B9: Concepto | C9: Recibo | D9: Expensas | E9: Agua | F9: Multa | G9: Total | H9: Deuda | I9: Pagado | J9: Columna1 | K9: Columna2 | L9: Columna3
B10: DEUDA GESTION 2017-2020 | H10: 0 | I10: =IF(T_T134111213141516171819202122232425[[#This Row],[Total]]<0,T_T134111213141516171819202122232425[[#This Row],[Total]]*-1,0) -> 0
B11: DEUDA GESTION 2021 | H11: 0 | I11: =IF(T_T134111213141516171819202122232425[[#This Row],[Total]]<0,T_T134111213141516171819202122232425[[#This Row],[Total]]*-1,0) -> 0
B12: DEUDA GESTION 2022 | H12: 0 | I12: =IF(T_T134111213141516171819202122232425[[#This Row],[Total]]<0,T_T134111213141516171819202122232425[[#This Row],[Total]]*-1,0) -> 0
B13: DEUDA GESTION 2023 | H13: 0 | I13: =IF(T_T134111213141516171819202122232425[[#This Row],[Total]]<0,T_T134111213141516171819202122232425[[#This Row],[Total]]*-1,0) -> 0
B14: DEUDA GESTION 2024 | I14: =IF(T_T134111213141516171819202122232425[[#This Row],[Total]]<0,T_T134111213141516171819202122232425[[#This Row],[Total]]*-1,0) -> 0
A15: 46052 | B15: Mantenimiento enero/2026 | D15: 164 | E15: 10 | G15: =SUM(D15:F15) -> 174 | H15: =+H13+T_T134111213141516171819202122232425[[#This Row],[Total]] -> 174 | I15: =IF(T_T134111213141516171819202122232425[[#This Row],[Total]]<0,T_T134111213141516171819202122232425[[#This Row],[Total]]*-1,0) -> 0
B16: Pago mantenimiento enero/2026 | C16: 8768 | D16: -164 | E16: -10 | G16: =SUM(D16:F16) -> -174 | H16: =H15+G16 -> 0 | I16: =IF(T_T134111213141516171819202122232425[[#This Row],[Total]]<0,T_T134111213141516171819202122232425[[#This Row],[Total]]*-1,0) -> 174
A17: 46081 | B17: Mantenimiento febrero/2026 | D17: 164 | E17: 16 | G17: =SUM(D17:F17) -> 180 | H17: =H16+G17 -> 180 | I17: =IF(T_T134111213141516171819202122232425[[#This Row],[Total]]<0,T_T134111213141516171819202122232425[[#This Row],[Total]]*-1,0) -> 0
B18: Pago mantenimiento febrero/2026 | C18: 8768 | D18: -164 | E18: -16 | G18: =SUM(D18:F18) -> -180 | H18: =H17+G18 -> 0 | I18: =IF(T_T134111213141516171819202122232425[[#This Row],[Total]]<0,T_T134111213141516171819202122232425[[#This Row],[Total]]*-1,0) -> 180
A19: 45747 | B19: Mantenimiento marzo/2025 | D19: 197 | E19: 9 | G19: =SUM(D19:F19) -> 206 | H19: =H18+G19 -> 206 | I19: =IF(T_T134111213141516171819202122232425[[#This Row],[Total]]<0,T_T134111213141516171819202122232425[[#This Row],[Total]]*-1,0) -> 0
B20: Pago matenimiento marzo/2025 | C20: 8768 | D20: -197 | E20: -9 | G20: =SUM(D20:F20) -> -206 | H20: =H19+G20 -> 0 | I20: =IF(T_T134111213141516171819202122232425[[#This Row],[Total]]<0,T_T134111213141516171819202122232425[[#This Row],[Total]]*-1,0) -> 206
A21: 45777 | B21: Mantenimiento abril/2025 | D21: 197 | E21: 7 | G21: =SUM(D21:F21) -> 204 | H21: =H20+G21 -> 204 | I21: =IF(T_T134111213141516171819202122232425[[#This Row],[Total]]<0,T_T134111213141516171819202122232425[[#This Row],[Total]]*-1,0) -> 0
B22: Pago mantenimiento abril/2025 | G22: =SUM(D22:F22) -> 0 | H22: =H21+G22 -> 204 | I22: =IF(T_T134111213141516171819202122232425[[#This Row],[Total]]<0,T_T134111213141516171819202122232425[[#This Row],[Total]]*-1,0) -> 0
A23: 45807 | B23: Mantenimiento mayo/2025 | D23: 197 | E23: 8 | G23: =SUM(D23:F23) -> 205 | H23: =H22+G23 -> 409 | I23: =IF(T_T134111213141516171819202122232425[[#This Row],[Total]]<0,T_T134111213141516171819202122232425[[#This Row],[Total]]*-1,0) -> 0
B24: Pago mantenimiento mayo/2025 | G24: =SUM(D24:F24) -> 0 | H24: =H23+G24 -> 409 | I24: =IF(T_T134111213141516171819202122232425[[#This Row],[Total]]<0,T_T134111213141516171819202122232425[[#This Row],[Total]]*-1,0) -> 0
A25: 45838 | B25: Mantenimiento junio/2025 | G25: =SUM(D25:F25) -> 0 | H25: =H24+G25 -> 409 | I25: =IF(T_T134111213141516171819202122232425[[#This Row],[Total]]<0,T_T134111213141516171819202122232425[[#This Row],[Total]]*-1,0) -> 0
B26: Pago mantenimiento junio/2025 | G26: =SUM(D26:F26) -> 0 | H26: =H25+G26 -> 409 | I26: =IF(T_T134111213141516171819202122232425[[#This Row],[Total]]<0,T_T134111213141516171819202122232425[[#This Row],[Total]]*-1,0) -> 0
A27: 45868 | B27: Mantenimiento julio/2025 | G27: =SUM(D27:F27) -> 0 | H27: =H26+G27 -> 409 | I27: =IF(T_T134111213141516171819202122232425[[#This Row],[Total]]<0,T_T134111213141516171819202122232425[[#This Row],[Total]]*-1,0) -> 0 | N27: 76560000 yazmin quiroga
B28: Pago mantenimient julio/2025 | G28: =SUM(D28:F28) -> 0 | H28: =H27+G28 -> 409 | I28: =IF(T_T134111213141516171819202122232425[[#This Row],[Total]]<0,T_T134111213141516171819202122232425[[#This Row],[Total]]*-1,0) -> 0
A29: 45899 | B29: Mantenimiento agosto/2025 | G29: =SUM(D29:F29) -> 0 | H29: =H28+G29 -> 409 | I29: =IF(T_T134111213141516171819202122232425[[#This Row],[Total]]<0,T_T134111213141516171819202122232425[[#This Row],[Total]]*-1,0) -> 0
B30: Pago mantenimiento agosto/2025 | G30: =SUM(D30:F30) -> 0 | H30: =H29+G30 -> 409 | I30: =IF(T_T134111213141516171819202122232425[[#This Row],[Total]]<0,T_T134111213141516171819202122232425[[#This Row],[Total]]*-1,0) -> 0
A31: 45930 | B31: Mantenimiento septiembre/2025 | G31: =SUM(D31:F31) -> 0 | H31: =H30+G31 -> 409 | I31: =IF(T_T134111213141516171819202122232425[[#This Row],[Total]]<0,T_T134111213141516171819202122232425[[#This Row],[Total]]*-1,0) -> 0
B32: Pago mantenimiento septiembre/2025 | G32: =SUM(D32:F32) -> 0 | H32: =H31+G32 -> 409 | I32: =IF(T_T134111213141516171819202122232425[[#This Row],[Total]]<0,T_T134111213141516171819202122232425[[#This Row],[Total]]*-1,0) -> 0
A33: 45960 | B33: Mantenimiento octubre /2025 | G33: =SUM(D33:F33) -> 0 | H33: =H32+G33 -> 409 | I33: =IF(T_T134111213141516171819202122232425[[#This Row],[Total]]<0,T_T134111213141516171819202122232425[[#This Row],[Total]]*-1,0) -> 0
B34: Pago mantenimiento octubre/2025 | G34: =SUM(D34:F34) -> 0 | H34: =H33+G34 -> 409 | I34: =IF(T_T134111213141516171819202122232425[[#This Row],[Total]]<0,T_T134111213141516171819202122232425[[#This Row],[Total]]*-1,0) -> 0
A35: 45991 | B35: Mantenimiento noviembre/2025 | G35: =SUM(D35:F35) -> 0 | H35: =H34+G35 -> 409 | I35: =IF(T_T134111213141516171819202122232425[[#This Row],[Total]]<0,T_T134111213141516171819202122232425[[#This Row],[Total]]*-1,0) -> 0
B36: Pago mantenimiento noviembre/2025 | G36: =SUM(D36:F36) -> 0 | H36: =H35+G36 -> 409 | I36: =IF(T_T134111213141516171819202122232425[[#This Row],[Total]]<0,T_T134111213141516171819202122232425[[#This Row],[Total]]*-1,0) -> 0
A37: 46021 | B37: Mantenimiento diciembre/2025 | G37: =SUM(D37:F37) -> 0 | H37: =H36+G37 -> 409 | I37: =IF(T_T134111213141516171819202122232425[[#This Row],[Total]]<0,T_T134111213141516171819202122232425[[#This Row],[Total]]*-1,0) -> 0
B38: Pago de Mantenimiento diciembre/2025 | G38: =SUM(D38:F38) -> 0 | H38: =H37+G38 -> 409 | I38: =IF(T_T134111213141516171819202122232425[[#This Row],[Total]]<0,T_T134111213141516171819202122232425[[#This Row],[Total]]*-1,0) -> 0
G39: =SUM(D39:F39) -> 0 | H39: =H38+G39 -> 409 | I39: =IF(T_T134111213141516171819202122232425[[#This Row],[Total]]<0,T_T134111213141516171819202122232425[[#This Row],[Total]]*-1,0) -> 0
G40: =SUM(D40:F40) -> 0 | H40: =H39+G40 -> 409 | I40: =IF(T_T134111213141516171819202122232425[[#This Row],[Total]]<0,T_T134111213141516171819202122232425[[#This Row],[Total]]*-1,0) -> 0
G41: =SUM(D41:F47) -> 0 | H41: =H40+G41 -> 409 | I41: =IF(T_T134111213141516171819202122232425[[#This Row],[Total]]<0,T_T134111213141516171819202122232425[[#This Row],[Total]]*-1,0) -> 0
G42: =SUM(D42:F47) -> 0 | H42: =H41+G42 -> 409 | I42: =IF(T_T134111213141516171819202122232425[[#This Row],[Total]]<0,T_T134111213141516171819202122232425[[#This Row],[Total]]*-1,0) -> 0
A43: Departamento : | B43: OF.4C-PARQUEO 125-BAULERA 78
A44: Propietario :
A45: Inquilino : | B45: JUAN CARLOS BALLON
A46: Teléfono : | B46: =LOOKUP(B43,#REF!,#REF!) -> #REF!

Sheet OF.5A
A2: Departamento : | B2: OF.5A
A3: Propietario : | B3: ROXANA CHAVEZ
A4: Inquilino : | B4: =LOOKUP(B2,#REF!,#REF!) -> #REF!
A5: Teléfono : | B5: =LOOKUP(B2,#REF!,#REF!) -> #REF!
A6: Celular : | B6: =LOOKUP(B2,#REF!,#REF!) -> #REF!
A7: Correo : | B7: =LOOKUP(B2,#REF!,#REF!) -> #REF! | H7: Resumen
A9: Fecha | B9: Concepto | C9: Recibo | D9: Expensas | E9: Agua | F9: Multa | G9: Total | H9: Deuda | I9: Pagado | J9: Columna1 | K9: Columna2 | L9: Columna3
B10: DEUDA GESTION 2017-2020 | H10: 0 | I10: =IF(T_T134111213141516171819202122232425262728[[#This Row],[Total]]<0,T_T134111213141516171819202122232425262728[[#This Row],[Total]]*-1,0) -> 0
B11: DEUDA GESTION 2021 | H11: 0 | I11: =IF(T_T134111213141516171819202122232425262728[[#This Row],[Total]]<0,T_T134111213141516171819202122232425262728[[#This Row],[Total]]*-1,0) -> 0
B12: DEUDA GESTION 2022 | H12: 0 | I12: =IF(T_T134111213141516171819202122232425262728[[#This Row],[Total]]<0,T_T134111213141516171819202122232425262728[[#This Row],[Total]]*-1,0) -> 0
B13: DEUDA GESTION 2023 | H13: 0 | I13: =IF(T_T134111213141516171819202122232425262728[[#This Row],[Total]]<0,T_T134111213141516171819202122232425262728[[#This Row],[Total]]*-1,0) -> 0
B14: DEUDA GESTION 2024 | I14: =IF(T_T134111213141516171819202122232425262728[[#This Row],[Total]]<0,T_T134111213141516171819202122232425262728[[#This Row],[Total]]*-1,0) -> 0
A15: 45687 | B15: Mantenimiento enero/2025 | D15: 222 | E15: 18 | G15: =SUM(D15:F15) -> 240 | H15: =+H13+T_T134111213141516171819202122232425262728[[#This Row],[Total]] -> 240 | I15: =IF(T_T134111213141516171819202122232425262728[[#This Row],[Total]]<0,T_T134111213141516171819202122232425262728[[#This Row],[Total]]*-1,0) -> 0
B16: Pago mantenimiento enero/2025 | C16: 8690 | D16: -210 | E16: -18 | G16: =SUM(D16:F16) -> -228 | H16: =H15+G16 -> 12 | I16: =IF(T_T134111213141516171819202122232425262728[[#This Row],[Total]]<0,T_T134111213141516171819202122232425262728[[#This Row],[Total]]*-1,0) -> 228
A17: 46081 | B17: Mantenimiento febrero/2026 | D17: 222 | E17: 22 | G17: =SUM(D17:F17) -> 244 | H17: =H16+G17 -> 256 | I17: =IF(T_T134111213141516171819202122232425262728[[#This Row],[Total]]<0,T_T134111213141516171819202122232425262728[[#This Row],[Total]]*-1,0) -> 0
B18: Pago mantenimiento febrero/2026 | C18: 8746 | D18: -210 | E18: -22 | G18: =SUM(D18:F18) -> -232 | H18: =H17+G18 -> 24 | I18: =IF(T_T134111213141516171819202122232425262728[[#This Row],[Total]]<0,T_T134111213141516171819202122232425262728[[#This Row],[Total]]*-1,0) -> 232 | N18: ALVARO ZAPATA
A19: 45747 | B19: Mantenimiento marzo/2025 | D19: =250+14 -> 264 | E19: 15 | G19: =SUM(D19:F19) -> 279 | H19: =H18+G19 -> 303 | I19: =IF(T_T134111213141516171819202122232425262728[[#This Row],[Total]]<0,T_T134111213141516171819202122232425262728[[#This Row],[Total]]*-1,0) -> 0
B20: Pago matenimiento marzo/2025 | C20: 8862 | D20: -250 | E20: -15 | G20: =SUM(D20:F20) -> -265 | H20: =H19+G20 -> 38 | I20: =IF(T_T134111213141516171819202122232425262728[[#This Row],[Total]]<0,T_T134111213141516171819202122232425262728[[#This Row],[Total]]*-1,0) -> 265
A21: 45777 | B21: Mantenimiento abril/2025 | D21: 264 | E21: 17 | G21: =SUM(D21:F21) -> 281 | H21: =H20+G21 -> 319 | I21: =IF(T_T134111213141516171819202122232425262728[[#This Row],[Total]]<0,T_T134111213141516171819202122232425262728[[#This Row],[Total]]*-1,0) -> 0
B22: Pago mantenimiento abril/2025 | G22: =SUM(D22:F22) -> 0 | H22: =H21+G22 -> 319 | I22: =IF(T_T134111213141516171819202122232425262728[[#This Row],[Total]]<0,T_T134111213141516171819202122232425262728[[#This Row],[Total]]*-1,0) -> 0
A23: 45807 | B23: Mantenimiento mayo/2025 | D23: 264 | E23: 25 | G23: =SUM(D23:F23) -> 289 | H23: =H22+G23 -> 608 | I23: =IF(T_T134111213141516171819202122232425262728[[#This Row],[Total]]<0,T_T134111213141516171819202122232425262728[[#This Row],[Total]]*-1,0) -> 0
B24: Pago mantenimiento mayo/2025 | G24: =SUM(D24:F24) -> 0 | H24: =H23+G24 -> 608 | I24: =IF(T_T134111213141516171819202122232425262728[[#This Row],[Total]]<0,T_T134111213141516171819202122232425262728[[#This Row],[Total]]*-1,0) -> 0
A25: 45838 | B25: Mantenimiento junio/2025 | G25: =SUM(D25:F25) -> 0 | H25: =H24+G25 -> 608 | I25: =IF(T_T134111213141516171819202122232425262728[[#This Row],[Total]]<0,T_T134111213141516171819202122232425262728[[#This Row],[Total]]*-1,0) -> 0
B26: Pago mantenimiento junio/2025 | G26: =SUM(D26:F26) -> 0 | H26: =H25+G26 -> 608 | I26: =IF(T_T134111213141516171819202122232425262728[[#This Row],[Total]]<0,T_T134111213141516171819202122232425262728[[#This Row],[Total]]*-1,0) -> 0
A27: 45868 | B27: Mantenimiento julio/2025 | G27: =SUM(D27:F27) -> 0 | H27: =H26+G27 -> 608 | I27: =IF(T_T134111213141516171819202122232425262728[[#This Row],[Total]]<0,T_T134111213141516171819202122232425262728[[#This Row],[Total]]*-1,0) -> 0
B28: Pago mantenimient julio/2025 | G28: =SUM(D28:F28) -> 0 | H28: =H27+G28 -> 608 | I28: =IF(T_T134111213141516171819202122232425262728[[#This Row],[Total]]<0,T_T134111213141516171819202122232425262728[[#This Row],[Total]]*-1,0) -> 0
A29: 45899 | B29: Mantenimiento agosto/2025 | G29: =SUM(D29:F29) -> 0 | H29: =H28+G29 -> 608 | I29: =IF(T_T134111213141516171819202122232425262728[[#This Row],[Total]]<0,T_T134111213141516171819202122232425262728[[#This Row],[Total]]*-1,0) -> 0
B30: Pago mantenimiento agosto/2025 | G30: =SUM(D30:F30) -> 0 | H30: =H29+G30 -> 608 | I30: =IF(T_T134111213141516171819202122232425262728[[#This Row],[Total]]<0,T_T134111213141516171819202122232425262728[[#This Row],[Total]]*-1,0) -> 0
A31: 45930 | B31: Mantenimiento septiembre/2025 | G31: =SUM(D31:F31) -> 0 | H31: =H30+G31 -> 608 | I31: =IF(T_T134111213141516171819202122232425262728[[#This Row],[Total]]<0,T_T134111213141516171819202122232425262728[[#This Row],[Total]]*-1,0) -> 0
B32: Pago mantenimiento septiembre/2025 | G32: =SUM(D32:F32) -> 0 | H32: =H31+G32 -> 608 | I32: =IF(T_T134111213141516171819202122232425262728[[#This Row],[Total]]<0,T_T134111213141516171819202122232425262728[[#This Row],[Total]]*-1,0) -> 0
A33: 45960 | B33: Mantenimiento octubre /2025 | G33: =SUM(D33:F33) -> 0 | H33: =H32+G33 -> 608 | I33: =IF(T_T134111213141516171819202122232425262728[[#This Row],[Total]]<0,T_T134111213141516171819202122232425262728[[#This Row],[Total]]*-1,0) -> 0
B34: Pago mantenimiento octubre/2025 | G34: =SUM(D34:F34) -> 0 | H34: =H33+G34 -> 608 | I34: =IF(T_T134111213141516171819202122232425262728[[#This Row],[Total]]<0,T_T134111213141516171819202122232425262728[[#This Row],[Total]]*-1,0) -> 0
A35: 45991 | B35: Mantenimiento noviembre/2025 | G35: =SUM(D35:F35) -> 0 | H35: =H34+G35 -> 608 | I35: =IF(T_T134111213141516171819202122232425262728[[#This Row],[Total]]<0,T_T134111213141516171819202122232425262728[[#This Row],[Total]]*-1,0) -> 0
B36: Pago mantenimiento noviembre/2025 | G36: =SUM(D36:F36) -> 0 | H36: =H35+G36 -> 608 | I36: =IF(T_T134111213141516171819202122232425262728[[#This Row],[Total]]<0,T_T134111213141516171819202122232425262728[[#This Row],[Total]]*-1,0) -> 0
A37: 46021 | B37: Mantenimiento diciembre/2025 | G37: =SUM(D37:F37) -> 0 | H37: =H36+G37 -> 608 | I37: =IF(T_T134111213141516171819202122232425262728[[#This Row],[Total]]<0,T_T134111213141516171819202122232425262728[[#This Row],[Total]]*-1,0) -> 0
B38: Pago de Mantenimiento diciembre/2025 | G38: =SUM(D38:F38) -> 0 | H38: =H37+G38 -> 608 | I38: =IF(T_T134111213141516171819202122232425262728[[#This Row],[Total]]<0,T_T134111213141516171819202122232425262728[[#This Row],[Total]]*-1,0) -> 0
G39: =SUM(D39:F40) -> 0 | H39: =H38+G39 -> 608 | I39: =IF(T_T134111213141516171819202122232425262728[[#This Row],[Total]]<0,T_T134111213141516171819202122232425262728[[#This Row],[Total]]*-1,0) -> 0
G40: =SUM(D40:F40) -> 0 | H40: =H39+G40 -> 608 | I40: =IF(T_T134111213141516171819202122232425262728[[#This Row],[Total]]<0,T_T134111213141516171819202122232425262728[[#This Row],[Total]]*-1,0) -> 0
I41: =IF(T_T134111213141516171819202122232425262728[[#This Row],[Total]]<0,T_T134111213141516171819202122232425262728[[#This Row],[Total]]*-1,0) -> 0

Sheet OF.5B
A2: Departamento : | B2: OF.5B
A3: Propietario : | B3: ROXANA CHAVEZ
A4: Inquilino :
A5: Teléfono : | B5: =LOOKUP(B2,#REF!,#REF!) -> #REF!
A6: Celular : | B6: =LOOKUP(B2,#REF!,#REF!) -> #REF!
A7: Correo : | B7: =LOOKUP(B2,#REF!,#REF!) -> #REF! | H7: Resumen
A9: Fecha | B9: Concepto | C9: Recibo | D9: Expensas | E9: Agua | F9: Multa | G9: Total | H9: Deuda | I9: Pagado
B10: DEUDA GESTION 2017-2020 | H10: 0 | I10: =IF(T_T13411121314151617181920212223242526272829[[#This Row],[Total]]<0,T_T13411121314151617181920212223242526272829[[#This Row],[Total]]*-1,0) -> 0
B11: DEUDA GESTION 2021 | H11: 0 | I11: =IF(T_T13411121314151617181920212223242526272829[[#This Row],[Total]]<0,T_T13411121314151617181920212223242526272829[[#This Row],[Total]]*-1,0) -> 0
B12: DEUDA GESTION 2022 | H12: 0 | I12: =IF(T_T13411121314151617181920212223242526272829[[#This Row],[Total]]<0,T_T13411121314151617181920212223242526272829[[#This Row],[Total]]*-1,0) -> 0
B13: DEUDA GESTION 2023 | H13: 0 | I13: =IF(T_T13411121314151617181920212223242526272829[[#This Row],[Total]]<0,T_T13411121314151617181920212223242526272829[[#This Row],[Total]]*-1,0) -> 0
B14: DEUDA GESTION 2024 | I14: =IF(T_T13411121314151617181920212223242526272829[[#This Row],[Total]]<0,T_T13411121314151617181920212223242526272829[[#This Row],[Total]]*-1,0) -> 0
A15: 30/1/202 | B15: Mantenimiento enero/2026 | D15: 157 | E15: 3 | G15: =SUM(D15:F15) -> 160 | H15: =+H13+T_T13411121314151617181920212223242526272829[[#This Row],[Total]] -> 160 | I15: =IF(T_T13411121314151617181920212223242526272829[[#This Row],[Total]]<0,T_T13411121314151617181920212223242526272829[[#This Row],[Total]]*-1,0) -> 0
B16: Pago mantenimiento enero/2026 | C16: 8597 | D16: -157 | E16: -3 | G16: =SUM(D16:F16) -> -160 | H16: =H15+G16 -> 0 | I16: =IF(T_T13411121314151617181920212223242526272829[[#This Row],[Total]]<0,T_T13411121314151617181920212223242526272829[[#This Row],[Total]]*-1,0) -> 160
A17: 45715 | B17: Mantenimiento febrero/2025 | D17: 157 | E17: 4 | G17: =SUM(D17:F17) -> 161 | H17: =H16+G17 -> 161 | I17: =IF(T_T13411121314151617181920212223242526272829[[#This Row],[Total]]<0,T_T13411121314151617181920212223242526272829[[#This Row],[Total]]*-1,0) -> 0
B18: Pago mantenimiento febrero/2025 | C18: 8663 | D18: -157 | E18: -4 | G18: =SUM(D18:F18) -> -161 | H18: =H17+G18 -> 0 | I18: =IF(T_T13411121314151617181920212223242526272829[[#This Row],[Total]]<0,T_T13411121314151617181920212223242526272829[[#This Row],[Total]]*-1,0) -> 161
A19: 45747 | B19: Mantenimiento marzo/2025 | D19: 189 | E19: 1 | G19: =SUM(D19:F19) -> 190 | H19: =H18+G19 -> 190 | I19: =IF(T_T13411121314151617181920212223242526272829[[#This Row],[Total]]<0,T_T13411121314151617181920212223242526272829[[#This Row],[Total]]*-1,0) -> 0
B20: Pago matenimiento marzo/2025 | C20: 8788 | D20: -189 | E20: -1 | G20: =SUM(D20:F20) -> -190 | H20: =H19+G20 -> 0 | I20: =IF(T_T13411121314151617181920212223242526272829[[#This Row],[Total]]<0,T_T13411121314151617181920212223242526272829[[#This Row],[Total]]*-1,0) -> 190
A21: 45777 | B21: Mantenimiento abril/2025 | D21: 189 | E21: 3 | G21: =SUM(D21:F21) -> 192 | H21: =H20+G21 -> 192 | I21: =IF(T_T13411121314151617181920212223242526272829[[#This Row],[Total]]<0,T_T13411121314151617181920212223242526272829[[#This Row],[Total]]*-1,0) -> 0
B22: Pago mantenimiento abril/2025 | C22: 8903 | D22: -189 | E22: -3 | G22: =SUM(D22:F22) -> -192 | H22: =H21+G22 -> 0 | I22: =IF(T_T13411121314151617181920212223242526272829[[#This Row],[Total]]<0,T_T13411121314151617181920212223242526272829[[#This Row],[Total]]*-1,0) -> 192
A23: 45807 | B23: Mantenimiento mayo/2025 | D23: 189 | E23: 2 | G23: =SUM(D23:F23) -> 191 | H23: =H22+G23 -> 191 | I23: =IF(T_T13411121314151617181920212223242526272829[[#This Row],[Total]]<0,T_T13411121314151617181920212223242526272829[[#This Row],[Total]]*-1,0) -> 0
B24: Pago mantenimiento mayo/2025 | G24: =SUM(D24:F24) -> 0 | H24: =H23+G24 -> 191 | I24: =IF(T_T13411121314151617181920212223242526272829[[#This Row],[Total]]<0,T_T13411121314151617181920212223242526272829[[#This Row],[Total]]*-1,0) -> 0 | L24: ROXANA CHAVEZ
A25: 45838 | B25: Mantenimiento junio/2025 | G25: =SUM(D25:F25) -> 0 | H25: =H24+G25 -> 191 | I25: =IF(T_T13411121314151617181920212223242526272829[[#This Row],[Total]]<0,T_T13411121314151617181920212223242526272829[[#This Row],[Total]]*-1,0) -> 0
B26: Pago mantenimiento junio/2025 | G26: =SUM(D26:F26) -> 0 | H26: =H25+G26 -> 191 | I26: =IF(T_T13411121314151617181920212223242526272829[[#This Row],[Total]]<0,T_T13411121314151617181920212223242526272829[[#This Row],[Total]]*-1,0) -> 0
A27: 45868 | B27: Mantenimiento julio/2025 | G27: =SUM(D27:F27) -> 0 | H27: =H26+G27 -> 191 | I27: =IF(T_T13411121314151617181920212223242526272829[[#This Row],[Total]]<0,T_T13411121314151617181920212223242526272829[[#This Row],[Total]]*-1,0) -> 0
B28: Pago mantenimient julio/2025 | G28: =SUM(D28:F28) -> 0 | H28: =H27+G28 -> 191 | I28: =IF(T_T13411121314151617181920212223242526272829[[#This Row],[Total]]<0,T_T13411121314151617181920212223242526272829[[#This Row],[Total]]*-1,0) -> 0
A29: 45899 | B29: Mantenimiento agosto/2025 | G29: =SUM(D29:F29) -> 0 | H29: =H28+G29 -> 191 | I29: =IF(T_T13411121314151617181920212223242526272829[[#This Row],[Total]]<0,T_T13411121314151617181920212223242526272829[[#This Row],[Total]]*-1,0) -> 0
B30: Pago mantenimiento agosto/2025 | G30: =SUM(D30:F30) -> 0 | H30: =H29+G30 -> 191 | I30: =IF(T_T13411121314151617181920212223242526272829[[#This Row],[Total]]<0,T_T13411121314151617181920212223242526272829[[#This Row],[Total]]*-1,0) -> 0
A31: 45930 | B31: Mantenimiento septiembre/2025 | G31: =SUM(D31:F31) -> 0 | H31: =H30+G31 -> 191 | I31: =IF(T_T13411121314151617181920212223242526272829[[#This Row],[Total]]<0,T_T13411121314151617181920212223242526272829[[#This Row],[Total]]*-1,0) -> 0
B32: Pago mantenimiento septiembre/2025 | G32: =SUM(D32:F32) -> 0 | H32: =H31+G32 -> 191 | I32: =IF(T_T13411121314151617181920212223242526272829[[#This Row],[Total]]<0,T_T13411121314151617181920212223242526272829[[#This Row],[Total]]*-1,0) -> 0
A33: 45960 | B33: Mantenimiento octubre /2025 | G33: =SUM(D33:F33) -> 0 | H33: =H32+G33 -> 191 | I33: =IF(T_T13411121314151617181920212223242526272829[[#This Row],[Total]]<0,T_T13411121314151617181920212223242526272829[[#This Row],[Total]]*-1,0) -> 0
B34: Pago mantenimiento octubre/2025 | G34: =SUM(D34:F34) -> 0 | H34: =H33+G34 -> 191 | I34: =IF(T_T13411121314151617181920212223242526272829[[#This Row],[Total]]<0,T_T13411121314151617181920212223242526272829[[#This Row],[Total]]*-1,0) -> 0
A35: 45991 | B35: Mantenimiento noviembre/2025 | G35: =SUM(D35:F35) -> 0 | H35: =H34+G35 -> 191 | I35: =IF(T_T13411121314151617181920212223242526272829[[#This Row],[Total]]<0,T_T13411121314151617181920212223242526272829[[#This Row],[Total]]*-1,0) -> 0
B36: Pago mantenimiento noviembre/2025 | G36: =SUM(D36:F36) -> 0 | H36: =H35+G36 -> 191 | I36: =IF(T_T13411121314151617181920212223242526272829[[#This Row],[Total]]<0,T_T13411121314151617181920212223242526272829[[#This Row],[Total]]*-1,0) -> 0
A37: 46021 | B37: Mantenimiento diciembre/2025 | G37: =SUM(D37:F37) -> 0 | H37: =H36+G37 -> 191 | I37: =IF(T_T13411121314151617181920212223242526272829[[#This Row],[Total]]<0,T_T13411121314151617181920212223242526272829[[#This Row],[Total]]*-1,0) -> 0
B38: Pago de Mantenimiento diciembre/2025 | G38: =SUM(D38:F38) -> 0 | H38: =H37+G38 -> 191 | I38: =IF(T_T13411121314151617181920212223242526272829[[#This Row],[Total]]<0,T_T13411121314151617181920212223242526272829[[#This Row],[Total]]*-1,0) -> 0
G39: =SUM(D39:F39) -> 0 | H39: =H38+G39 -> 191 | I39: =IF(T_T13411121314151617181920212223242526272829[[#This Row],[Total]]<0,T_T13411121314151617181920212223242526272829[[#This Row],[Total]]*-1,0) -> 0
I40: =IF(T_T13411121314151617181920212223242526272829[[#This Row],[Total]]<0,T_T13411121314151617181920212223242526272829[[#This Row],[Total]]*-1,0) -> 0
I41: =IF(T_T13411121314151617181920212223242526272829[[#This Row],[Total]]<0,T_T13411121314151617181920212223242526272829[[#This Row],[Total]]*-1,0) -> 0

Sheet OF.5C
A2: OFICINA | B2: OF.5C
A3: Propietario : | B3: ROXANA CHAVEZ
A4: Inquilino : | B4: =LOOKUP(B2,#REF!,#REF!) -> #REF!
A5: Teléfono : | B5: =LOOKUP(B2,#REF!,#REF!) -> #REF!
A6: Celular : | B6: =LOOKUP(B2,#REF!,#REF!) -> #REF!
A7: Correo : | B7: =LOOKUP(B2,#REF!,#REF!) -> #REF! | H7: Resumen
A9: Fecha | B9: Concepto | C9: Recibo | D9: Expensas | E9: Agua | F9: Multa | G9: Total | H9: Deuda | I9: Pagado | J9: Columna1 | N9: RECIBO | O9: FECHA | P9: DETALLE | Q9: IMPORTE | R9: RECIBIDO
B10: DEUDA GESTION 2017-2020 | H10: 0 | I10: =IF(T_T1341112131415161718192021222324252627282930[[#This Row],[Total]]<0,T_T1341112131415161718192021222324252627282930[[#This Row],[Total]]*-1,0) -> 0
B11: DEUDA GESTION 2021 | H11: 0 | I11: =IF(T_T1341112131415161718192021222324252627282930[[#This Row],[Total]]<0,T_T1341112131415161718192021222324252627282930[[#This Row],[Total]]*-1,0) -> 0
B12: DEUDA GESTION 2022 | H12: 0 | I12: =IF(T_T1341112131415161718192021222324252627282930[[#This Row],[Total]]<0,T_T1341112131415161718192021222324252627282930[[#This Row],[Total]]*-1,0) -> 0
B13: DEUDA GESTION 2023 | H13: 0 | I13: =IF(T_T1341112131415161718192021222324252627282930[[#This Row],[Total]]<0,T_T1341112131415161718192021222324252627282930[[#This Row],[Total]]*-1,0) -> 0
B14: DEUDA GESTION 2024 | I14: =IF(T_T1341112131415161718192021222324252627282930[[#This Row],[Total]]<0,T_T1341112131415161718192021222324252627282930[[#This Row],[Total]]*-1,0) -> 0
A15: 45687 | B15: Mantenimiento enero/2025 | D15: 230 | E15: 4 | G15: =SUM(D15:F15) -> 234 | H15: =+H13+T_T1341112131415161718192021222324252627282930[[#This Row],[Total]] -> 234 | I15: =IF(T_T1341112131415161718192021222324252627282930[[#This Row],[Total]]<0,T_T1341112131415161718192021222324252627282930[[#This Row],[Total]]*-1,0) -> 0
B16: Pago mantenimiento enero/2025 | C16: 8678 | D16: -230 | E16: -4 | G16: =SUM(D16:F16) -> -234 | H16: =+H15+T_T1341112131415161718192021222324252627282930[[#This Row],[Total]] -> 0 | I16: =IF(T_T1341112131415161718192021222324252627282930[[#This Row],[Total]]<0,T_T1341112131415161718192021222324252627282930[[#This Row],[Total]]*-1,0) -> 234
A17: 46081 | B17: Mantenimiento febrero/2026 | D17: 230 | E17: 5 | G17: =SUM(D17:F17) -> 235 | H17: =+H16+T_T1341112131415161718192021222324252627282930[[#This Row],[Total]] -> 235 | I17: =IF(T_T1341112131415161718192021222324252627282930[[#This Row],[Total]]<0,T_T1341112131415161718192021222324252627282930[[#This Row],[Total]]*-1,0) -> 0
B18: Pago mantenimiento febrero/2026 | C18: 8843 | D18: -230 | E18: -5 | G18: =SUM(D18:F18) -> -235 | H18: =+H17+T_T1341112131415161718192021222324252627282930[[#This Row],[Total]] -> 0 | I18: =IF(T_T1341112131415161718192021222324252627282930[[#This Row],[Total]]<0,T_T1341112131415161718192021222324252627282930[[#This Row],[Total]]*-1,0) -> 235
A19: 45747 | B19: Mantenimiento marzo/2025 | D19: 273 | E19: 2 | G19: =SUM(D19:F19) -> 275 | H19: =+H18+T_T1341112131415161718192021222324252627282930[[#This Row],[Total]] -> 275 | I19: =IF(T_T1341112131415161718192021222324252627282930[[#This Row],[Total]]<0,T_T1341112131415161718192021222324252627282930[[#This Row],[Total]]*-1,0) -> 0
B20: Pago matenimiento marzo/2025 | G20: =SUM(D20:F20) -> 0 | H20: =+H19+T_T1341112131415161718192021222324252627282930[[#This Row],[Total]] -> 275 | I20: =IF(T_T1341112131415161718192021222324252627282930[[#This Row],[Total]]<0,T_T1341112131415161718192021222324252627282930[[#This Row],[Total]]*-1,0) -> 0 | L20: LILIAN TEJERINA
A21: 45777 | B21: Mantenimiento abril/2025 | D21: 273 | E21: 6 | G21: =SUM(D21:F21) -> 279 | H21: =+H20+T_T1341112131415161718192021222324252627282930[[#This Row],[Total]] -> 554 | I21: =IF(T_T1341112131415161718192021222324252627282930[[#This Row],[Total]]<0,T_T1341112131415161718192021222324252627282930[[#This Row],[Total]]*-1,0) -> 0
B22: Pago mantenimiento abril/2025 | G22: =SUM(D22:F22) -> 0 | H22: =+H21+T_T1341112131415161718192021222324252627282930[[#This Row],[Total]] -> 554 | I22: =IF(T_T1341112131415161718192021222324252627282930[[#This Row],[Total]]<0,T_T1341112131415161718192021222324252627282930[[#This Row],[Total]]*-1,0) -> 0
A23: 45807 | B23: Mantenimiento mayo/2025 | D23: 273 | E23: 3 | G23: =SUM(D23:F23) -> 276 | H23: =+H22+T_T1341112131415161718192021222324252627282930[[#This Row],[Total]] -> 830 | I23: =IF(T_T1341112131415161718192021222324252627282930[[#This Row],[Total]]<0,T_T1341112131415161718192021222324252627282930[[#This Row],[Total]]*-1,0) -> 0
B24: Pago mantenimiento mayo/2025 | G24: =SUM(D24:F24) -> 0 | H24: =+H23+T_T1341112131415161718192021222324252627282930[[#This Row],[Total]] -> 830 | I24: =IF(T_T1341112131415161718192021222324252627282930[[#This Row],[Total]]<0,T_T1341112131415161718192021222324252627282930[[#This Row],[Total]]*-1,0) -> 0
A25: 45838 | B25: Mantenimiento junio/2025 | G25: =SUM(D25:F25) -> 0 | H25: =+H24+T_T1341112131415161718192021222324252627282930[[#This Row],[Total]] -> 830 | I25: =IF(T_T1341112131415161718192021222324252627282930[[#This Row],[Total]]<0,T_T1341112131415161718192021222324252627282930[[#This Row],[Total]]*-1,0) -> 0
B26: Pago mantenimiento junio/2025 | G26: =SUM(D26:F26) -> 0 | H26: =+H25+T_T1341112131415161718192021222324252627282930[[#This Row],[Total]] -> 830 | I26: =IF(T_T1341112131415161718192021222324252627282930[[#This Row],[Total]]<0,T_T1341112131415161718192021222324252627282930[[#This Row],[Total]]*-1,0) -> 0
A27: 45868 | B27: Mantenimiento julio/2025 | G27: =SUM(D27:F27) -> 0 | H27: =H26+G27 -> 830 | I27: =IF(T_T1341112131415161718192021222324252627282930[[#This Row],[Total]]<0,T_T1341112131415161718192021222324252627282930[[#This Row],[Total]]*-1,0) -> 0
B28: Pago mantenimient julio/2025 | G28: =SUM(D28:F28) -> 0 | H28: =H27+G28 -> 830 | I28: =IF(T_T1341112131415161718192021222324252627282930[[#This Row],[Total]]<0,T_T1341112131415161718192021222324252627282930[[#This Row],[Total]]*-1,0) -> 0
A29: 45899 | B29: Mantenimiento agosto/2025 | G29: =SUM(D29:F29) -> 0 | H29: =H28+G29 -> 830 | I29: =IF(T_T1341112131415161718192021222324252627282930[[#This Row],[Total]]<0,T_T1341112131415161718192021222324252627282930[[#This Row],[Total]]*-1,0) -> 0
B30: Pago mantenimiento agosto/2025 | G30: =SUM(D30:F30) -> 0 | H30: =H29+G30 -> 830 | I30: =IF(T_T1341112131415161718192021222324252627282930[[#This Row],[Total]]<0,T_T1341112131415161718192021222324252627282930[[#This Row],[Total]]*-1,0) -> 0
A31: 45930 | B31: Mantenimiento septiembre/2025 | G31: =SUM(D31:F31) -> 0 | H31: =H30+G31 -> 830 | I31: =IF(T_T1341112131415161718192021222324252627282930[[#This Row],[Total]]<0,T_T1341112131415161718192021222324252627282930[[#This Row],[Total]]*-1,0) -> 0
B32: Pago mantenimiento septiembre/2025 | G32: =SUM(D32:F32) -> 0 | H32: =H31+G32 -> 830 | I32: =IF(T_T1341112131415161718192021222324252627282930[[#This Row],[Total]]<0,T_T1341112131415161718192021222324252627282930[[#This Row],[Total]]*-1,0) -> 0
A33: 45960 | B33: Mantenimiento octubre /2025 | G33: =SUM(D33:F33) -> 0 | H33: =H32+G33 -> 830 | I33: =IF(T_T1341112131415161718192021222324252627282930[[#This Row],[Total]]<0,T_T1341112131415161718192021222324252627282930[[#This Row],[Total]]*-1,0) -> 0
B34: Pago mantenimiento octubre/2025 | G34: =SUM(D34:F34) -> 0 | H34: =H33+G34 -> 830 | I34: =IF(T_T1341112131415161718192021222324252627282930[[#This Row],[Total]]<0,T_T1341112131415161718192021222324252627282930[[#This Row],[Total]]*-1,0) -> 0
A35: 45991 | B35: Mantenimiento noviembre/2025 | G35: =SUM(D35:F35) -> 0 | H35: =H34+G35 -> 830 | I35: =IF(T_T1341112131415161718192021222324252627282930[[#This Row],[Total]]<0,T_T1341112131415161718192021222324252627282930[[#This Row],[Total]]*-1,0) -> 0
B36: Pago mantenimiento noviembre/2025 | G36: =SUM(D36:F36) -> 0 | H36: =H35+G36 -> 830 | I36: =IF(T_T1341112131415161718192021222324252627282930[[#This Row],[Total]]<0,T_T1341112131415161718192021222324252627282930[[#This Row],[Total]]*-1,0) -> 0
A37: 46021 | B37: Mantenimiento diciembre/2025 | G37: =SUM(D37:F37) -> 0 | H37: =H36+G37 -> 830 | I37: =IF(T_T1341112131415161718192021222324252627282930[[#This Row],[Total]]<0,T_T1341112131415161718192021222324252627282930[[#This Row],[Total]]*-1,0) -> 0
B38: Pago de Mantenimiento diciembre/2025 | G38: =SUM(D38:F38) -> 0 | H38: =H37+G38 -> 830 | I38: =IF(T_T1341112131415161718192021222324252627282930[[#This Row],[Total]]<0,T_T1341112131415161718192021222324252627282930[[#This Row],[Total]]*-1,0) -> 0
G39: =SUM(D39:F39) -> 0 | H39: =H38+G39 -> 830 | I39: =IF(T_T1341112131415161718192021222324252627282930[[#This Row],[Total]]<0,T_T1341112131415161718192021222324252627282930[[#This Row],[Total]]*-1,0) -> 0
G40: =SUM(D40:F40) -> 0 | H40: =H39+G40 -> 830 | I40: =IF(T_T1341112131415161718192021222324252627282930[[#This Row],[Total]]<0,T_T1341112131415161718192021222324252627282930[[#This Row],[Total]]*-1,0) -> 0
G41: =SUM(D41:F41) -> 0 | H41: =H40+G41 -> 830 | I41: =IF(T_T1341112131415161718192021222324252627282930[[#This Row],[Total]]<0,T_T1341112131415161718192021222324252627282930[[#This Row],[Total]]*-1,0) -> 0

Sheet OF.5D
A2: Departamento : | B2: OF.5D
A3: Propietario : | B3: ERMES ROMERO
A4: Inquilino : | B4: =LOOKUP(B2,#REF!,#REF!) -> #REF!
A5: Teléfono : | B5: =LOOKUP(B2,#REF!,#REF!) -> #REF!
A6: Celular : | B6: =LOOKUP(B2,#REF!,#REF!) -> #REF!
A7: Correo : | B7: =LOOKUP(B2,#REF!,#REF!) -> #REF! | H7: Resumen
A9: Fecha | B9: Concepto | C9: Recibo | D9: Expensas | E9: Agua | F9: Multa | G9: Total | H9: Deuda | I9: Pagado | J9: Columna1
B10: DEUDA GESTION 2017-2020 | H10: 0
B11: DEUDA GESTION 2021 | H11: 0 | I11: =IF(T_T134111213141516171819202122232425262728293031[[#This Row],[Total]]<0,T_T134111213141516171819202122232425262728293031[[#This Row],[Total]]*-1,0) -> 0
B12: DEUDA GESTION 2022 | H12: 0 | I12: =IF(T_T134111213141516171819202122232425262728293031[[#This Row],[Total]]<0,T_T134111213141516171819202122232425262728293031[[#This Row],[Total]]*-1,0) -> 0
B13: DEUDA GESTION 2023 | H13: 0 | I13: =IF(T_T134111213141516171819202122232425262728293031[[#This Row],[Total]]<0,T_T134111213141516171819202122232425262728293031[[#This Row],[Total]]*-1,0) -> 0
B14: DEUDA GESTION 2024 | I14: =IF(T_T134111213141516171819202122232425262728293031[[#This Row],[Total]]<0,T_T134111213141516171819202122232425262728293031[[#This Row],[Total]]*-1,0) -> 0
A15: 46052 | B15: Mantenimiento enero/2026 | D15: 217 | G15: =SUM(D15:F15) -> 217 | H15: =+H13+T_T134111213141516171819202122232425262728293031[[#This Row],[Total]] -> 217 | I15: =IF(T_T134111213141516171819202122232425262728293031[[#This Row],[Total]]<0,T_T134111213141516171819202122232425262728293031[[#This Row],[Total]]*-1,0) -> 0
B16: Pago mantenimiento enero/2026 | C16: 8623 | D16: -217 | G16: =SUM(D16:F16) -> -217 | H16: =H15+G16 -> 0 | I16: =IF(T_T134111213141516171819202122232425262728293031[[#This Row],[Total]]<0,T_T134111213141516171819202122232425262728293031[[#This Row],[Total]]*-1,0) -> 217
A17: 46081 | B17: Mantenimiento febrero/2026 | D17: 217 | E17: 1 | G17: =SUM(D17:F17) -> 218 | H17: =H16+G17 -> 218 | I17: =IF(T_T134111213141516171819202122232425262728293031[[#This Row],[Total]]<0,T_T134111213141516171819202122232425262728293031[[#This Row],[Total]]*-1,0) -> 0
B18: Pago mantenimiento febrero/2026 | G18: =SUM(D18:F18) -> 0 | H18: =H17+G18 -> 218 | I18: =IF(T_T134111213141516171819202122232425262728293031[[#This Row],[Total]]<0,T_T134111213141516171819202122232425262728293031[[#This Row],[Total]]*-1,0) -> 0
A19: 45747 | B19: Mantenimiento marzo/2025 | D19: 258 | G19: =SUM(D19:F19) -> 258 | H19: =H18+G19 -> 476 | I19: =IF(T_T134111213141516171819202122232425262728293031[[#This Row],[Total]]<0,T_T134111213141516171819202122232425262728293031[[#This Row],[Total]]*-1,0) -> 0
B20: Pago matenimiento marzo/2025 | G20: =SUM(D20:F20) -> 0 | H20: =H19+G20 -> 476 | I20: =IF(T_T134111213141516171819202122232425262728293031[[#This Row],[Total]]<0,T_T134111213141516171819202122232425262728293031[[#This Row],[Total]]*-1,0) -> 0
A21: 45777 | B21: Mantenimiento abril/2025 | D21: 258 | G21: =SUM(D21:F21) -> 258 | H21: =H20+G21 -> 734 | I21: =IF(T_T134111213141516171819202122232425262728293031[[#This Row],[Total]]<0,T_T134111213141516171819202122232425262728293031[[#This Row],[Total]]*-1,0) -> 0
B22: Pago mantenimiento abril/2025 | G22: =SUM(D22:F22) -> 0 | H22: =H21+G22 -> 734 | I22: =IF(T_T134111213141516171819202122232425262728293031[[#This Row],[Total]]<0,T_T134111213141516171819202122232425262728293031[[#This Row],[Total]]*-1,0) -> 0
A23: 45807 | B23: Mantenimiento mayo/2025 | D23: 258 | G23: =SUM(D23:F23) -> 258 | H23: =H22+G23 -> 992 | I23: =IF(T_T134111213141516171819202122232425262728293031[[#This Row],[Total]]<0,T_T134111213141516171819202122232425262728293031[[#This Row],[Total]]*-1,0) -> 0
B24: Pago mantenimiento mayo/2025 | G24: =SUM(D24:F24) -> 0 | H24: =H23+G24 -> 992 | I24: =IF(T_T134111213141516171819202122232425262728293031[[#This Row],[Total]]<0,T_T134111213141516171819202122232425262728293031[[#This Row],[Total]]*-1,0) -> 0
A25: 45838 | B25: Mantenimiento junio/2025 | G25: =SUM(D25:F25) -> 0 | H25: =H24+G25 -> 992 | I25: =IF(T_T134111213141516171819202122232425262728293031[[#This Row],[Total]]<0,T_T134111213141516171819202122232425262728293031[[#This Row],[Total]]*-1,0) -> 0
B26: Pago mantenimiento junio/2025 | G26: =SUM(D26:F26) -> 0 | H26: =H25+G26 -> 992 | I26: =IF(T_T134111213141516171819202122232425262728293031[[#This Row],[Total]]<0,T_T134111213141516171819202122232425262728293031[[#This Row],[Total]]*-1,0) -> 0
A27: 45868 | B27: Mantenimiento julio/2025 | G27: =SUM(D27:F27) -> 0 | H27: =H26+G27 -> 992 | I27: =IF(T_T134111213141516171819202122232425262728293031[[#This Row],[Total]]<0,T_T134111213141516171819202122232425262728293031[[#This Row],[Total]]*-1,0) -> 0
B28: Pago mantenimient julio/2025 | G28: =SUM(D28:F28) -> 0 | H28: =H27+G28 -> 992 | I28: =IF(T_T134111213141516171819202122232425262728293031[[#This Row],[Total]]<0,T_T134111213141516171819202122232425262728293031[[#This Row],[Total]]*-1,0) -> 0
A29: 45899 | B29: Mantenimiento agosto/2025 | G29: =SUM(D29:F29) -> 0 | H29: =H28+G29 -> 992 | I29: =IF(T_T134111213141516171819202122232425262728293031[[#This Row],[Total]]<0,T_T134111213141516171819202122232425262728293031[[#This Row],[Total]]*-1,0) -> 0
B30: Pago mantenimiento agosto/2025 | G30: =SUM(D30:F30) -> 0 | H30: =H29+G30 -> 992 | I30: =IF(T_T134111213141516171819202122232425262728293031[[#This Row],[Total]]<0,T_T134111213141516171819202122232425262728293031[[#This Row],[Total]]*-1,0) -> 0
A31: 45930 | B31: Mantenimiento septiembre/2025 | G31: =SUM(D31:F31) -> 0 | H31: =H30+G31 -> 992 | I31: =IF(T_T134111213141516171819202122232425262728293031[[#This Row],[Total]]<0,T_T134111213141516171819202122232425262728293031[[#This Row],[Total]]*-1,0) -> 0
B32: Pago mantenimiento septiembre/2025 | G32: =SUM(D32:F32) -> 0 | H32: =H31+G32 -> 992 | I32: =IF(T_T134111213141516171819202122232425262728293031[[#This Row],[Total]]<0,T_T134111213141516171819202122232425262728293031[[#This Row],[Total]]*-1,0) -> 0
A33: 45960 | B33: Mantenimiento octubre /2025 | G33: =SUM(D33:F33) -> 0 | H33: =H32+G33 -> 992 | I33: =IF(T_T134111213141516171819202122232425262728293031[[#This Row],[Total]]<0,T_T134111213141516171819202122232425262728293031[[#This Row],[Total]]*-1,0) -> 0
B34: Pago mantenimiento octubre/2025 | G34: =SUM(D34:F34) -> 0 | H34: =H33+G34 -> 992 | I34: =IF(T_T134111213141516171819202122232425262728293031[[#This Row],[Total]]<0,T_T134111213141516171819202122232425262728293031[[#This Row],[Total]]*-1,0) -> 0
A35: 45991 | B35: Mantenimiento noviembre/2025 | G35: =SUM(D35:F35) -> 0 | H35: =H34+G35 -> 992 | I35: =IF(T_T134111213141516171819202122232425262728293031[[#This Row],[Total]]<0,T_T134111213141516171819202122232425262728293031[[#This Row],[Total]]*-1,0) -> 0
